Workbook

Sheet README
A1: PSX Momentum Investing Case Study — Workbook
A2: A Case Study of Momentum Investing on Selected PSX Stocks: Evaluating Rebalancing Frequency for Pakistani Retail Investors
A5: Data period: Jan 2015 – Dec 2024 (120 months). Original instructions stated Jan 2014; corrected after data review — no 2014 data exists in any source.
A7: Sheet guide:
A8: Raw_Prices Monthly close prices for 8 PSX stocks (source: FYP.xlsx, "Mutual Fund" placeholder column removed — out of scope)
A9: KSE100_Benchmark Monthly KSE-100 index level (source: Karachi_100_Historical_Data_1.csv, cleaned)
A10: RiskFree Monthly 3-Month T-Bill yield (source: data_series.csv, originally bi-weekly auction data)
A11: Returns Monthly simple returns for all 8 stocks + KSE-100, computed via formula from Raw_Prices/KSE100_Benchmark
A12: Assumptions All model assumptions: costs, CGT brackets, strategy parameters (single source of truth — referenced by formula in later sheets, not retyped)
A14: Data cleaning notes (see also project report, Data & Methodology section):
A15: 1. Raw_Prices dates: the source file stored the calendar month number in the "day" field of the date (a data entry artifact). Corrected so each row maps to the correct Year-Month.
A16: 2. KSE100_Benchmark: prices were stored as text with thousand-separator commas; converted to numeric.
... A18: 4. "Mutual fund" column in original FYP.xlsx was an empty placeholder for an out-of-scope dataset; removed entirely.

Sheet Assumptions
A1: Model Assumptions
A3: Strategy Parameters
A4: Formation Period (months) | B4: 6
A5: Holding Period (months) | B5: 12
A6: Portfolio Sizes (Top N) | B6: 2 / 3 / 5 | C6: Tested as separate scenarios
A7: Rebalancing Frequencies | B7: Annual / Semi-Annual / Quarterly | C7: Tested as separate scenarios
A8: Weighting Scheme | B8: Equal-weighted
A10: Trading Costs
A11: Brokerage (per trade, one-way) | B11: 0.0025 | C11: %
A12: CDC Charges (per trade, one-way) | B12: 0.001 | C12: %
A13: Total Transaction Cost (per trade) | B13: =B11+B12 -> 0.0035 | C13: Applied on buy and sell
A15: Capital Gains Tax (CGT)
A16: CGT — Holding < 1 year | B16: 0.15 | C16: Applies to positions closed before 12 full months
A17: CGT — Holding 1–2 years | B17: 0.125
A18: CGT — Holding > 2 years | B18: 0
A19: CGT convention for exactly 12-month holds | B19: Treated as < 1 year (15%) | C19: Documented assumption — strategy holding period is exactly 12 months, so this bracket choice is applied consistently across all scenarios
A21: Benchmark & Risk-Free
A22: Benchmark | B22: KSE-100 Index
A23: Risk-Free Rate | B23: 3-Month T-Bill (monthly, see RiskFree sheet)
A25: Sample Period
A26: Start | B26: Jan-2015 | C26: Corrected from Jan-2014 — no 2014 data available in source files
A27: End | B27: Dec-2024
A28: Number of months | B28: =COUNT(Raw_Prices!A2:A121) -> 120

Sheet Raw_Prices
A1: Date | B1: OGDC | C1: MEBL | D1: EFERT | E1: MCB | F1: LUCK | G1: FFC | H1: SAZEW | I1: MARI
A2: 42005 | B2: 210.51 | C2: 29.09 | D2: 85.49 | E2: 333.1 | F2: 521.99 | G2: 132.23 | H2: 11.84 | I2: 55.37
A3: 42036 | B3: 210.8 | C3: 28.45 | D3: 85.77 | E3: 307.97 | F3: 502.95 | G3: 141.44 | H3: 15.14 | I3: 48.85
A4: 42064 | B4: 181.5 | C4: 25.65 | D4: 77.14 | E4: 246.5 | F4: 446.04 | G4: 133.25 | H4: 13.35 | I4: 47.37
A5: 42095 | B5: 182.25 | C5: 25.6 | D5: 86.6 | E5: 276.1 | F5: 488 | G5: 142.5 | H5: 13.79 | I5: 50.14
A6: 42125 | B6: 184.5 | C6: 24.37 | D6: 84.15 | E6: 268.73 | F6: 448.65 | G6: 140.4 | H6: 12.75 | I6: 43
A7: 42156 | B7: 179.25 | C7: 23.85 | D7: 88.5 | E7: 248.75 | F7: 517.85 | G7: 150 | H7: 12.95 | I7: 43.16
A8: 42186 | B8: 163 | C8: 26.93 | D8: 92.8 | E8: 280 | F8: 555.5 | G8: 146.89 | H8: 13.56 | I8: 41.05
A9: 42217 | B9: 142.36 | C9: 28.85 | D9: 95.19 | E9: 253 | F9: 528 | G9: 137.51 | H9: 13.12 | I9: 37.38
A10: 42248 | B10: 125 | C10: 29.09 | D10: 89.49 | E10: 228 | F10: 525 | G10: 124.3 | H10: 10.83 | I10: 33.54
A11: 42278 | B11: 138 | C11: 27.4 | D11: 91.5 | E11: 245 | F11: 539.84 | G11: 125.7 | H11: 11.2 | I11: 38.7
A12: 42309 | B12: 121.4 | C12: 26.76 | D12: 81.5 | E12: 204.15 | F12: 480.5 | G12: 120.25 | H12: 10.11 | I12: 47.06
A13: 42339 | B13: 117.3 | C13: 26.61 | D13: 84.24 | E13: 217.95 | F13: 493 | G13: 118 | H13: 10.77 | I13: 64
... A121: 45627 | B121: 227.26 | C121: 241.97 | D121: 204.19 | E121: 281.3 | F121: 1100.49 | G121: 366.32 | H121: 1118.38 | I121: 719.61

Sheet KSE100_Benchmark
A1: Date | B1: KSE-100
A2: 42005 | B2: 34443.87
A3: 42036 | B3: 33632.19
A4: 42064 | B4: 30233.87
A5: 42095 | B5: 33729.96
A6: 42125 | B6: 33056.79
A7: 42156 | B7: 34398.86
A8: 42186 | B8: 35741.52
A9: 42217 | B9: 34726.51
A10: 42248 | B10: 32287.41
A11: 42278 | B11: 34261.6
A12: 42309 | B12: 32255.2
A13: 42339 | B13: 32816.31
... A121: 45627 | B121: 115126.9

Sheet RiskFree
A1: Date | B1: T-Bill 3M Yield (Annualized %) | D1: Note: converted from bi-weekly auction data — last observed yield per calendar month.
A2: 42005 | B2: 0.089217
A3: 42036 | B3: 0.083232
A4: 42064 | B4: 0.081578
A5: 42095 | B5: 0.073798
A6: 42125 | B6: 0.066055
A7: 42156 | B7: 0.068637
A8: 42186 | B8: 0.06919
A9: 42217 | B9: 0.069308
A10: 42248 | B10: 0.064663
A11: 42278 | B11: 0.063038
A12: 42309 | B12: 0.063691
A13: 42339 | B13: 0.063374
... A121: 45627 | B121: 0.1185

Sheet Returns
A1: Date | B1: OGDC | C1: MEBL | D1: EFERT | E1: MCB | F1: LUCK | G1: FFC | H1: SAZEW | I1: MARI | J1: KSE-100 | L1: Row 2 (Jan-2015) is blank — no prior month to compute return from.
A2: =Raw_Prices!A2 -> 42005
A3: =Raw_Prices!A3 -> 42036 | B3: =Raw_Prices!B3/Raw_Prices!B2-1 -> 0.0013776068 | C3: =Raw_Prices!C3/Raw_Prices!C2-1 -> -0.022000688 | D3: =Raw_Prices!D3/Raw_Prices!D2-1 -> 0.0032752369 | E3: =Raw_Prices!E3/Raw_Prices!E2-1 -> -0.07544281 | F3: =Raw_Prices!F3/Raw_Prices!F2-1 -> -0.036475795 | G3: =Raw_Prices!G3/Raw_Prices!G2-1 -> 0.069651365 | H3: =Raw_Prices!H3/Raw_Prices!H2-1 -> 0.27871622 | I3: =Raw_Prices!I3/Raw_Prices!I2-1 -> -0.1177533 | J3: =KSE100_Benchmark!B3/KSE100_Benchmark!B2-1 -> -0.023565296
A4: =Raw_Prices!A4 -> 42064 | B4: =Raw_Prices!B4/Raw_Prices!B3-1 -> -0.13899431 | C4: =Raw_Prices!C4/Raw_Prices!C3-1 -> -0.098418278 | D4: =Raw_Prices!D4/Raw_Prices!D3-1 -> -0.10061793 | E4: =Raw_Prices!E4/Raw_Prices!E3-1 -> -0.19959736 | F4: =Raw_Prices!F4/Raw_Prices!F3-1 -> -0.1131524 | G4: =Raw_Prices!G4/Raw_Prices!G3-1 -> -0.057904412 | H4: =Raw_Prices!H4/Raw_Prices!H3-1 -> -0.11822985 | I4: =Raw_Prices!I4/Raw_Prices!I3-1 -> -0.030296827 | J4: =KSE100_Benchmark!B4/KSE100_Benchmark!B3-1 -> -0.10104367
A5: =Raw_Prices!A5 -> 42095 | B5: =Raw_Prices!B5/Raw_Prices!B4-1 -> 0.0041322314 | C5: =Raw_Prices!C5/Raw_Prices!C4-1 -> -0.0019493177 | D5: =Raw_Prices!D5/Raw_Prices!D4-1 -> 0.12263417 | E5: =Raw_Prices!E5/Raw_Prices!E4-1 -> 0.12008114 | F5: =Raw_Prices!F5/Raw_Prices!F4-1 -> 0.094072281 | G5: =Raw_Prices!G5/Raw_Prices!G4-1 -> 0.069418386 | H5: =Raw_Prices!H5/Raw_Prices!H4-1 -> 0.032958801 | I5: =Raw_Prices!I5/Raw_Prices!I4-1 -> 0.058475829 | J5: =KSE100_Benchmark!B5/KSE100_Benchmark!B4-1 -> 0.11563488
A6: =Raw_Prices!A6 -> 42125 | B6: =Raw_Prices!B6/Raw_Prices!B5-1 -> 0.012345679 | C6: =Raw_Prices!C6/Raw_Prices!C5-1 -> -0.048046875 | D6: =Raw_Prices!D6/Raw_Prices!D5-1 -> -0.028290993 | E6: =Raw_Prices!E6/Raw_Prices!E5-1 -> -0.026693227 | F6: =Raw_Prices!F6/Raw_Prices!F5-1 -> -0.080635246 | G6: =Raw_Prices!G6/Raw_Prices!G5-1 -> -0.014736842 | H6: =Raw_Prices!H6/Raw_Prices!H5-1 -> -0.075416969 | I6: =Raw_Prices!I6/Raw_Prices!I5-1 -> -0.14240128 | J6: =KSE100_Benchmark!B6/KSE100_Benchmark!B5-1 -> -0.019957628
A7: =Raw_Prices!A7 -> 42156 | B7: =Raw_Prices!B7/Raw_Prices!B6-1 -> -0.028455285 | C7: =Raw_Prices!C7/Raw_Prices!C6-1 -> -0.02133771 | D7: =Raw_Prices!D7/Raw_Prices!D6-1 -> 0.051693405 | E7: =Raw_Prices!E7/Raw_Prices!E6-1 -> -0.074349719 | F7: =Raw_Prices!F7/Raw_Prices!F6-1 -> 0.1542405 | G7: =Raw_Prices!G7/Raw_Prices!G6-1 -> 0.068376068 | H7: =Raw_Prices!H7/Raw_Prices!H6-1 -> 0.015686275 | I7: =Raw_Prices!I7/Raw_Prices!I6-1 -> 0.0037209302 | J7: =KSE100_Benchmark!B7/KSE100_Benchmark!B6-1 -> 0.040598921
A8: =Raw_Prices!A8 -> 42186 | B8: =Raw_Prices!B8/Raw_Prices!B7-1 -> -0.090655509 | C8: =Raw_Prices!C8/Raw_Prices!C7-1 -> 0.12914046 | D8: =Raw_Prices!D8/Raw_Prices!D7-1 -> 0.048587571 | E8: =Raw_Prices!E8/Raw_Prices!E7-1 -> 0.12562814 | F8: =Raw_Prices!F8/Raw_Prices!F7-1 -> 0.072704451 | G8: =Raw_Prices!G8/Raw_Prices!G7-1 -> -0.020733333 | H8: =Raw_Prices!H8/Raw_Prices!H7-1 -> 0.047104247 | I8: =Raw_Prices!I8/Raw_Prices!I7-1 -> -0.048887859 | J8: =KSE100_Benchmark!B8/KSE100_Benchmark!B7-1 -> 0.039032107
A9: =Raw_Prices!A9 -> 42217 | B9: =Raw_Prices!B9/Raw_Prices!B8-1 -> -0.12662577 | C9: =Raw_Prices!C9/Raw_Prices!C8-1 -> 0.071295952 | D9: =Raw_Prices!D9/Raw_Prices!D8-1 -> 0.02575431 | E9: =Raw_Prices!E9/Raw_Prices!E8-1 -> -0.096428571 | F9: =Raw_Prices!F9/Raw_Prices!F8-1 -> -0.04950495 | G9: =Raw_Prices!G9/Raw_Prices!G8-1 -> -0.063857308 | H9: =Raw_Prices!H9/Raw_Prices!H8-1 -> -0.032448378 | I9: =Raw_Prices!I9/Raw_Prices!I8-1 -> -0.089403167 | J9: =KSE100_Benchmark!B9/KSE100_Benchmark!B8-1 -> -0.028398624
A10: =Raw_Prices!A10 -> 42248 | B10: =Raw_Prices!B10/Raw_Prices!B9-1 -> -0.12194437 | C10: =Raw_Prices!C10/Raw_Prices!C9-1 -> 0.0083188908 | D10: =Raw_Prices!D10/Raw_Prices!D9-1 -> -0.05988024 | E10: =Raw_Prices!E10/Raw_Prices!E9-1 -> -0.098814229 | F10: =Raw_Prices!F10/Raw_Prices!F9-1 -> -0.0056818182 | G10: =Raw_Prices!G10/Raw_Prices!G9-1 -> -0.096065741 | H10: =Raw_Prices!H10/Raw_Prices!H9-1 -> -0.17454268 | I10: =Raw_Prices!I10/Raw_Prices!I9-1 -> -0.10272873 | J10: =KSE100_Benchmark!B10/KSE100_Benchmark!B9-1 -> -0.070237407
A11: =Raw_Prices!A11 -> 42278 | B11: =Raw_Prices!B11/Raw_Prices!B10-1 -> 0.104 | C11: =Raw_Prices!C11/Raw_Prices!C10-1 -> -0.058095565 | D11: =Raw_Prices!D11/Raw_Prices!D10-1 -> 0.02246061 | E11: =Raw_Prices!E11/Raw_Prices!E10-1 -> 0.074561404 | F11: =Raw_Prices!F11/Raw_Prices!F10-1 -> 0.028266667 | G11: =Raw_Prices!G11/Raw_Prices!G10-1 -> 0.011263073 | H11: =Raw_Prices!H11/Raw_Prices!H10-1 -> 0.034164358 | I11: =Raw_Prices!I11/Raw_Prices!I10-1 -> 0.15384615 | J11: =KSE100_Benchmark!B11/KSE100_Benchmark!B10-1 -> 0.061144266
A12: =Raw_Prices!A12 -> 42309 | B12: =Raw_Prices!B12/Raw_Prices!B11-1 -> -0.12028986 | C12: =Raw_Prices!C12/Raw_Prices!C11-1 -> -0.023357664 | D12: =Raw_Prices!D12/Raw_Prices!D11-1 -> -0.10928962 | E12: =Raw_Prices!E12/Raw_Prices!E11-1 -> -0.16673469 | F12: =Raw_Prices!F12/Raw_Prices!F11-1 -> -0.10992146 | G12: =Raw_Prices!G12/Raw_Prices!G11-1 -> -0.0433572 | H12: =Raw_Prices!H12/Raw_Prices!H11-1 -> -0.097321429 | I12: =Raw_Prices!I12/Raw_Prices!I11-1 -> 0.21602067 | J12: =KSE100_Benchmark!B12/KSE100_Benchmark!B11-1 -> -0.058561188
A13: =Raw_Prices!A13 -> 42339 | B13: =Raw_Prices!B13/Raw_Prices!B12-1 -> -0.033772652 | C13: =Raw_Prices!C13/Raw_Prices!C12-1 -> -0.0056053812 | D13: =Raw_Prices!D13/Raw_Prices!D12-1 -> 0.033619632 | E13: =Raw_Prices!E13/Raw_Prices!E12-1 -> 0.067597355 | F13: =Raw_Prices!F13/Raw_Prices!F12-1 -> 0.026014568 | G13: =Raw_Prices!G13/Raw_Prices!G12-1 -> -0.018711019 | H13: =Raw_Prices!H13/Raw_Prices!H12-1 -> 0.065281899 | I13: =Raw_Prices!I13/Raw_Prices!I12-1 -> 0.359966 | J13: =KSE100_Benchmark!B13/KSE100_Benchmark!B12-1 -> 0.017395955
A14: =Raw_Prices!A14 -> 42370 | B14: =Raw_Prices!B14/Raw_Prices!B13-1 -> -0.070758738 | C14: =Raw_Prices!C14/Raw_Prices!C13-1 -> -0.049229613 | D14: =Raw_Prices!D14/Raw_Prices!D13-1 -> -0.053181387 | E14: =Raw_Prices!E14/Raw_Prices!E13-1 -> -0.1144758 | F14: =Raw_Prices!F14/Raw_Prices!F13-1 -> -0.020263692 | G14: =Raw_Prices!G14/Raw_Prices!G13-1 -> -0.058389831 | H14: =Raw_Prices!H14/Raw_Prices!H13-1 -> -0.078922934 | I14: =Raw_Prices!I14/Raw_Prices!I13-1 -> -0.1190625 | J14: =KSE100_Benchmark!B14/KSE100_Benchmark!B13-1 -> -0.046248649
... A121: =Raw_Prices!A121 -> 45627 | B121: =Raw_Prices!B121/Raw_Prices!B120-1 -> 0.16394366 | C121: =Raw_Prices!C121/Raw_Prices!C120-1 -> 0.064165714 | D121: =Raw_Prices!D121/Raw_Prices!D120-1 -> 0.019879127 | E121: =Raw_Prices!E121/Raw_Prices!E120-1 -> 0.03701246 | F121: =Raw_Prices!F121/Raw_Prices!F120-1 -> 0.079387965 | G121: =Raw_Prices!G121/Raw_Prices!G120-1 -> 0.12752008 | H121: =Raw_Prices!H121/Raw_Prices!H120-1 -> 0.11338092 | I121: =Raw_Prices!I121/Raw_Prices!I120-1 -> 0.55685604 | J121: =KSE100_Benchmark!B121/KSE100_Benchmark!B120-1 -> 0.13585186

Sheet Momentum_Signal
A1: 6-Month Trailing Formation Return (Momentum Signal)
A2: Signal at month i = cumulative return over months (i-5) to i. First available i=7 (Jul-2015), needs 6 prior monthly returns.
A4: Month (i) | B4: Date | C4: OGDC | D4: MEBL | E4: EFERT | F4: MCB | G4: LUCK | H4: FFC | I4: SAZEW | J4: MARI
A5: 1 | B5: =Returns!A2 -> 42005
A6: 2 | B6: =Returns!A3 -> 42036
A7: 3 | B7: =Returns!A4 -> 42064
A8: 4 | B8: =Returns!A5 -> 42095
A9: 5 | B9: =Returns!A6 -> 42125
A10: 6 | B10: =Returns!A7 -> 42156
A11: 7 | B11: =Returns!A8 -> 42186 | C11: =(1+Returns!C3)*(1+Returns!C4)*(1+Returns!C5)*(1+Returns!C6)*(1+Returns!C7)*(1+Returns!C8)-1 -> -0.07425232 | D11: =(1+Returns!D3)*(1+Returns!D4)*(1+Returns!D5)*(1+Returns!D6)*(1+Returns!D7)*(1+Returns!D8)-1 -> 0.085507077 | E11: =(1+Returns!E3)*(1+Returns!E4)*(1+Returns!E5)*(1+Returns!E6)*(1+Returns!E7)*(1+Returns!E8)-1 -> -0.15941159 | F11: =(1+Returns!F3)*(1+Returns!F4)*(1+Returns!F5)*(1+Returns!F6)*(1+Returns!F7)*(1+Returns!F8)-1 -> 0.064196632 | G11: =(1+Returns!G3)*(1+Returns!G4)*(1+Returns!G5)*(1+Returns!G6)*(1+Returns!G7)*(1+Returns!G8)-1 -> 0.11086743 | H11: =(1+Returns!H3)*(1+Returns!H4)*(1+Returns!H5)*(1+Returns!H6)*(1+Returns!H7)*(1+Returns!H8)-1 -> 0.14527027 | I11: =(1+Returns!I3)*(1+Returns!I4)*(1+Returns!I5)*(1+Returns!I6)*(1+Returns!I7)*(1+Returns!I8)-1 -> -0.2586238 | J11: =(1+Returns!J3)*(1+Returns!J4)*(1+Returns!J5)*(1+Returns!J6)*(1+Returns!J7)*(1+Returns!J8)-1 -> 0.037674338
A12: 8 | B12: =Returns!A9 -> 42217 | C12: =(1+Returns!C4)*(1+Returns!C5)*(1+Returns!C6)*(1+Returns!C7)*(1+Returns!C8)*(1+Returns!C9)-1 -> 0.014059754 | D12: =(1+Returns!D4)*(1+Returns!D5)*(1+Returns!D6)*(1+Returns!D7)*(1+Returns!D8)*(1+Returns!D9)-1 -> 0.10982861 | E12: =(1+Returns!E4)*(1+Returns!E5)*(1+Returns!E6)*(1+Returns!E7)*(1+Returns!E8)*(1+Returns!E9)-1 -> -0.17849141 | F12: =(1+Returns!F4)*(1+Returns!F5)*(1+Returns!F6)*(1+Returns!F7)*(1+Returns!F8)*(1+Returns!F9)-1 -> 0.049806144 | G12: =(1+Returns!G4)*(1+Returns!G5)*(1+Returns!G6)*(1+Returns!G7)*(1+Returns!G8)*(1+Returns!G9)-1 -> -0.027785633 | H12: =(1+Returns!H4)*(1+Returns!H5)*(1+Returns!H6)*(1+Returns!H7)*(1+Returns!H8)*(1+Returns!H9)-1 -> -0.1334214 | I12: =(1+Returns!I4)*(1+Returns!I5)*(1+Returns!I6)*(1+Returns!I7)*(1+Returns!I8)*(1+Returns!I9)-1 -> -0.23480041 | J12: =(1+Returns!J4)*(1+Returns!J5)*(1+Returns!J6)*(1+Returns!J7)*(1+Returns!J8)*(1+Returns!J9)-1 -> 0.032537875
A13: 9 | B13: =Returns!A10 -> 42248 | C13: =(1+Returns!C5)*(1+Returns!C6)*(1+Returns!C7)*(1+Returns!C8)*(1+Returns!C9)*(1+Returns!C10)-1 -> 0.13411306 | D13: =(1+Returns!D5)*(1+Returns!D6)*(1+Returns!D7)*(1+Returns!D8)*(1+Returns!D9)*(1+Returns!D10)-1 -> 0.16009852 | E13: =(1+Returns!E5)*(1+Returns!E6)*(1+Returns!E7)*(1+Returns!E8)*(1+Returns!E9)*(1+Returns!E10)-1 -> -0.07505071 | F13: =(1+Returns!F5)*(1+Returns!F6)*(1+Returns!F7)*(1+Returns!F8)*(1+Returns!F9)*(1+Returns!F10)-1 -> 0.17702448 | G13: =(1+Returns!G5)*(1+Returns!G6)*(1+Returns!G7)*(1+Returns!G8)*(1+Returns!G9)*(1+Returns!G10)-1 -> -0.067166979 | H13: =(1+Returns!H5)*(1+Returns!H6)*(1+Returns!H7)*(1+Returns!H8)*(1+Returns!H9)*(1+Returns!H10)-1 -> -0.18876404 | I13: =(1+Returns!I5)*(1+Returns!I6)*(1+Returns!I7)*(1+Returns!I8)*(1+Returns!I9)*(1+Returns!I10)-1 -> -0.29195693 | J13: =(1+Returns!J5)*(1+Returns!J6)*(1+Returns!J7)*(1+Returns!J8)*(1+Returns!J9)*(1+Returns!J10)-1 -> 0.067921837
A14: 10 | B14: =Returns!A11 -> 42278 | C14: =(1+Returns!C6)*(1+Returns!C7)*(1+Returns!C8)*(1+Returns!C9)*(1+Returns!C10)*(1+Returns!C11)-1 -> 0.0703125 | D14: =(1+Returns!D6)*(1+Returns!D7)*(1+Returns!D8)*(1+Returns!D9)*(1+Returns!D10)*(1+Returns!D11)-1 -> 0.056581986 | E14: =(1+Returns!E6)*(1+Returns!E7)*(1+Returns!E8)*(1+Returns!E9)*(1+Returns!E10)*(1+Returns!E11)-1 -> -0.11264035 | F14: =(1+Returns!F6)*(1+Returns!F7)*(1+Returns!F8)*(1+Returns!F9)*(1+Returns!F10)*(1+Returns!F11)-1 -> 0.10622951 | G14: =(1+Returns!G6)*(1+Returns!G7)*(1+Returns!G8)*(1+Returns!G9)*(1+Returns!G10)*(1+Returns!G11)-1 -> -0.11789474 | H14: =(1+Returns!H6)*(1+Returns!H7)*(1+Returns!H8)*(1+Returns!H9)*(1+Returns!H10)*(1+Returns!H11)-1 -> -0.18781726 | I14: =(1+Returns!I6)*(1+Returns!I7)*(1+Returns!I8)*(1+Returns!I9)*(1+Returns!I10)*(1+Returns!I11)-1 -> -0.22816115 | J14: =(1+Returns!J6)*(1+Returns!J7)*(1+Returns!J8)*(1+Returns!J9)*(1+Returns!J10)*(1+Returns!J11)-1 -> 0.015761655
A15: 11 | B15: =Returns!A12 -> 42309 | C15: =(1+Returns!C7)*(1+Returns!C8)*(1+Returns!C9)*(1+Returns!C10)*(1+Returns!C11)*(1+Returns!C12)-1 -> 0.098071399 | D15: =(1+Returns!D7)*(1+Returns!D8)*(1+Returns!D9)*(1+Returns!D10)*(1+Returns!D11)*(1+Returns!D12)-1 -> -0.031491384 | E15: =(1+Returns!E7)*(1+Returns!E8)*(1+Returns!E9)*(1+Returns!E10)*(1+Returns!E11)*(1+Returns!E12)-1 -> -0.24031556 | F15: =(1+Returns!F7)*(1+Returns!F8)*(1+Returns!F9)*(1+Returns!F10)*(1+Returns!F11)*(1+Returns!F12)-1 -> 0.07099075 | G15: =(1+Returns!G7)*(1+Returns!G8)*(1+Returns!G9)*(1+Returns!G10)*(1+Returns!G11)*(1+Returns!G12)-1 -> -0.14351852 | H15: =(1+Returns!H7)*(1+Returns!H8)*(1+Returns!H9)*(1+Returns!H10)*(1+Returns!H11)*(1+Returns!H12)-1 -> -0.20705882 | I15: =(1+Returns!I7)*(1+Returns!I8)*(1+Returns!I9)*(1+Returns!I10)*(1+Returns!I11)*(1+Returns!I12)-1 -> 0.094418605 | J15: =(1+Returns!J7)*(1+Returns!J8)*(1+Returns!J9)*(1+Returns!J10)*(1+Returns!J11)*(1+Returns!J12)-1 -> -0.024248876
A16: 12 | B16: =Returns!A13 -> 42339 | C16: =(1+Returns!C8)*(1+Returns!C9)*(1+Returns!C10)*(1+Returns!C11)*(1+Returns!C12)*(1+Returns!C13)-1 -> 0.11572327 | D16: =(1+Returns!D8)*(1+Returns!D9)*(1+Returns!D10)*(1+Returns!D11)*(1+Returns!D12)*(1+Returns!D13)-1 -> -0.048135593 | E16: =(1+Returns!E8)*(1+Returns!E9)*(1+Returns!E10)*(1+Returns!E11)*(1+Returns!E12)*(1+Returns!E13)-1 -> -0.1238191 | F16: =(1+Returns!F8)*(1+Returns!F9)*(1+Returns!F10)*(1+Returns!F11)*(1+Returns!F12)*(1+Returns!F13)-1 -> -0.047986869 | G16: =(1+Returns!G8)*(1+Returns!G9)*(1+Returns!G10)*(1+Returns!G11)*(1+Returns!G12)*(1+Returns!G13)-1 -> -0.21333333 | H16: =(1+Returns!H8)*(1+Returns!H9)*(1+Returns!H10)*(1+Returns!H11)*(1+Returns!H12)*(1+Returns!H13)-1 -> -0.16833977 | I16: =(1+Returns!I8)*(1+Returns!I9)*(1+Returns!I10)*(1+Returns!I11)*(1+Returns!I12)*(1+Returns!I13)-1 -> 0.48285449 | J16: =(1+Returns!J8)*(1+Returns!J9)*(1+Returns!J10)*(1+Returns!J11)*(1+Returns!J12)*(1+Returns!J13)-1 -> -0.046005885
A17: 13 | B17: =Returns!A14 -> 42370 | C17: =(1+Returns!C9)*(1+Returns!C10)*(1+Returns!C11)*(1+Returns!C12)*(1+Returns!C13)*(1+Returns!C14)-1 -> -0.060527293 | D17: =(1+Returns!D9)*(1+Returns!D10)*(1+Returns!D11)*(1+Returns!D12)*(1+Returns!D13)*(1+Returns!D14)-1 -> -0.14051724 | E17: =(1+Returns!E9)*(1+Returns!E10)*(1+Returns!E11)*(1+Returns!E12)*(1+Returns!E13)*(1+Returns!E14)-1 -> -0.31071429 | F17: =(1+Returns!F9)*(1+Returns!F10)*(1+Returns!F11)*(1+Returns!F12)*(1+Returns!F13)*(1+Returns!F14)-1 -> -0.13049505 | G17: =(1+Returns!G9)*(1+Returns!G10)*(1+Returns!G11)*(1+Returns!G12)*(1+Returns!G13)*(1+Returns!G14)-1 -> -0.24358363 | H17: =(1+Returns!H9)*(1+Returns!H10)*(1+Returns!H11)*(1+Returns!H12)*(1+Returns!H13)*(1+Returns!H14)-1 -> -0.26843658 | I17: =(1+Returns!I9)*(1+Returns!I10)*(1+Returns!I11)*(1+Returns!I12)*(1+Returns!I13)*(1+Returns!I14)-1 -> 0.37344702 | J17: =(1+Returns!J9)*(1+Returns!J10)*(1+Returns!J11)*(1+Returns!J12)*(1+Returns!J13)*(1+Returns!J14)-1 -> -0.12430697
A18: 14 | B18: =Returns!A15 -> 42401 | C18: =(1+Returns!C10)*(1+Returns!C11)*(1+Returns!C12)*(1+Returns!C13)*(1+Returns!C14)*(1+Returns!C15)-1 -> -0.15632582 | D18: =(1+Returns!D10)*(1+Returns!D11)*(1+Returns!D12)*(1+Returns!D13)*(1+Returns!D14)*(1+Returns!D15)-1 -> -0.2081101 | E18: =(1+Returns!E10)*(1+Returns!E11)*(1+Returns!E12)*(1+Returns!E13)*(1+Returns!E14)*(1+Returns!E15)-1 -> -0.22687747 | F18: =(1+Returns!F10)*(1+Returns!F11)*(1+Returns!F12)*(1+Returns!F13)*(1+Returns!F14)*(1+Returns!F15)-1 -> -0.070833333 | G18: =(1+Returns!G10)*(1+Returns!G11)*(1+Returns!G12)*(1+Returns!G13)*(1+Returns!G14)*(1+Returns!G15)-1 -> -0.21023926 | H18: =(1+Returns!H10)*(1+Returns!H11)*(1+Returns!H12)*(1+Returns!H13)*(1+Returns!H14)*(1+Returns!H15)-1 -> -0.27057927 | I18: =(1+Returns!I10)*(1+Returns!I11)*(1+Returns!I12)*(1+Returns!I13)*(1+Returns!I14)*(1+Returns!I15)-1 -> 0.42536116 | J18: =(1+Returns!J10)*(1+Returns!J11)*(1+Returns!J12)*(1+Returns!J13)*(1+Returns!J14)*(1+Returns!J15)-1 -> -0.096669662
A19: 15 | B19: =Returns!A16 -> 42430 | C19: =(1+Returns!C11)*(1+Returns!C12)*(1+Returns!C13)*(1+Returns!C14)*(1+Returns!C15)*(1+Returns!C16)-1 -> -0.16019251 | D19: =(1+Returns!D11)*(1+Returns!D12)*(1+Returns!D13)*(1+Returns!D14)*(1+Returns!D15)*(1+Returns!D16)-1 -> -0.22449436 | E19: =(1+Returns!E11)*(1+Returns!E12)*(1+Returns!E13)*(1+Returns!E14)*(1+Returns!E15)*(1+Returns!E16)-1 -> -0.096447368 | F19: =(1+Returns!F11)*(1+Returns!F12)*(1+Returns!F13)*(1+Returns!F14)*(1+Returns!F15)*(1+Returns!F16)-1 -> 0.022857143 | G19: =(1+Returns!G11)*(1+Returns!G12)*(1+Returns!G13)*(1+Returns!G14)*(1+Returns!G15)*(1+Returns!G16)-1 -> -0.14432824 | H19: =(1+Returns!H11)*(1+Returns!H12)*(1+Returns!H13)*(1+Returns!H14)*(1+Returns!H15)*(1+Returns!H16)-1 -> -0.046168052 | I19: =(1+Returns!I11)*(1+Returns!I12)*(1+Returns!I13)*(1+Returns!I14)*(1+Returns!I15)*(1+Returns!I16)-1 -> 0.92397138 | J19: =(1+Returns!J11)*(1+Returns!J12)*(1+Returns!J13)*(1+Returns!J14)*(1+Returns!J15)*(1+Returns!J16)-1 -> 0.026375296
A20: 16 | B20: =Returns!A17 -> 42461 | C20: =(1+Returns!C12)*(1+Returns!C13)*(1+Returns!C14)*(1+Returns!C15)*(1+Returns!C16)*(1+Returns!C17)-1 -> -0.10948905 | D20: =(1+Returns!D12)*(1+Returns!D13)*(1+Returns!D14)*(1+Returns!D15)*(1+Returns!D16)*(1+Returns!D17)-1 -> -0.23715847 | E20: =(1+Returns!E12)*(1+Returns!E13)*(1+Returns!E14)*(1+Returns!E15)*(1+Returns!E16)*(1+Returns!E17)-1 -> -0.13538776 | F20: =(1+Returns!F12)*(1+Returns!F13)*(1+Returns!F14)*(1+Returns!F15)*(1+Returns!F16)*(1+Returns!F17)-1 -> 0.023451393 | G20: =(1+Returns!G12)*(1+Returns!G13)*(1+Returns!G14)*(1+Returns!G15)*(1+Returns!G16)*(1+Returns!G17)-1 -> -0.14868735 | H20: =(1+Returns!H12)*(1+Returns!H13)*(1+Returns!H14)*(1+Returns!H15)*(1+Returns!H16)*(1+Returns!H17)-1 -> 0.021428571 | I20: =(1+Returns!I12)*(1+Returns!I13)*(1+Returns!I14)*(1+Returns!I15)*(1+Returns!I16)*(1+Returns!I17)-1 -> 0.79844961 | J20: =(1+Returns!J12)*(1+Returns!J13)*(1+Returns!J14)*(1+Returns!J15)*(1+Returns!J16)*(1+Returns!J17)-1 -> 0.013358687
A21: 17 | B21: =Returns!A18 -> 42491 | C21: =(1+Returns!C13)*(1+Returns!C14)*(1+Returns!C15)*(1+Returns!C16)*(1+Returns!C17)*(1+Returns!C18)-1 -> -0.097907324 | D21: =(1+Returns!D13)*(1+Returns!D14)*(1+Returns!D15)*(1+Returns!D16)*(1+Returns!D17)*(1+Returns!D18)-1 -> -0.1403681 | E21: =(1+Returns!E13)*(1+Returns!E14)*(1+Returns!E15)*(1+Returns!E16)*(1+Returns!E17)*(1+Returns!E18)-1 -> 0.013960323 | F21: =(1+Returns!F13)*(1+Returns!F14)*(1+Returns!F15)*(1+Returns!F16)*(1+Returns!F17)*(1+Returns!F18)-1 -> 0.23621228 | G21: =(1+Returns!G13)*(1+Returns!G14)*(1+Returns!G15)*(1+Returns!G16)*(1+Returns!G17)*(1+Returns!G18)-1 -> -0.054054054 | H21: =(1+Returns!H13)*(1+Returns!H14)*(1+Returns!H15)*(1+Returns!H16)*(1+Returns!H17)*(1+Returns!H18)-1 -> 0.043521266 | I21: =(1+Returns!I13)*(1+Returns!I14)*(1+Returns!I15)*(1+Returns!I16)*(1+Returns!I17)*(1+Returns!I18)-1 -> 0.71716957 | J21: =(1+Returns!J13)*(1+Returns!J14)*(1+Returns!J15)*(1+Returns!J16)*(1+Returns!J17)*(1+Returns!J18)-1 -> 0.11800764
A22: 18 | B22: =Returns!A19 -> 42522 | C22: =(1+Returns!C14)*(1+Returns!C15)*(1+Returns!C16)*(1+Returns!C17)*(1+Returns!C18)*(1+Returns!C19)-1 -> -0.07102593 | D22: =(1+Returns!D14)*(1+Returns!D15)*(1+Returns!D16)*(1+Returns!D17)*(1+Returns!D18)*(1+Returns!D19)-1 -> -0.23433048 | E22: =(1+Returns!E14)*(1+Returns!E15)*(1+Returns!E16)*(1+Returns!E17)*(1+Returns!E18)*(1+Returns!E19)-1 -> 0.0012388162 | F22: =(1+Returns!F14)*(1+Returns!F15)*(1+Returns!F16)*(1+Returns!F17)*(1+Returns!F18)*(1+Returns!F19)-1 -> 0.31237323 | G22: =(1+Returns!G14)*(1+Returns!G15)*(1+Returns!G16)*(1+Returns!G17)*(1+Returns!G18)*(1+Returns!G19)-1 -> -0.025423729 | H22: =(1+Returns!H14)*(1+Returns!H15)*(1+Returns!H16)*(1+Returns!H17)*(1+Returns!H18)*(1+Returns!H19)-1 -> -0.024141133 | I22: =(1+Returns!I14)*(1+Returns!I15)*(1+Returns!I16)*(1+Returns!I17)*(1+Returns!I18)*(1+Returns!I19)-1 -> 0.3 | J22: =(1+Returns!J14)*(1+Returns!J15)*(1+Returns!J16)*(1+Returns!J17)*(1+Returns!J18)*(1+Returns!J19)-1 -> 0.15136467
... A124: 120 | B124: =Returns!A121 -> 45627 | C124: =(1+Returns!C116)*(1+Returns!C117)*(1+Returns!C118)*(1+Returns!C119)*(1+Returns!C120)*(1+Returns!C121)-1 -> 0.012426778 | D124: =(1+Returns!D116)*(1+Returns!D117)*(1+Returns!D118)*(1+Returns!D119)*(1+Returns!D120)*(1+Returns!D121)-1 -> 0.22991206 | E124: =(1+Returns!E116)*(1+Returns!E117)*(1+Returns!E118)*(1+Returns!E119)*(1+Returns!E120)*(1+Returns!E121)-1 -> 0.23920705 | F124: =(1+Returns!F116)*(1+Returns!F117)*(1+Returns!F118)*(1+Returns!F119)*(1+Returns!F120)*(1+Returns!F121)-1 -> 0.21852889 | G124: =(1+Returns!G116)*(1+Returns!G117)*(1+Returns!G118)*(1+Returns!G119)*(1+Returns!G120)*(1+Returns!G121)-1 -> 1.2446078 | H124: =(1+Returns!H116)*(1+Returns!H117)*(1+Returns!H118)*(1+Returns!H119)*(1+Returns!H120)*(1+Returns!H121)-1 -> 0.34021187 | I124: =(1+Returns!I116)*(1+Returns!I117)*(1+Returns!I118)*(1+Returns!I119)*(1+Returns!I120)*(1+Returns!I121)-1 -> 1.3960643 | J124: =(1+Returns!J116)*(1+Returns!J117)*(1+Returns!J118)*(1+Returns!J119)*(1+Returns!J120)*(1+Returns!J121)-1 -> 0.46761373

Sheet Rankings
A1: Momentum Rank (1 = strongest 6-month trailing return)
A4: Month (i) | B4: Date | C4: OGDC | D4: MEBL | E4: EFERT | F4: MCB | G4: LUCK | H4: FFC | I4: SAZEW | J4: MARI
A5: 1 | B5: =Momentum_Signal!B5 -> 42005
A6: 2 | B6: =Momentum_Signal!B6 -> 42036
A7: 3 | B7: =Momentum_Signal!B7 -> 42064
A8: 4 | B8: =Momentum_Signal!B8 -> 42095
A9: 5 | B9: =Momentum_Signal!B9 -> 42125
A10: 6 | B10: =Momentum_Signal!B10 -> 42156
A11: 7 | B11: =Momentum_Signal!B11 -> 42186 | C11: =RANK(Momentum_Signal!C11,Momentum_Signal!$C11:$J11,0) -> 6 | D11: =RANK(Momentum_Signal!D11,Momentum_Signal!$C11:$J11,0) -> 3 | E11: =RANK(Momentum_Signal!E11,Momentum_Signal!$C11:$J11,0) -> 7 | F11: =RANK(Momentum_Signal!F11,Momentum_Signal!$C11:$J11,0) -> 4 | G11: =RANK(Momentum_Signal!G11,Momentum_Signal!$C11:$J11,0) -> 2 | H11: =RANK(Momentum_Signal!H11,Momentum_Signal!$C11:$J11,0) -> 1 | I11: =RANK(Momentum_Signal!I11,Momentum_Signal!$C11:$J11,0) -> 8 | J11: =RANK(Momentum_Signal!J11,Momentum_Signal!$C11:$J11,0) -> 5
A12: 8 | B12: =Momentum_Signal!B12 -> 42217 | C12: =RANK(Momentum_Signal!C12,Momentum_Signal!$C12:$J12,0) -> 4 | D12: =RANK(Momentum_Signal!D12,Momentum_Signal!$C12:$J12,0) -> 1 | E12: =RANK(Momentum_Signal!E12,Momentum_Signal!$C12:$J12,0) -> 7 | F12: =RANK(Momentum_Signal!F12,Momentum_Signal!$C12:$J12,0) -> 2 | G12: =RANK(Momentum_Signal!G12,Momentum_Signal!$C12:$J12,0) -> 5 | H12: =RANK(Momentum_Signal!H12,Momentum_Signal!$C12:$J12,0) -> 6 | I12: =RANK(Momentum_Signal!I12,Momentum_Signal!$C12:$J12,0) -> 8 | J12: =RANK(Momentum_Signal!J12,Momentum_Signal!$C12:$J12,0) -> 3
A13: 9 | B13: =Momentum_Signal!B13 -> 42248 | C13: =RANK(Momentum_Signal!C13,Momentum_Signal!$C13:$J13,0) -> 3 | D13: =RANK(Momentum_Signal!D13,Momentum_Signal!$C13:$J13,0) -> 2 | E13: =RANK(Momentum_Signal!E13,Momentum_Signal!$C13:$J13,0) -> 6 | F13: =RANK(Momentum_Signal!F13,Momentum_Signal!$C13:$J13,0) -> 1 | G13: =RANK(Momentum_Signal!G13,Momentum_Signal!$C13:$J13,0) -> 5 | H13: =RANK(Momentum_Signal!H13,Momentum_Signal!$C13:$J13,0) -> 7 | I13: =RANK(Momentum_Signal!I13,Momentum_Signal!$C13:$J13,0) -> 8 | J13: =RANK(Momentum_Signal!J13,Momentum_Signal!$C13:$J13,0) -> 4
A14: 10 | B14: =Momentum_Signal!B14 -> 42278 | C14: =RANK(Momentum_Signal!C14,Momentum_Signal!$C14:$J14,0) -> 2 | D14: =RANK(Momentum_Signal!D14,Momentum_Signal!$C14:$J14,0) -> 3 | E14: =RANK(Momentum_Signal!E14,Momentum_Signal!$C14:$J14,0) -> 5 | F14: =RANK(Momentum_Signal!F14,Momentum_Signal!$C14:$J14,0) -> 1 | G14: =RANK(Momentum_Signal!G14,Momentum_Signal!$C14:$J14,0) -> 6 | H14: =RANK(Momentum_Signal!H14,Momentum_Signal!$C14:$J14,0) -> 7 | I14: =RANK(Momentum_Signal!I14,Momentum_Signal!$C14:$J14,0) -> 8 | J14: =RANK(Momentum_Signal!J14,Momentum_Signal!$C14:$J14,0) -> 4
A15: 11 | B15: =Momentum_Signal!B15 -> 42309 | C15: =RANK(Momentum_Signal!C15,Momentum_Signal!$C15:$J15,0) -> 1 | D15: =RANK(Momentum_Signal!D15,Momentum_Signal!$C15:$J15,0) -> 5 | E15: =RANK(Momentum_Signal!E15,Momentum_Signal!$C15:$J15,0) -> 8 | F15: =RANK(Momentum_Signal!F15,Momentum_Signal!$C15:$J15,0) -> 3 | G15: =RANK(Momentum_Signal!G15,Momentum_Signal!$C15:$J15,0) -> 6 | H15: =RANK(Momentum_Signal!H15,Momentum_Signal!$C15:$J15,0) -> 7 | I15: =RANK(Momentum_Signal!I15,Momentum_Signal!$C15:$J15,0) -> 2 | J15: =RANK(Momentum_Signal!J15,Momentum_Signal!$C15:$J15,0) -> 4
A16: 12 | B16: =Momentum_Signal!B16 -> 42339 | C16: =RANK(Momentum_Signal!C16,Momentum_Signal!$C16:$J16,0) -> 2 | D16: =RANK(Momentum_Signal!D16,Momentum_Signal!$C16:$J16,0) -> 5 | E16: =RANK(Momentum_Signal!E16,Momentum_Signal!$C16:$J16,0) -> 6 | F16: =RANK(Momentum_Signal!F16,Momentum_Signal!$C16:$J16,0) -> 4 | G16: =RANK(Momentum_Signal!G16,Momentum_Signal!$C16:$J16,0) -> 8 | H16: =RANK(Momentum_Signal!H16,Momentum_Signal!$C16:$J16,0) -> 7 | I16: =RANK(Momentum_Signal!I16,Momentum_Signal!$C16:$J16,0) -> 1 | J16: =RANK(Momentum_Signal!J16,Momentum_Signal!$C16:$J16,0) -> 3
A17: 13 | B17: =Momentum_Signal!B17 -> 42370 | C17: =RANK(Momentum_Signal!C17,Momentum_Signal!$C17:$J17,0) -> 2 | D17: =RANK(Momentum_Signal!D17,Momentum_Signal!$C17:$J17,0) -> 5 | E17: =RANK(Momentum_Signal!E17,Momentum_Signal!$C17:$J17,0) -> 8 | F17: =RANK(Momentum_Signal!F17,Momentum_Signal!$C17:$J17,0) -> 4 | G17: =RANK(Momentum_Signal!G17,Momentum_Signal!$C17:$J17,0) -> 6 | H17: =RANK(Momentum_Signal!H17,Momentum_Signal!$C17:$J17,0) -> 7 | I17: =RANK(Momentum_Signal!I17,Momentum_Signal!$C17:$J17,0) -> 1 | J17: =RANK(Momentum_Signal!J17,Momentum_Signal!$C17:$J17,0) -> 3
A18: 14 | B18: =Momentum_Signal!B18 -> 42401 | C18: =RANK(Momentum_Signal!C18,Momentum_Signal!$C18:$J18,0) -> 4 | D18: =RANK(Momentum_Signal!D18,Momentum_Signal!$C18:$J18,0) -> 5 | E18: =RANK(Momentum_Signal!E18,Momentum_Signal!$C18:$J18,0) -> 7 | F18: =RANK(Momentum_Signal!F18,Momentum_Signal!$C18:$J18,0) -> 2 | G18: =RANK(Momentum_Signal!G18,Momentum_Signal!$C18:$J18,0) -> 6 | H18: =RANK(Momentum_Signal!H18,Momentum_Signal!$C18:$J18,0) -> 8 | I18: =RANK(Momentum_Signal!I18,Momentum_Signal!$C18:$J18,0) -> 1 | J18: =RANK(Momentum_Signal!J18,Momentum_Signal!$C18:$J18,0) -> 3
A19: 15 | B19: =Momentum_Signal!B19 -> 42430 | C19: =RANK(Momentum_Signal!C19,Momentum_Signal!$C19:$J19,0) -> 7 | D19: =RANK(Momentum_Signal!D19,Momentum_Signal!$C19:$J19,0) -> 8 | E19: =RANK(Momentum_Signal!E19,Momentum_Signal!$C19:$J19,0) -> 5 | F19: =RANK(Momentum_Signal!F19,Momentum_Signal!$C19:$J19,0) -> 3 | G19: =RANK(Momentum_Signal!G19,Momentum_Signal!$C19:$J19,0) -> 6 | H19: =RANK(Momentum_Signal!H19,Momentum_Signal!$C19:$J19,0) -> 4 | I19: =RANK(Momentum_Signal!I19,Momentum_Signal!$C19:$J19,0) -> 1 | J19: =RANK(Momentum_Signal!J19,Momentum_Signal!$C19:$J19,0) -> 2
A20: 16 | B20: =Momentum_Signal!B20 -> 42461 | C20: =RANK(Momentum_Signal!C20,Momentum_Signal!$C20:$J20,0) -> 5 | D20: =RANK(Momentum_Signal!D20,Momentum_Signal!$C20:$J20,0) -> 8 | E20: =RANK(Momentum_Signal!E20,Momentum_Signal!$C20:$J20,0) -> 6 | F20: =RANK(Momentum_Signal!F20,Momentum_Signal!$C20:$J20,0) -> 2 | G20: =RANK(Momentum_Signal!G20,Momentum_Signal!$C20:$J20,0) -> 7 | H20: =RANK(Momentum_Signal!H20,Momentum_Signal!$C20:$J20,0) -> 3 | I20: =RANK(Momentum_Signal!I20,Momentum_Signal!$C20:$J20,0) -> 1 | J20: =RANK(Momentum_Signal!J20,Momentum_Signal!$C20:$J20,0) -> 4
A21: 17 | B21: =Momentum_Signal!B21 -> 42491 | C21: =RANK(Momentum_Signal!C21,Momentum_Signal!$C21:$J21,0) -> 7 | D21: =RANK(Momentum_Signal!D21,Momentum_Signal!$C21:$J21,0) -> 8 | E21: =RANK(Momentum_Signal!E21,Momentum_Signal!$C21:$J21,0) -> 5 | F21: =RANK(Momentum_Signal!F21,Momentum_Signal!$C21:$J21,0) -> 2 | G21: =RANK(Momentum_Signal!G21,Momentum_Signal!$C21:$J21,0) -> 6 | H21: =RANK(Momentum_Signal!H21,Momentum_Signal!$C21:$J21,0) -> 4 | I21: =RANK(Momentum_Signal!I21,Momentum_Signal!$C21:$J21,0) -> 1 | J21: =RANK(Momentum_Signal!J21,Momentum_Signal!$C21:$J21,0) -> 3
A22: 18 | B22: =Momentum_Signal!B22 -> 42522 | C22: =RANK(Momentum_Signal!C22,Momentum_Signal!$C22:$J22,0) -> 7 | D22: =RANK(Momentum_Signal!D22,Momentum_Signal!$C22:$J22,0) -> 8 | E22: =RANK(Momentum_Signal!E22,Momentum_Signal!$C22:$J22,0) -> 4 | F22: =RANK(Momentum_Signal!F22,Momentum_Signal!$C22:$J22,0) -> 1 | G22: =RANK(Momentum_Signal!G22,Momentum_Signal!$C22:$J22,0) -> 6 | H22: =RANK(Momentum_Signal!H22,Momentum_Signal!$C22:$J22,0) -> 5 | I22: =RANK(Momentum_Signal!I22,Momentum_Signal!$C22:$J22,0) -> 2 | J22: =RANK(Momentum_Signal!J22,Momentum_Signal!$C22:$J22,0) -> 3
... A124: 120 | B124: =Momentum_Signal!B124 -> 45627 | C124: =RANK(Momentum_Signal!C124,Momentum_Signal!$C124:$J124,0) -> 8 | D124: =RANK(Momentum_Signal!D124,Momentum_Signal!$C124:$J124,0) -> 6 | E124: =RANK(Momentum_Signal!E124,Momentum_Signal!$C124:$J124,0) -> 5 | F124: =RANK(Momentum_Signal!F124,Momentum_Signal!$C124:$J124,0) -> 7 | G124: =RANK(Momentum_Signal!G124,Momentum_Signal!$C124:$J124,0) -> 2 | H124: =RANK(Momentum_Signal!H124,Momentum_Signal!$C124:$J124,0) -> 4 | I124: =RANK(Momentum_Signal!I124,Momentum_Signal!$C124:$J124,0) -> 1 | J124: =RANK(Momentum_Signal!J124,Momentum_Signal!$C124:$J124,0) -> 3

Sheet S_Top2_Annual
A1: Scenario: Top 2 stocks, Annual rebalancing (hold 12 months)
A2: Holdings flag in each row = lookup of Rankings at the governing formation-month (decision row), held constant until next rebalance. Decision i -> holding starts month i+1.
A4: Month (j) | B4: Date | C4: OGDC | D4: MEBL | E4: EFERT | F4: MCB | G4: LUCK | H4: FFC | I4: SAZEW | J4: MARI | K4: Held N | L4: Gross Return | M4: Txn Cost | N4: CGT | O4: Net Return | P4: Growth of Rs.1 | Q4: Running Max | R4: Drawdown | S4: Excess Return
A5: 8 | B5: =Returns!A9 -> 42217 | C5: =IF(Rankings!C11<=2,1,0) -> 0 | D5: =IF(Rankings!D11<=2,1,0) -> 0 | E5: =IF(Rankings!E11<=2,1,0) -> 0 | F5: =IF(Rankings!F11<=2,1,0) -> 0 | G5: =IF(Rankings!G11<=2,1,0) -> 1 | H5: =IF(Rankings!H11<=2,1,0) -> 1 | I5: =IF(Rankings!I11<=2,1,0) -> 0 | J5: =IF(Rankings!J11<=2,1,0) -> 0 | K5: =SUM(C5:J5) -> 2 | L5: =SUMPRODUCT(C5:J5,Returns!B9:I9)/K5 -> -0.056681129 | M5: =-2*Assumptions!$B$13 -> -0.007 | N5: 0 | O5: =L5+M5+N5 -> -0.063681129 | P5: =1*(1+O5) -> 0.93631887 | Q5: =MAX($P$5:P5) -> 0.93631887 | R5: =P5/Q5-1 -> 0 | S5: =O5-Benchmark_RF!D5 -> -0.06928106
A6: 9 | B6: =Returns!A10 -> 42248 | C6: =IF(Rankings!C11<=2,1,0) -> 0 | D6: =IF(Rankings!D11<=2,1,0) -> 0 | E6: =IF(Rankings!E11<=2,1,0) -> 0 | F6: =IF(Rankings!F11<=2,1,0) -> 0 | G6: =IF(Rankings!G11<=2,1,0) -> 1 | H6: =IF(Rankings!H11<=2,1,0) -> 1 | I6: =IF(Rankings!I11<=2,1,0) -> 0 | J6: =IF(Rankings!J11<=2,1,0) -> 0 | K6: =SUM(C6:J6) -> 2 | L6: =SUMPRODUCT(C6:J6,Returns!B10:I10)/K6 -> -0.050873779 | M6: 0 | N6: 0 | O6: =L6+M6+N6 -> -0.050873779 | P6: =P5*(1+O6) -> 0.88868479 | Q6: =MAX($P$5:P6) -> 0.93631887 | R6: =P6/Q6-1 -> -0.050873779 | S6: =O6-Benchmark_RF!D6 -> -0.056108962
A7: 10 | B7: =Returns!A11 -> 42278 | C7: =IF(Rankings!C11<=2,1,0) -> 0 | D7: =IF(Rankings!D11<=2,1,0) -> 0 | E7: =IF(Rankings!E11<=2,1,0) -> 0 | F7: =IF(Rankings!F11<=2,1,0) -> 0 | G7: =IF(Rankings!G11<=2,1,0) -> 1 | H7: =IF(Rankings!H11<=2,1,0) -> 1 | I7: =IF(Rankings!I11<=2,1,0) -> 0 | J7: =IF(Rankings!J11<=2,1,0) -> 0 | K7: =SUM(C7:J7) -> 2 | L7: =SUMPRODUCT(C7:J7,Returns!B11:I11)/K7 -> 0.01976487 | M7: 0 | N7: 0 | O7: =L7+M7+N7 -> 0.01976487 | P7: =P6*(1+O7) -> 0.90624953 | Q7: =MAX($P$5:P7) -> 0.93631887 | R7: =P7/Q7-1 -> -0.032114423 | S7: =O7-Benchmark_RF!D7 -> 0.014657635
A8: 11 | B8: =Returns!A12 -> 42309 | C8: =IF(Rankings!C11<=2,1,0) -> 0 | D8: =IF(Rankings!D11<=2,1,0) -> 0 | E8: =IF(Rankings!E11<=2,1,0) -> 0 | F8: =IF(Rankings!F11<=2,1,0) -> 0 | G8: =IF(Rankings!G11<=2,1,0) -> 1 | H8: =IF(Rankings!H11<=2,1,0) -> 1 | I8: =IF(Rankings!I11<=2,1,0) -> 0 | J8: =IF(Rankings!J11<=2,1,0) -> 0 | K8: =SUM(C8:J8) -> 2 | L8: =SUMPRODUCT(C8:J8,Returns!B12:I12)/K8 -> -0.076639329 | M8: 0 | N8: 0 | O8: =L8+M8+N8 -> -0.076639329 | P8: =P7*(1+O8) -> 0.83679517 | Q8: =MAX($P$5:P8) -> 0.93631887 | R8: =P8/Q8-1 -> -0.10629252 | S8: =O8-Benchmark_RF!D8 -> -0.081798001
A9: 12 | B9: =Returns!A13 -> 42339 | C9: =IF(Rankings!C11<=2,1,0) -> 0 | D9: =IF(Rankings!D11<=2,1,0) -> 0 | E9: =IF(Rankings!E11<=2,1,0) -> 0 | F9: =IF(Rankings!F11<=2,1,0) -> 0 | G9: =IF(Rankings!G11<=2,1,0) -> 1 | H9: =IF(Rankings!H11<=2,1,0) -> 1 | I9: =IF(Rankings!I11<=2,1,0) -> 0 | J9: =IF(Rankings!J11<=2,1,0) -> 0 | K9: =SUM(C9:J9) -> 2 | L9: =SUMPRODUCT(C9:J9,Returns!B13:I13)/K9 -> 0.0036517747 | M9: 0 | N9: 0 | O9: =L9+M9+N9 -> 0.0036517747 | P9: =P8*(1+O9) -> 0.83985096 | Q9: =MAX($P$5:P9) -> 0.93631887 | R9: =P9/Q9-1 -> -0.10302891 | S9: =O9-Benchmark_RF!D9 -> -0.0014819305
A10: 13 | B10: =Returns!A14 -> 42370 | C10: =IF(Rankings!C11<=2,1,0) -> 0 | D10: =IF(Rankings!D11<=2,1,0) -> 0 | E10: =IF(Rankings!E11<=2,1,0) -> 0 | F10: =IF(Rankings!F11<=2,1,0) -> 0 | G10: =IF(Rankings!G11<=2,1,0) -> 1 | H10: =IF(Rankings!H11<=2,1,0) -> 1 | I10: =IF(Rankings!I11<=2,1,0) -> 0 | J10: =IF(Rankings!J11<=2,1,0) -> 0 | K10: =SUM(C10:J10) -> 2 | L10: =SUMPRODUCT(C10:J10,Returns!B14:I14)/K10 -> -0.039326761 | M10: 0 | N10: 0 | O10: =L10+M10+N10 -> -0.039326761 | P10: =P9*(1+O10) -> 0.80682234 | Q10: =MAX($P$5:P10) -> 0.93631887 | R10: =P10/Q10-1 -> -0.13830387 | S10: =O10-Benchmark_RF!D10 -> -0.044321964
A11: 14 | B11: =Returns!A15 -> 42401 | C11: =IF(Rankings!C11<=2,1,0) -> 0 | D11: =IF(Rankings!D11<=2,1,0) -> 0 | E11: =IF(Rankings!E11<=2,1,0) -> 0 | F11: =IF(Rankings!F11<=2,1,0) -> 0 | G11: =IF(Rankings!G11<=2,1,0) -> 1 | H11: =IF(Rankings!H11<=2,1,0) -> 1 | I11: =IF(Rankings!I11<=2,1,0) -> 0 | J11: =IF(Rankings!J11<=2,1,0) -> 0 | K11: =SUM(C11:J11) -> 2 | L11: =SUMPRODUCT(C11:J11,Returns!B15:I15)/K11 -> -0.0034381328 | M11: 0 | N11: 0 | O11: =L11+M11+N11 -> -0.0034381328 | P11: =P10*(1+O11) -> 0.80404838 | Q11: =MAX($P$5:P11) -> 0.93631887 | R11: =P11/Q11-1 -> -0.1412665 | S11: =O11-Benchmark_RF!D11 -> -0.0084746639
A12: 15 | B12: =Returns!A16 -> 42430 | C12: =IF(Rankings!C11<=2,1,0) -> 0 | D12: =IF(Rankings!D11<=2,1,0) -> 0 | E12: =IF(Rankings!E11<=2,1,0) -> 0 | F12: =IF(Rankings!F11<=2,1,0) -> 0 | G12: =IF(Rankings!G11<=2,1,0) -> 1 | H12: =IF(Rankings!H11<=2,1,0) -> 1 | I12: =IF(Rankings!I11<=2,1,0) -> 0 | J12: =IF(Rankings!J11<=2,1,0) -> 0 | K12: =SUM(C12:J12) -> 2 | L12: =SUMPRODUCT(C12:J12,Returns!B16:I16)/K12 -> 0.036975958 | M12: 0 | N12: 0 | O12: =L12+M12+N12 -> 0.036975958 | P12: =P11*(1+O12) -> 0.83377884 | Q12: =MAX($P$5:P12) -> 0.93631887 | R12: =P12/Q12-1 -> -0.10951401 | S12: =O12-Benchmark_RF!D12 -> 0.031974445
A13: 16 | B13: =Returns!A17 -> 42461 | C13: =IF(Rankings!C11<=2,1,0) -> 0 | D13: =IF(Rankings!D11<=2,1,0) -> 0 | E13: =IF(Rankings!E11<=2,1,0) -> 0 | F13: =IF(Rankings!F11<=2,1,0) -> 0 | G13: =IF(Rankings!G11<=2,1,0) -> 1 | H13: =IF(Rankings!H11<=2,1,0) -> 1 | I13: =IF(Rankings!I11<=2,1,0) -> 0 | J13: =IF(Rankings!J11<=2,1,0) -> 0 | K13: =SUM(C13:J13) -> 2 | L13: =SUMPRODUCT(C13:J13,Returns!B17:I17)/K13 -> 0.01748769 | M13: 0 | N13: 0 | O13: =L13+M13+N13 -> 0.01748769 | P13: =P12*(1+O13) -> 0.84835971 | Q13: =MAX($P$5:P13) -> 0.93631887 | R13: =P13/Q13-1 -> -0.093941462 | S13: =O13-Benchmark_RF!D13 -> 0.012486176
A14: 17 | B14: =Returns!A18 -> 42491 | C14: =IF(Rankings!C11<=2,1,0) -> 0 | D14: =IF(Rankings!D11<=2,1,0) -> 0 | E14: =IF(Rankings!E11<=2,1,0) -> 0 | F14: =IF(Rankings!F11<=2,1,0) -> 0 | G14: =IF(Rankings!G11<=2,1,0) -> 1 | H14: =IF(Rankings!H11<=2,1,0) -> 1 | I14: =IF(Rankings!I11<=2,1,0) -> 0 | J14: =IF(Rankings!J11<=2,1,0) -> 0 | K14: =SUM(C14:J14) -> 2 | L14: =SUMPRODUCT(C14:J14,Returns!B18:I18)/K14 -> 0.069048945 | M14: 0 | N14: 0 | O14: =L14+M14+N14 -> 0.069048945 | P14: =P13*(1+O14) -> 0.90693805 | Q14: =MAX($P$5:P14) -> 0.93631887 | R14: =P14/Q14-1 -> -0.031379076 | S14: =O14-Benchmark_RF!D14 -> 0.06419127
A15: 18 | B15: =Returns!A19 -> 42522 | C15: =IF(Rankings!C11<=2,1,0) -> 0 | D15: =IF(Rankings!D11<=2,1,0) -> 0 | E15: =IF(Rankings!E11<=2,1,0) -> 0 | F15: =IF(Rankings!F11<=2,1,0) -> 0 | G15: =IF(Rankings!G11<=2,1,0) -> 1 | H15: =IF(Rankings!H11<=2,1,0) -> 1 | I15: =IF(Rankings!I11<=2,1,0) -> 0 | J15: =IF(Rankings!J11<=2,1,0) -> 0 | K15: =SUM(C15:J15) -> 2 | L15: =SUMPRODUCT(C15:J15,Returns!B19:I19)/K15 -> 0.0501073 | M15: 0 | N15: 0 | O15: =L15+M15+N15 -> 0.0501073 | P15: =P14*(1+O15) -> 0.95238227 | Q15: =MAX($P$5:P15) -> 0.95238227 | R15: =P15/Q15-1 -> 0 | S15: =O15-Benchmark_RF!D15 -> 0.045318941
A16: 19 | B16: =Returns!A20 -> 42552 | C16: =IF(Rankings!C11<=2,1,0) -> 0 | D16: =IF(Rankings!D11<=2,1,0) -> 0 | E16: =IF(Rankings!E11<=2,1,0) -> 0 | F16: =IF(Rankings!F11<=2,1,0) -> 0 | G16: =IF(Rankings!G11<=2,1,0) -> 1 | H16: =IF(Rankings!H11<=2,1,0) -> 1 | I16: =IF(Rankings!I11<=2,1,0) -> 0 | J16: =IF(Rankings!J11<=2,1,0) -> 0 | K16: =SUM(C16:J16) -> 2 | L16: =SUMPRODUCT(C16:J16,Returns!B20:I20)/K16 -> 0.067811975 | M16: 0 | N16: 0 | O16: =L16+M16+N16 -> 0.067811975 | P16: =P15*(1+O16) -> 1.0169652 | Q16: =MAX($P$5:P16) -> 1.0169652 | R16: =P16/Q16-1 -> 0 | S16: =O16-Benchmark_RF!D16 -> 0.06311261
A17: 20 | B17: =Returns!A21 -> 42583 | C17: =IF(Rankings!C23<=2,1,0) -> 0 | D17: =IF(Rankings!D23<=2,1,0) -> 0 | E17: =IF(Rankings!E23<=2,1,0) -> 0 | F17: =IF(Rankings!F23<=2,1,0) -> 1 | G17: =IF(Rankings!G23<=2,1,0) -> 0 | H17: =IF(Rankings!H23<=2,1,0) -> 0 | I17: =IF(Rankings!I23<=2,1,0) -> 1 | J17: =IF(Rankings!J23<=2,1,0) -> 0 | K17: =SUM(C17:J17) -> 2 | L17: =SUMPRODUCT(C17:J17,Returns!B21:I21)/K17 -> 0.042663683 | M17: =-2*Assumptions!$B$13 -> -0.007 | N17: =-Assumptions!$B$16*MAX(0,(1+O5)*(1+O6)*(1+O7)*(1+O8)*(1+O9)*(1+O10)*(1+O11)*(1+O12)*(1+O13)*(1+O14)*(1+O15)*(1+O16)-1) -> -0.0025447783 | O17: =L17+M17+N17 -> 0.033118905 | P17: =P16*(1+O17) -> 1.050646 | Q17: =MAX($P$5:P17) -> 1.050646 | R17: =P17/Q17-1 -> 0 | S17: =O17-Benchmark_RF!D17 -> 0.02836202
A18: 21 | B18: =Returns!A22 -> 42614 | C18: =IF(Rankings!C23<=2,1,0) -> 0 | D18: =IF(Rankings!D23<=2,1,0) -> 0 | E18: =IF(Rankings!E23<=2,1,0) -> 0 | F18: =IF(Rankings!F23<=2,1,0) -> 1 | G18: =IF(Rankings!G23<=2,1,0) -> 0 | H18: =IF(Rankings!H23<=2,1,0) -> 0 | I18: =IF(Rankings!I23<=2,1,0) -> 1 | J18: =IF(Rankings!J23<=2,1,0) -> 0 | K18: =SUM(C18:J18) -> 2 | L18: =SUMPRODUCT(C18:J18,Returns!B22:I22)/K18 -> 0.30210015 | M18: 0 | N18: 0 | O18: =L18+M18+N18 -> 0.30210015 | P18: =P17*(1+O18) -> 1.3680463 | Q18: =MAX($P$5:P18) -> 1.3680463 | R18: =P18/Q18-1 -> 0 | S18: =O18-Benchmark_RF!D18 -> 0.29734326
A19: 22 | B19: =Returns!A23 -> 42644 | C19: =IF(Rankings!C23<=2,1,0) -> 0 | D19: =IF(Rankings!D23<=2,1,0) -> 0 | E19: =IF(Rankings!E23<=2,1,0) -> 0 | F19: =IF(Rankings!F23<=2,1,0) -> 1 | G19: =IF(Rankings!G23<=2,1,0) -> 0 | H19: =IF(Rankings!H23<=2,1,0) -> 0 | I19: =IF(Rankings!I23<=2,1,0) -> 1 | J19: =IF(Rankings!J23<=2,1,0) -> 0 | K19: =SUM(C19:J19) -> 2 | L19: =SUMPRODUCT(C19:J19,Returns!B23:I23)/K19 -> 0.10422243 | M19: 0 | N19: 0 | O19: =L19+M19+N19 -> 0.10422243 | P19: =P18*(1+O19) -> 1.5106274 | Q19: =MAX($P$5:P19) -> 1.5106274 | R19: =P19/Q19-1 -> 0 | S19: =O19-Benchmark_RF!D19 -> 0.099449724
A20: 23 | B20: =Returns!A24 -> 42675 | C20: =IF(Rankings!C23<=2,1,0) -> 0 | D20: =IF(Rankings!D23<=2,1,0) -> 0 | E20: =IF(Rankings!E23<=2,1,0) -> 0 | F20: =IF(Rankings!F23<=2,1,0) -> 1 | G20: =IF(Rankings!G23<=2,1,0) -> 0 | H20: =IF(Rankings!H23<=2,1,0) -> 0 | I20: =IF(Rankings!I23<=2,1,0) -> 1 | J20: =IF(Rankings!J23<=2,1,0) -> 0 | K20: =SUM(C20:J20) -> 2 | L20: =SUMPRODUCT(C20:J20,Returns!B24:I24)/K20 -> 0.22200623 | M20: 0 | N20: 0 | O20: =L20+M20+N20 -> 0.22200623 | P20: =P19*(1+O20) -> 1.845996 | Q20: =MAX($P$5:P20) -> 1.845996 | R20: =P20/Q20-1 -> 0 | S20: =O20-Benchmark_RF!D20 -> 0.21717819
A21: 24 | B21: =Returns!A25 -> 42705 | C21: =IF(Rankings!C23<=2,1,0) -> 0 | D21: =IF(Rankings!D23<=2,1,0) -> 0 | E21: =IF(Rankings!E23<=2,1,0) -> 0 | F21: =IF(Rankings!F23<=2,1,0) -> 1 | G21: =IF(Rankings!G23<=2,1,0) -> 0 | H21: =IF(Rankings!H23<=2,1,0) -> 0 | I21: =IF(Rankings!I23<=2,1,0) -> 1 | J21: =IF(Rankings!J23<=2,1,0) -> 0 | K21: =SUM(C21:J21) -> 2 | L21: =SUMPRODUCT(C21:J21,Returns!B25:I25)/K21 -> 0.0085534527 | M21: 0 | N21: 0 | O21: =L21+M21+N21 -> 0.0085534527 | P21: =P20*(1+O21) -> 1.8617857 | Q21: =MAX($P$5:P21) -> 1.8617857 | R21: =P21/Q21-1 -> 0 | S21: =O21-Benchmark_RF!D21 -> 0.003713635
A22: 25 | B22: =Returns!A26 -> 42736 | C22: =IF(Rankings!C23<=2,1,0) -> 0 | D22: =IF(Rankings!D23<=2,1,0) -> 0 | E22: =IF(Rankings!E23<=2,1,0) -> 0 | F22: =IF(Rankings!F23<=2,1,0) -> 1 | G22: =IF(Rankings!G23<=2,1,0) -> 0 | H22: =IF(Rankings!H23<=2,1,0) -> 0 | I22: =IF(Rankings!I23<=2,1,0) -> 1 | J22: =IF(Rankings!J23<=2,1,0) -> 0 | K22: =SUM(C22:J22) -> 2 | L22: =SUMPRODUCT(C22:J22,Returns!B26:I26)/K22 -> -0.0048449545 | M22: 0 | N22: 0 | O22: =L22+M22+N22 -> -0.0048449545 | P22: =P21*(1+O22) -> 1.8527654 | Q22: =MAX($P$5:P22) -> 1.8617857 | R22: =P22/Q22-1 -> -0.0048449545 | S22: =O22-Benchmark_RF!D22 -> -0.0096193177
A23: 26 | B23: =Returns!A27 -> 42767 | C23: =IF(Rankings!C23<=2,1,0) -> 0 | D23: =IF(Rankings!D23<=2,1,0) -> 0 | E23: =IF(Rankings!E23<=2,1,0) -> 0 | F23: =IF(Rankings!F23<=2,1,0) -> 1 | G23: =IF(Rankings!G23<=2,1,0) -> 0 | H23: =IF(Rankings!H23<=2,1,0) -> 0 | I23: =IF(Rankings!I23<=2,1,0) -> 1 | J23: =IF(Rankings!J23<=2,1,0) -> 0 | K23: =SUM(C23:J23) -> 2 | L23: =SUMPRODUCT(C23:J23,Returns!B27:I27)/K23 -> -0.046817195 | M23: 0 | N23: 0 | O23: =L23+M23+N23 -> -0.046817195 | P23: =P22*(1+O23) -> 1.7660241 | Q23: =MAX($P$5:P23) -> 1.8617857 | R23: =P23/Q23-1 -> -0.051435322 | S23: =O23-Benchmark_RF!D23 -> -0.051638677
A24: 27 | B24: =Returns!A28 -> 42795 | C24: =IF(Rankings!C23<=2,1,0) -> 0 | D24: =IF(Rankings!D23<=2,1,0) -> 0 | E24: =IF(Rankings!E23<=2,1,0) -> 0 | F24: =IF(Rankings!F23<=2,1,0) -> 1 | G24: =IF(Rankings!G23<=2,1,0) -> 0 | H24: =IF(Rankings!H23<=2,1,0) -> 0 | I24: =IF(Rankings!I23<=2,1,0) -> 1 | J24: =IF(Rankings!J23<=2,1,0) -> 0 | K24: =SUM(C24:J24) -> 2 | L24: =SUMPRODUCT(C24:J24,Returns!B28:I28)/K24 -> 0.015948658 | M24: 0 | N24: 0 | O24: =L24+M24+N24 -> 0.015948658 | P24: =P23*(1+O24) -> 1.7941899 | Q24: =MAX($P$5:P24) -> 1.8617857 | R24: =P24/Q24-1 -> -0.036306988 | S24: =O24-Benchmark_RF!D24 -> 0.011103388
A25: 28 | B25: =Returns!A29 -> 42826 | C25: =IF(Rankings!C23<=2,1,0) -> 0 | D25: =IF(Rankings!D23<=2,1,0) -> 0 | E25: =IF(Rankings!E23<=2,1,0) -> 0 | F25: =IF(Rankings!F23<=2,1,0) -> 1 | G25: =IF(Rankings!G23<=2,1,0) -> 0 | H25: =IF(Rankings!H23<=2,1,0) -> 0 | I25: =IF(Rankings!I23<=2,1,0) -> 1 | J25: =IF(Rankings!J23<=2,1,0) -> 0 | K25: =SUM(C25:J25) -> 2 | L25: =SUMPRODUCT(C25:J25,Returns!B29:I29)/K25 -> 0.11523305 | M25: 0 | N25: 0 | O25: =L25+M25+N25 -> 0.11523305 | P25: =P24*(1+O25) -> 2.0009398 | Q25: =MAX($P$5:P25) -> 2.0009398 | R25: =P25/Q25-1 -> 0 | S25: =O25-Benchmark_RF!D25 -> 0.11037727
A26: 29 | B26: =Returns!A30 -> 42856 | C26: =IF(Rankings!C23<=2,1,0) -> 0 | D26: =IF(Rankings!D23<=2,1,0) -> 0 | E26: =IF(Rankings!E23<=2,1,0) -> 0 | F26: =IF(Rankings!F23<=2,1,0) -> 1 | G26: =IF(Rankings!G23<=2,1,0) -> 0 | H26: =IF(Rankings!H23<=2,1,0) -> 0 | I26: =IF(Rankings!I23<=2,1,0) -> 1 | J26: =IF(Rankings!J23<=2,1,0) -> 0 | K26: =SUM(C26:J26) -> 2 | L26: =SUMPRODUCT(C26:J26,Returns!B30:I30)/K26 -> 0.37108568 | M26: 0 | N26: 0 | O26: =L26+M26+N26 -> 0.37108568 | P26: =P25*(1+O26) -> 2.74346 | Q26: =MAX($P$5:P26) -> 2.74346 | R26: =P26/Q26-1 -> 0 | S26: =O26-Benchmark_RF!D26 -> 0.36622991
A27: 30 | B27: =Returns!A31 -> 42887 | C27: =IF(Rankings!C23<=2,1,0) -> 0 | D27: =IF(Rankings!D23<=2,1,0) -> 0 | E27: =IF(Rankings!E23<=2,1,0) -> 0 | F27: =IF(Rankings!F23<=2,1,0) -> 1 | G27: =IF(Rankings!G23<=2,1,0) -> 0 | H27: =IF(Rankings!H23<=2,1,0) -> 0 | I27: =IF(Rankings!I23<=2,1,0) -> 1 | J27: =IF(Rankings!J23<=2,1,0) -> 0 | K27: =SUM(C27:J27) -> 2 | L27: =SUMPRODUCT(C27:J27,Returns!B31:I31)/K27 -> 0.14838463 | M27: 0 | N27: 0 | O27: =L27+M27+N27 -> 0.14838463 | P27: =P26*(1+O27) -> 3.1505472 | Q27: =MAX($P$5:P27) -> 3.1505472 | R27: =P27/Q27-1 -> 0 | S27: =O27-Benchmark_RF!D27 -> 0.14352419
A28: 31 | B28: =Returns!A32 -> 42917 | C28: =IF(Rankings!C23<=2,1,0) -> 0 | D28: =IF(Rankings!D23<=2,1,0) -> 0 | E28: =IF(Rankings!E23<=2,1,0) -> 0 | F28: =IF(Rankings!F23<=2,1,0) -> 1 | G28: =IF(Rankings!G23<=2,1,0) -> 0 | H28: =IF(Rankings!H23<=2,1,0) -> 0 | I28: =IF(Rankings!I23<=2,1,0) -> 1 | J28: =IF(Rankings!J23<=2,1,0) -> 0 | K28: =SUM(C28:J28) -> 2 | L28: =SUMPRODUCT(C28:J28,Returns!B32:I32)/K28 -> -0.097675356 | M28: 0 | N28: 0 | O28: =L28+M28+N28 -> -0.097675356 | P28: =P27*(1+O28) -> 2.8428164 | Q28: =MAX($P$5:P28) -> 3.1505472 | R28: =P28/Q28-1 -> -0.097675356 | S28: =O28-Benchmark_RF!D28 -> -0.10253572
A29: 32 | B29: =Returns!A33 -> 42948 | C29: =IF(Rankings!C35<=2,1,0) -> 0 | D29: =IF(Rankings!D35<=2,1,0) -> 0 | E29: =IF(Rankings!E35<=2,1,0) -> 0 | F29: =IF(Rankings!F35<=2,1,0) -> 0 | G29: =IF(Rankings!G35<=2,1,0) -> 0 | H29: =IF(Rankings!H35<=2,1,0) -> 1 | I29: =IF(Rankings!I35<=2,1,0) -> 1 | J29: =IF(Rankings!J35<=2,1,0) -> 0 | K29: =SUM(C29:J29) -> 2 | L29: =SUMPRODUCT(C29:J29,Returns!B33:I33)/K29 -> -0.21319483 | M29: =-2*Assumptions!$B$13 -> -0.007 | N29: =-Assumptions!$B$16*MAX(0,(1+O17)*(1+O18)*(1+O19)*(1+O20)*(1+O21)*(1+O22)*(1+O23)*(1+O24)*(1+O25)*(1+O26)*(1+O27)*(1+O28)-1) -> -0.26930881 | O29: =L29+M29+N29 -> -0.48950364 | P29: =P28*(1+O29) -> 1.4512474 | Q29: =MAX($P$5:P29) -> 3.1505472 | R29: =P29/Q29-1 -> -0.53936655 | S29: =O29-Benchmark_RF!D29 -> -0.49436345
A30: 33 | B30: =Returns!A34 -> 42979 | C30: =IF(Rankings!C35<=2,1,0) -> 0 | D30: =IF(Rankings!D35<=2,1,0) -> 0 | E30: =IF(Rankings!E35<=2,1,0) -> 0 | F30: =IF(Rankings!F35<=2,1,0) -> 0 | G30: =IF(Rankings!G35<=2,1,0) -> 0 | H30: =IF(Rankings!H35<=2,1,0) -> 1 | I30: =IF(Rankings!I35<=2,1,0) -> 1 | J30: =IF(Rankings!J35<=2,1,0) -> 0 | K30: =SUM(C30:J30) -> 2 | L30: =SUMPRODUCT(C30:J30,Returns!B34:I34)/K30 -> 0.10265278 | M30: 0 | N30: 0 | O30: =L30+M30+N30 -> 0.10265278 | P30: =P29*(1+O30) -> 1.600222 | Q30: =MAX($P$5:P30) -> 3.1505472 | R30: =P30/Q30-1 -> -0.49208125 | S30: =O30-Benchmark_RF!D30 -> 0.09779234
A31: 34 | B31: =Returns!A35 -> 43009 | C31: =IF(Rankings!C35<=2,1,0) -> 0 | D31: =IF(Rankings!D35<=2,1,0) -> 0 | E31: =IF(Rankings!E35<=2,1,0) -> 0 | F31: =IF(Rankings!F35<=2,1,0) -> 0 | G31: =IF(Rankings!G35<=2,1,0) -> 0 | H31: =IF(Rankings!H35<=2,1,0) -> 1 | I31: =IF(Rankings!I35<=2,1,0) -> 1 | J31: =IF(Rankings!J35<=2,1,0) -> 0 | K31: =SUM(C31:J31) -> 2 | L31: =SUMPRODUCT(C31:J31,Returns!B35:I35)/K31 -> -0.045651394 | M31: 0 | N31: 0 | O31: =L31+M31+N31 -> -0.045651394 | P31: =P30*(1+O31) -> 1.5271697 | Q31: =MAX($P$5:P31) -> 3.1505472 | R31: =P31/Q31-1 -> -0.51526845 | S31: =O31-Benchmark_RF!D31 -> -0.050511834
A32: 35 | B32: =Returns!A36 -> 43040 | C32: =IF(Rankings!C35<=2,1,0) -> 0 | D32: =IF(Rankings!D35<=2,1,0) -> 0 | E32: =IF(Rankings!E35<=2,1,0) -> 0 | F32: =IF(Rankings!F35<=2,1,0) -> 0 | G32: =IF(Rankings!G35<=2,1,0) -> 0 | H32: =IF(Rankings!H35<=2,1,0) -> 1 | I32: =IF(Rankings!I35<=2,1,0) -> 1 | J32: =IF(Rankings!J35<=2,1,0) -> 0 | K32: =SUM(C32:J32) -> 2 | L32: =SUMPRODUCT(C32:J32,Returns!B36:I36)/K32 -> 0.25527342 | M32: 0 | N32: 0 | O32: =L32+M32+N32 -> 0.25527342 | P32: =P31*(1+O32) -> 1.9170155 | Q32: =MAX($P$5:P32) -> 3.1505472 | R32: =P32/Q32-1 -> -0.39152937 | S32: =O32-Benchmark_RF!D32 -> 0.25041306
A33: 36 | B33: =Returns!A37 -> 43070 | C33: =IF(Rankings!C35<=2,1,0) -> 0 | D33: =IF(Rankings!D35<=2,1,0) -> 0 | E33: =IF(Rankings!E35<=2,1,0) -> 0 | F33: =IF(Rankings!F35<=2,1,0) -> 0 | G33: =IF(Rankings!G35<=2,1,0) -> 0 | H33: =IF(Rankings!H35<=2,1,0) -> 1 | I33: =IF(Rankings!I35<=2,1,0) -> 1 | J33: =IF(Rankings!J35<=2,1,0) -> 0 | K33: =SUM(C33:J33) -> 2 | L33: =SUMPRODUCT(C33:J33,Returns!B37:I37)/K33 -> -0.029051268 | M33: 0 | N33: 0 | O33: =L33+M33+N33 -> -0.029051268 | P33: =P32*(1+O33) -> 1.8613237 | Q33: =MAX($P$5:P33) -> 3.1505472 | R33: =P33/Q33-1 -> -0.40920621 | S33: =O33-Benchmark_RF!D33 -> -0.033911708
A34: 37 | B34: =Returns!A38 -> 43101 | C34: =IF(Rankings!C35<=2,1,0) -> 0 | D34: =IF(Rankings!D35<=2,1,0) -> 0 | E34: =IF(Rankings!E35<=2,1,0) -> 0 | F34: =IF(Rankings!F35<=2,1,0) -> 0 | G34: =IF(Rankings!G35<=2,1,0) -> 0 | H34: =IF(Rankings!H35<=2,1,0) -> 1 | I34: =IF(Rankings!I35<=2,1,0) -> 1 | J34: =IF(Rankings!J35<=2,1,0) -> 0 | K34: =SUM(C34:J34) -> 2 | L34: =SUMPRODUCT(C34:J34,Returns!B38:I38)/K34 -> 0.058860759 | M34: 0 | N34: 0 | O34: =L34+M34+N34 -> 0.058860759 | P34: =P33*(1+O34) -> 1.9708827 | Q34: =MAX($P$5:P34) -> 3.1505472 | R34: =P34/Q34-1 -> -0.37443164 | S34: =O34-Benchmark_RF!D34 -> 0.053835347
A35: 38 | B35: =Returns!A39 -> 43132 | C35: =IF(Rankings!C35<=2,1,0) -> 0 | D35: =IF(Rankings!D35<=2,1,0) -> 0 | E35: =IF(Rankings!E35<=2,1,0) -> 0 | F35: =IF(Rankings!F35<=2,1,0) -> 0 | G35: =IF(Rankings!G35<=2,1,0) -> 0 | H35: =IF(Rankings!H35<=2,1,0) -> 1 | I35: =IF(Rankings!I35<=2,1,0) -> 1 | J35: =IF(Rankings!J35<=2,1,0) -> 0 | K35: =SUM(C35:J35) -> 2 | L35: =SUMPRODUCT(C35:J35,Returns!B39:I39)/K35 -> 0.010483002 | M35: 0 | N35: 0 | O35: =L35+M35+N35 -> 0.010483002 | P35: =P34*(1+O35) -> 1.9915434 | Q35: =MAX($P$5:P35) -> 3.1505472 | R35: =P35/Q35-1 -> -0.36787381 | S35: =O35-Benchmark_RF!D35 -> 0.0054321997
A36: 39 | B36: =Returns!A40 -> 43160 | C36: =IF(Rankings!C35<=2,1,0) -> 0 | D36: =IF(Rankings!D35<=2,1,0) -> 0 | E36: =IF(Rankings!E35<=2,1,0) -> 0 | F36: =IF(Rankings!F35<=2,1,0) -> 0 | G36: =IF(Rankings!G35<=2,1,0) -> 0 | H36: =IF(Rankings!H35<=2,1,0) -> 1 | I36: =IF(Rankings!I35<=2,1,0) -> 1 | J36: =IF(Rankings!J35<=2,1,0) -> 0 | K36: =SUM(C36:J36) -> 2 | L36: =SUMPRODUCT(C36:J36,Returns!B40:I40)/K36 -> 0.21335634 | M36: 0 | N36: 0 | O36: =L36+M36+N36 -> 0.21335634 | P36: =P35*(1+O36) -> 2.4164519 | Q36: =MAX($P$5:P36) -> 3.1505472 | R36: =P36/Q36-1 -> -0.23300567 | S36: =O36-Benchmark_RF!D36 -> 0.20828433
A37: 40 | B37: =Returns!A41 -> 43191 | C37: =IF(Rankings!C35<=2,1,0) -> 0 | D37: =IF(Rankings!D35<=2,1,0) -> 0 | E37: =IF(Rankings!E35<=2,1,0) -> 0 | F37: =IF(Rankings!F35<=2,1,0) -> 0 | G37: =IF(Rankings!G35<=2,1,0) -> 0 | H37: =IF(Rankings!H35<=2,1,0) -> 1 | I37: =IF(Rankings!I35<=2,1,0) -> 1 | J37: =IF(Rankings!J35<=2,1,0) -> 0 | K37: =SUM(C37:J37) -> 2 | L37: =SUMPRODUCT(C37:J37,Returns!B41:I41)/K37 -> 0.023455402 | M37: 0 | N37: 0 | O37: =L37+M37+N37 -> 0.023455402 | P37: =P36*(1+O37) -> 2.4731307 | Q37: =MAX($P$5:P37) -> 3.1505472 | R37: =P37/Q37-1 -> -0.21501551 | S37: =O37-Benchmark_RF!D37 -> 0.018400895
A38: 41 | B38: =Returns!A42 -> 43221 | C38: =IF(Rankings!C35<=2,1,0) -> 0 | D38: =IF(Rankings!D35<=2,1,0) -> 0 | E38: =IF(Rankings!E35<=2,1,0) -> 0 | F38: =IF(Rankings!F35<=2,1,0) -> 0 | G38: =IF(Rankings!G35<=2,1,0) -> 0 | H38: =IF(Rankings!H35<=2,1,0) -> 1 | I38: =IF(Rankings!I35<=2,1,0) -> 1 | J38: =IF(Rankings!J35<=2,1,0) -> 0 | K38: =SUM(C38:J38) -> 2 | L38: =SUMPRODUCT(C38:J38,Returns!B42:I42)/K38 -> 0.019805924 | M38: 0 | N38: 0 | O38: =L38+M38+N38 -> 0.019805924 | P38: =P37*(1+O38) -> 2.5221134 | Q38: =MAX($P$5:P38) -> 3.1505472 | R38: =P38/Q38-1 -> -0.19946817 | S38: =O38-Benchmark_RF!D38 -> 0.014734389
A39: 42 | B39: =Returns!A43 -> 43252 | C39: =IF(Rankings!C35<=2,1,0) -> 0 | D39: =IF(Rankings!D35<=2,1,0) -> 0 | E39: =IF(Rankings!E35<=2,1,0) -> 0 | F39: =IF(Rankings!F35<=2,1,0) -> 0 | G39: =IF(Rankings!G35<=2,1,0) -> 0 | H39: =IF(Rankings!H35<=2,1,0) -> 1 | I39: =IF(Rankings!I35<=2,1,0) -> 1 | J39: =IF(Rankings!J35<=2,1,0) -> 0 | K39: =SUM(C39:J39) -> 2 | L39: =SUMPRODUCT(C39:J39,Returns!B43:I43)/K39 -> 0.042045583 | M39: 0 | N39: 0 | O39: =L39+M39+N39 -> 0.042045583 | P39: =P38*(1+O39) -> 2.6281571 | Q39: =MAX($P$5:P39) -> 3.1505472 | R39: =P39/Q39-1 -> -0.16580934 | S39: =O39-Benchmark_RF!D39 -> 0.036579997
A40: 43 | B40: =Returns!A44 -> 43282 | C40: =IF(Rankings!C35<=2,1,0) -> 0 | D40: =IF(Rankings!D35<=2,1,0) -> 0 | E40: =IF(Rankings!E35<=2,1,0) -> 0 | F40: =IF(Rankings!F35<=2,1,0) -> 0 | G40: =IF(Rankings!G35<=2,1,0) -> 0 | H40: =IF(Rankings!H35<=2,1,0) -> 1 | I40: =IF(Rankings!I35<=2,1,0) -> 1 | J40: =IF(Rankings!J35<=2,1,0) -> 0 | K40: =SUM(C40:J40) -> 2 | L40: =SUMPRODUCT(C40:J40,Returns!B44:I44)/K40 -> 0.068663569 | M40: 0 | N40: 0 | O40: =L40+M40+N40 -> 0.068663569 | P40: =P39*(1+O40) -> 2.8086157 | Q40: =MAX($P$5:P40) -> 3.1505472 | R40: =P40/Q40-1 -> -0.10853084 | S40: =O40-Benchmark_RF!D40 -> 0.062446226
A41: 44 | B41: =Returns!A45 -> 43313 | C41: =IF(Rankings!C47<=2,1,0) -> 1 | D41: =IF(Rankings!D47<=2,1,0) -> 0 | E41: =IF(Rankings!E47<=2,1,0) -> 0 | F41: =IF(Rankings!F47<=2,1,0) -> 0 | G41: =IF(Rankings!G47<=2,1,0) -> 0 | H41: =IF(Rankings!H47<=2,1,0) -> 1 | I41: =IF(Rankings!I47<=2,1,0) -> 0 | J41: =IF(Rankings!J47<=2,1,0) -> 0 | K41: =SUM(C41:J41) -> 2 | L41: =SUMPRODUCT(C41:J41,Returns!B45:I45)/K41 -> -0.0044257353 | M41: =-2*Assumptions!$B$13 -> -0.007 | N41: =-Assumptions!$B$16*MAX(0,(1+O29)*(1+O30)*(1+O31)*(1+O32)*(1+O33)*(1+O34)*(1+O35)*(1+O36)*(1+O37)*(1+O38)*(1+O39)*(1+O40)-1) -> 0 | O41: =L41+M41+N41 -> -0.011425735 | P41: =P40*(1+O41) -> 2.7765252 | Q41: =MAX($P$5:P41) -> 3.1505472 | R41: =P41/Q41-1 -> -0.11871653 | S41: =O41-Benchmark_RF!D41 -> -0.017665417
A42: 45 | B42: =Returns!A46 -> 43344 | C42: =IF(Rankings!C47<=2,1,0) -> 1 | D42: =IF(Rankings!D47<=2,1,0) -> 0 | E42: =IF(Rankings!E47<=2,1,0) -> 0 | F42: =IF(Rankings!F47<=2,1,0) -> 0 | G42: =IF(Rankings!G47<=2,1,0) -> 0 | H42: =IF(Rankings!H47<=2,1,0) -> 1 | I42: =IF(Rankings!I47<=2,1,0) -> 0 | J42: =IF(Rankings!J47<=2,1,0) -> 0 | K42: =SUM(C42:J42) -> 2 | L42: =SUMPRODUCT(C42:J42,Returns!B46:I46)/K42 -> 0.0027633255 | M42: 0 | N42: 0 | O42: =L42+M42+N42 -> 0.0027633255 | P42: =P41*(1+O42) -> 2.7841977 | Q42: =MAX($P$5:P42) -> 3.1505472 | R42: =P42/Q42-1 -> -0.11628125 | S42: =O42-Benchmark_RF!D42 -> -0.003476356
A43: 46 | B43: =Returns!A47 -> 43374 | C43: =IF(Rankings!C47<=2,1,0) -> 1 | D43: =IF(Rankings!D47<=2,1,0) -> 0 | E43: =IF(Rankings!E47<=2,1,0) -> 0 | F43: =IF(Rankings!F47<=2,1,0) -> 0 | G43: =IF(Rankings!G47<=2,1,0) -> 0 | H43: =IF(Rankings!H47<=2,1,0) -> 1 | I43: =IF(Rankings!I47<=2,1,0) -> 0 | J43: =IF(Rankings!J47<=2,1,0) -> 0 | K43: =SUM(C43:J43) -> 2 | L43: =SUMPRODUCT(C43:J43,Returns!B47:I47)/K43 -> 0.020208866 | M43: 0 | N43: 0 | O43: =L43+M43+N43 -> 0.020208866 | P43: =P42*(1+O43) -> 2.8404631 | Q43: =MAX($P$5:P43) -> 3.1505472 | R43: =P43/Q43-1 -> -0.098422299 | S43: =O43-Benchmark_RF!D43 -> 0.013161928
A44: 47 | B44: =Returns!A48 -> 43405 | C44: =IF(Rankings!C47<=2,1,0) -> 1 | D44: =IF(Rankings!D47<=2,1,0) -> 0 | E44: =IF(Rankings!E47<=2,1,0) -> 0 | F44: =IF(Rankings!F47<=2,1,0) -> 0 | G44: =IF(Rankings!G47<=2,1,0) -> 0 | H44: =IF(Rankings!H47<=2,1,0) -> 1 | I44: =IF(Rankings!I47<=2,1,0) -> 0 | J44: =IF(Rankings!J47<=2,1,0) -> 0 | K44: =SUM(C44:J44) -> 2 | L44: =SUMPRODUCT(C44:J44,Returns!B48:I48)/K44 -> -0.031861779 | M44: 0 | N44: 0 | O44: =L44+M44+N44 -> -0.031861779 | P44: =P43*(1+O44) -> 2.7499609 | Q44: =MAX($P$5:P44) -> 3.1505472 | R44: =P44/Q44-1 -> -0.12714817 | S44: =O44-Benchmark_RF!D44 -> -0.0389135
A45: 48 | B45: =Returns!A49 -> 43435 | C45: =IF(Rankings!C47<=2,1,0) -> 1 | D45: =IF(Rankings!D47<=2,1,0) -> 0 | E45: =IF(Rankings!E47<=2,1,0) -> 0 | F45: =IF(Rankings!F47<=2,1,0) -> 0 | G45: =IF(Rankings!G47<=2,1,0) -> 0 | H45: =IF(Rankings!H47<=2,1,0) -> 1 | I45: =IF(Rankings!I47<=2,1,0) -> 0 | J45: =IF(Rankings!J47<=2,1,0) -> 0 | K45: =SUM(C45:J45) -> 2 | L45: =SUMPRODUCT(C45:J45,Returns!B49:I49)/K45 -> -0.095163809 | M45: 0 | N45: 0 | O45: =L45+M45+N45 -> -0.095163809 | P45: =P44*(1+O45) -> 2.4882642 | Q45: =MAX($P$5:P45) -> 3.1505472 | R45: =P45/Q45-1 -> -0.21021207 | S45: =O45-Benchmark_RF!D45 -> -0.10336416
A46: 49 | B46: =Returns!A50 -> 43466 | C46: =IF(Rankings!C47<=2,1,0) -> 1 | D46: =IF(Rankings!D47<=2,1,0) -> 0 | E46: =IF(Rankings!E47<=2,1,0) -> 0 | F46: =IF(Rankings!F47<=2,1,0) -> 0 | G46: =IF(Rankings!G47<=2,1,0) -> 0 | H46: =IF(Rankings!H47<=2,1,0) -> 1 | I46: =IF(Rankings!I47<=2,1,0) -> 0 | J46: =IF(Rankings!J47<=2,1,0) -> 0 | K46: =SUM(C46:J46) -> 2 | L46: =SUMPRODUCT(C46:J46,Returns!B50:I50)/K46 -> 0.16000743 | M46: 0 | N46: 0 | O46: =L46+M46+N46 -> 0.16000743 | P46: =P45*(1+O46) -> 2.8864049 | Q46: =MAX($P$5:P46) -> 3.1505472 | R46: =P46/Q46-1 -> -0.083840135 | S46: =O46-Benchmark_RF!D46 -> 0.15180373
A47: 50 | B47: =Returns!A51 -> 43497 | C47: =IF(Rankings!C47<=2,1,0) -> 1 | D47: =IF(Rankings!D47<=2,1,0) -> 0 | E47: =IF(Rankings!E47<=2,1,0) -> 0 | F47: =IF(Rankings!F47<=2,1,0) -> 0 | G47: =IF(Rankings!G47<=2,1,0) -> 0 | H47: =IF(Rankings!H47<=2,1,0) -> 1 | I47: =IF(Rankings!I47<=2,1,0) -> 0 | J47: =IF(Rankings!J47<=2,1,0) -> 0 | K47: =SUM(C47:J47) -> 2 | L47: =SUMPRODUCT(C47:J47,Returns!B51:I51)/K47 -> -0.00015271011 | M47: 0 | N47: 0 | O47: =L47+M47+N47 -> -0.00015271011 | P47: =P46*(1+O47) -> 2.8859642 | Q47: =MAX($P$5:P47) -> 3.1505472 | R47: =P47/Q47-1 -> -0.083980042 | S47: =O47-Benchmark_RF!D47 -> -0.0085457283
A48: 51 | B48: =Returns!A52 -> 43525 | C48: =IF(Rankings!C47<=2,1,0) -> 1 | D48: =IF(Rankings!D47<=2,1,0) -> 0 | E48: =IF(Rankings!E47<=2,1,0) -> 0 | F48: =IF(Rankings!F47<=2,1,0) -> 0 | G48: =IF(Rankings!G47<=2,1,0) -> 0 | H48: =IF(Rankings!H47<=2,1,0) -> 1 | I48: =IF(Rankings!I47<=2,1,0) -> 0 | J48: =IF(Rankings!J47<=2,1,0) -> 0 | K48: =SUM(C48:J48) -> 2 | L48: =SUMPRODUCT(C48:J48,Returns!B52:I52)/K48 -> -0.018474586 | M48: 0 | N48: 0 | O48: =L48+M48+N48 -> -0.018474586 | P48: =P47*(1+O48) -> 2.8326472 | Q48: =MAX($P$5:P48) -> 3.1505472 | R48: =P48/Q48-1 -> -0.10090313 | S48: =O48-Benchmark_RF!D48 -> -0.026862283
A49: 52 | B49: =Returns!A53 -> 43556 | C49: =IF(Rankings!C47<=2,1,0) -> 1 | D49: =IF(Rankings!D47<=2,1,0) -> 0 | E49: =IF(Rankings!E47<=2,1,0) -> 0 | F49: =IF(Rankings!F47<=2,1,0) -> 0 | G49: =IF(Rankings!G47<=2,1,0) -> 0 | H49: =IF(Rankings!H47<=2,1,0) -> 1 | I49: =IF(Rankings!I47<=2,1,0) -> 0 | J49: =IF(Rankings!J47<=2,1,0) -> 0 | K49: =SUM(C49:J49) -> 2 | L49: =SUMPRODUCT(C49:J49,Returns!B53:I53)/K49 -> -0.02660501 | M49: 0 | N49: 0 | O49: =L49+M49+N49 -> -0.02660501 | P49: =P48*(1+O49) -> 2.7572846 | Q49: =MAX($P$5:P49) -> 3.1505472 | R49: =P49/Q49-1 -> -0.12482361 | S49: =O49-Benchmark_RF!D49 -> -0.035301957
A50: 53 | B50: =Returns!A54 -> 43586 | C50: =IF(Rankings!C47<=2,1,0) -> 1 | D50: =IF(Rankings!D47<=2,1,0) -> 0 | E50: =IF(Rankings!E47<=2,1,0) -> 0 | F50: =IF(Rankings!F47<=2,1,0) -> 0 | G50: =IF(Rankings!G47<=2,1,0) -> 0 | H50: =IF(Rankings!H47<=2,1,0) -> 1 | I50: =IF(Rankings!I47<=2,1,0) -> 0 | J50: =IF(Rankings!J47<=2,1,0) -> 0 | K50: =SUM(C50:J50) -> 2 | L50: =SUMPRODUCT(C50:J50,Returns!B54:I54)/K50 -> -0.067083904 | M50: 0 | N50: 0 | O50: =L50+M50+N50 -> -0.067083904 | P50: =P49*(1+O50) -> 2.5723151 | Q50: =MAX($P$5:P50) -> 3.1505472 | R50: =P50/Q50-1 -> -0.18353386 | S50: =O50-Benchmark_RF!D50 -> -0.077003346
A51: 54 | B51: =Returns!A55 -> 43617 | C51: =IF(Rankings!C47<=2,1,0) -> 1 | D51: =IF(Rankings!D47<=2,1,0) -> 0 | E51: =IF(Rankings!E47<=2,1,0) -> 0 | F51: =IF(Rankings!F47<=2,1,0) -> 0 | G51: =IF(Rankings!G47<=2,1,0) -> 0 | H51: =IF(Rankings!H47<=2,1,0) -> 1 | I51: =IF(Rankings!I47<=2,1,0) -> 0 | J51: =IF(Rankings!J47<=2,1,0) -> 0 | K51: =SUM(C51:J51) -> 2 | L51: =SUMPRODUCT(C51:J51,Returns!B55:I55)/K51 -> -0.053225641 | M51: 0 | N51: 0 | O51: =L51+M51+N51 -> -0.053225641 | P51: =P50*(1+O51) -> 2.435402 | Q51: =MAX($P$5:P51) -> 3.1505472 | R51: =P51/Q51-1 -> -0.22699079 | S51: =O51-Benchmark_RF!D51 -> -0.063267159
A52: 55 | B52: =Returns!A56 -> 43647 | C52: =IF(Rankings!C47<=2,1,0) -> 1 | D52: =IF(Rankings!D47<=2,1,0) -> 0 | E52: =IF(Rankings!E47<=2,1,0) -> 0 | F52: =IF(Rankings!F47<=2,1,0) -> 0 | G52: =IF(Rankings!G47<=2,1,0) -> 0 | H52: =IF(Rankings!H47<=2,1,0) -> 1 | I52: =IF(Rankings!I47<=2,1,0) -> 0 | J52: =IF(Rankings!J47<=2,1,0) -> 0 | K52: =SUM(C52:J52) -> 2 | L52: =SUMPRODUCT(C52:J52,Returns!B56:I56)/K52 -> 0.031270776 | M52: 0 | N52: 0 | O52: =L52+M52+N52 -> 0.031270776 | P52: =P51*(1+O52) -> 2.5115589 | Q52: =MAX($P$5:P52) -> 3.1505472 | R52: =P52/Q52-1 -> -0.2028182 | S52: =O52-Benchmark_RF!D52 -> 0.02048005
A53: 56 | B53: =Returns!A57 -> 43678 | C53: =IF(Rankings!C59<=2,1,0) -> 1 | D53: =IF(Rankings!D59<=2,1,0) -> 0 | E53: =IF(Rankings!E59<=2,1,0) -> 0 | F53: =IF(Rankings!F59<=2,1,0) -> 0 | G53: =IF(Rankings!G59<=2,1,0) -> 1 | H53: =IF(Rankings!H59<=2,1,0) -> 0 | I53: =IF(Rankings!I59<=2,1,0) -> 0 | J53: =IF(Rankings!J59<=2,1,0) -> 0 | K53: =SUM(C53:J53) -> 2 | L53: =SUMPRODUCT(C53:J53,Returns!B57:I57)/K53 -> -0.12575351 | M53: =-2*Assumptions!$B$13 -> -0.007 | N53: =-Assumptions!$B$16*MAX(0,(1+O41)*(1+O42)*(1+O43)*(1+O44)*(1+O45)*(1+O46)*(1+O47)*(1+O48)*(1+O49)*(1+O50)*(1+O51)*(1+O52)-1) -> 0 | O53: =L53+M53+N53 -> -0.13275351 | P53: =P52*(1+O53) -> 2.1781407 | Q53: =MAX($P$5:P53) -> 3.1505472 | R53: =P53/Q53-1 -> -0.30864688 | S53: =O53-Benchmark_RF!D53 -> -0.14354668
A54: 57 | B54: =Returns!A58 -> 43709 | C54: =IF(Rankings!C59<=2,1,0) -> 1 | D54: =IF(Rankings!D59<=2,1,0) -> 0 | E54: =IF(Rankings!E59<=2,1,0) -> 0 | F54: =IF(Rankings!F59<=2,1,0) -> 0 | G54: =IF(Rankings!G59<=2,1,0) -> 1 | H54: =IF(Rankings!H59<=2,1,0) -> 0 | I54: =IF(Rankings!I59<=2,1,0) -> 0 | J54: =IF(Rankings!J59<=2,1,0) -> 0 | K54: =SUM(C54:J54) -> 2 | L54: =SUMPRODUCT(C54:J54,Returns!B58:I58)/K54 -> 0.081285585 | M54: 0 | N54: 0 | O54: =L54+M54+N54 -> 0.081285585 | P54: =P53*(1+O54) -> 2.3551921 | Q54: =MAX($P$5:P54) -> 3.1505472 | R54: =P54/Q54-1 -> -0.25244984 | S54: =O54-Benchmark_RF!D54 -> 0.070515447
A55: 58 | B55: =Returns!A59 -> 43739 | C55: =IF(Rankings!C59<=2,1,0) -> 1 | D55: =IF(Rankings!D59<=2,1,0) -> 0 | E55: =IF(Rankings!E59<=2,1,0) -> 0 | F55: =IF(Rankings!F59<=2,1,0) -> 0 | G55: =IF(Rankings!G59<=2,1,0) -> 1 | H55: =IF(Rankings!H59<=2,1,0) -> 0 | I55: =IF(Rankings!I59<=2,1,0) -> 0 | J55: =IF(Rankings!J59<=2,1,0) -> 0 | K55: =SUM(C55:J55) -> 2 | L55: =SUMPRODUCT(C55:J55,Returns!B59:I59)/K55 -> 0.03024912 | M55: 0 | N55: 0 | O55: =L55+M55+N55 -> 0.03024912 | P55: =P54*(1+O55) -> 2.4264346 | Q55: =MAX($P$5:P55) -> 3.1505472 | R55: =P55/Q55-1 -> -0.22983711 | S55: =O55-Benchmark_RF!D55 -> 0.019825913
A56: 59 | B56: =Returns!A60 -> 43770 | C56: =IF(Rankings!C59<=2,1,0) -> 1 | D56: =IF(Rankings!D59<=2,1,0) -> 0 | E56: =IF(Rankings!E59<=2,1,0) -> 0 | F56: =IF(Rankings!F59<=2,1,0) -> 0 | G56: =IF(Rankings!G59<=2,1,0) -> 1 | H56: =IF(Rankings!H59<=2,1,0) -> 0 | I56: =IF(Rankings!I59<=2,1,0) -> 0 | J56: =IF(Rankings!J59<=2,1,0) -> 0 | K56: =SUM(C56:J56) -> 2 | L56: =SUMPRODUCT(C56:J56,Returns!B60:I60)/K56 -> 0.1128608 | M56: 0 | N56: 0 | O56: =L56+M56+N56 -> 0.1128608 | P56: =P55*(1+O56) -> 2.7002839 | Q56: =MAX($P$5:P56) -> 3.1505472 | R56: =P56/Q56-1 -> -0.1429159 | S56: =O56-Benchmark_RF!D56 -> 0.1022813
A57: 60 | B57: =Returns!A61 -> 43800 | C57: =IF(Rankings!C59<=2,1,0) -> 1 | D57: =IF(Rankings!D59<=2,1,0) -> 0 | E57: =IF(Rankings!E59<=2,1,0) -> 0 | F57: =IF(Rankings!F59<=2,1,0) -> 0 | G57: =IF(Rankings!G59<=2,1,0) -> 1 | H57: =IF(Rankings!H59<=2,1,0) -> 0 | I57: =IF(Rankings!I59<=2,1,0) -> 0 | J57: =IF(Rankings!J59<=2,1,0) -> 0 | K57: =SUM(C57:J57) -> 2 | L57: =SUMPRODUCT(C57:J57,Returns!B61:I61)/K57 -> 0.046760683 | M57: 0 | N57: 0 | O57: =L57+M57+N57 -> 0.046760683 | P57: =P56*(1+O57) -> 2.8265511 | Q57: =MAX($P$5:P57) -> 3.1505472 | R57: =P57/Q57-1 -> -0.10283806 | S57: =O57-Benchmark_RF!D57 -> 0.036192014
A58: 61 | B58: =Returns!A62 -> 43831 | C58: =IF(Rankings!C59<=2,1,0) -> 1 | D58: =IF(Rankings!D59<=2,1,0) -> 0 | E58: =IF(Rankings!E59<=2,1,0) -> 0 | F58: =IF(Rankings!F59<=2,1,0) -> 0 | G58: =IF(Rankings!G59<=2,1,0) -> 1 | H58: =IF(Rankings!H59<=2,1,0) -> 0 | I58: =IF(Rankings!I59<=2,1,0) -> 0 | J58: =IF(Rankings!J59<=2,1,0) -> 0 | K58: =SUM(C58:J58) -> 2 | L58: =SUMPRODUCT(C58:J58,Returns!B62:I62)/K58 -> 0.043506416 | M58: 0 | N58: 0 | O58: =L58+M58+N58 -> 0.043506416 | P58: =P57*(1+O58) -> 2.9495242 | Q58: =MAX($P$5:P58) -> 3.1505472 | R58: =P58/Q58-1 -> -0.063805763 | S58: =O58-Benchmark_RF!D58 -> 0.03298059
A59: 62 | B59: =Returns!A63 -> 43862 | C59: =IF(Rankings!C59<=2,1,0) -> 1 | D59: =IF(Rankings!D59<=2,1,0) -> 0 | E59: =IF(Rankings!E59<=2,1,0) -> 0 | F59: =IF(Rankings!F59<=2,1,0) -> 0 | G59: =IF(Rankings!G59<=2,1,0) -> 1 | H59: =IF(Rankings!H59<=2,1,0) -> 0 | I59: =IF(Rankings!I59<=2,1,0) -> 0 | J59: =IF(Rankings!J59<=2,1,0) -> 0 | K59: =SUM(C59:J59) -> 2 | L59: =SUMPRODUCT(C59:J59,Returns!B63:I63)/K59 -> -0.060028809 | M59: 0 | N59: 0 | O59: =L59+M59+N59 -> -0.060028809 | P59: =P58*(1+O59) -> 2.7724678 | Q59: =MAX($P$5:P59) -> 3.1505472 | R59: =P59/Q59-1 -> -0.12000439 | S59: =O59-Benchmark_RF!D59 -> -0.070549139
A60: 63 | B60: =Returns!A64 -> 43891 | C60: =IF(Rankings!C59<=2,1,0) -> 1 | D60: =IF(Rankings!D59<=2,1,0) -> 0 | E60: =IF(Rankings!E59<=2,1,0) -> 0 | F60: =IF(Rankings!F59<=2,1,0) -> 0 | G60: =IF(Rankings!G59<=2,1,0) -> 1 | H60: =IF(Rankings!H59<=2,1,0) -> 0 | I60: =IF(Rankings!I59<=2,1,0) -> 0 | J60: =IF(Rankings!J59<=2,1,0) -> 0 | K60: =SUM(C60:J60) -> 2 | L60: =SUMPRODUCT(C60:J60,Returns!B64:I64)/K60 -> -0.29506094 | M60: 0 | N60: 0 | O60: =L60+M60+N60 -> -0.29506094 | P60: =P59*(1+O60) -> 1.9544208 | Q60: =MAX($P$5:P60) -> 3.1505472 | R60: =P60/Q60-1 -> -0.37965672 | S60: =O60-Benchmark_RF!D60 -> -0.30396003
A61: 64 | B61: =Returns!A65 -> 43922 | C61: =IF(Rankings!C59<=2,1,0) -> 1 | D61: =IF(Rankings!D59<=2,1,0) -> 0 | E61: =IF(Rankings!E59<=2,1,0) -> 0 | F61: =IF(Rankings!F59<=2,1,0) -> 0 | G61: =IF(Rankings!G59<=2,1,0) -> 1 | H61: =IF(Rankings!H59<=2,1,0) -> 0 | I61: =IF(Rankings!I59<=2,1,0) -> 0 | J61: =IF(Rankings!J59<=2,1,0) -> 0 | K61: =SUM(C61:J61) -> 2 | L61: =SUMPRODUCT(C61:J61,Returns!B65:I65)/K61 -> 0.31887202 | M61: 0 | N61: 0 | O61: =L61+M61+N61 -> 0.31887202 | P61: =P60*(1+O61) -> 2.5776309 | Q61: =MAX($P$5:P61) -> 3.1505472 | R61: =P61/Q61-1 -> -0.18184661 | S61: =O61-Benchmark_RF!D61 -> 0.31227195
A62: 65 | B62: =Returns!A66 -> 43952 | C62: =IF(Rankings!C59<=2,1,0) -> 1 | D62: =IF(Rankings!D59<=2,1,0) -> 0 | E62: =IF(Rankings!E59<=2,1,0) -> 0 | F62: =IF(Rankings!F59<=2,1,0) -> 0 | G62: =IF(Rankings!G59<=2,1,0) -> 1 | H62: =IF(Rankings!H59<=2,1,0) -> 0 | I62: =IF(Rankings!I59<=2,1,0) -> 0 | J62: =IF(Rankings!J59<=2,1,0) -> 0 | K62: =SUM(C62:J62) -> 2 | L62: =SUMPRODUCT(C62:J62,Returns!B66:I66)/K62 -> 0.033050955 | M62: 0 | N62: 0 | O62: =L62+M62+N62 -> 0.033050955 | P62: =P61*(1+O62) -> 2.6628241 | Q62: =MAX($P$5:P62) -> 3.1505472 | R62: =P62/Q62-1 -> -0.15480586 | S62: =O62-Benchmark_RF!D62 -> 0.02652324
A63: 66 | B63: =Returns!A67 -> 43983 | C63: =IF(Rankings!C59<=2,1,0) -> 1 | D63: =IF(Rankings!D59<=2,1,0) -> 0 | E63: =IF(Rankings!E59<=2,1,0) -> 0 | F63: =IF(Rankings!F59<=2,1,0) -> 0 | G63: =IF(Rankings!G59<=2,1,0) -> 1 | H63: =IF(Rankings!H59<=2,1,0) -> 0 | I63: =IF(Rankings!I59<=2,1,0) -> 0 | J63: =IF(Rankings!J59<=2,1,0) -> 0 | K63: =SUM(C63:J63) -> 2 | L63: =SUMPRODUCT(C63:J63,Returns!B67:I67)/K63 -> -0.0098465753 | M63: 0 | N63: 0 | O63: =L63+M63+N63 -> -0.0098465753 | P63: =P62*(1+O63) -> 2.6366044 | Q63: =MAX($P$5:P63) -> 3.1505472 | R63: =P63/Q63-1 -> -0.16312813 | S63: =O63-Benchmark_RF!D63 -> -0.015382221
A64: 67 | B64: =Returns!A68 -> 44013 | C64: =IF(Rankings!C59<=2,1,0) -> 1 | D64: =IF(Rankings!D59<=2,1,0) -> 0 | E64: =IF(Rankings!E59<=2,1,0) -> 0 | F64: =IF(Rankings!F59<=2,1,0) -> 0 | G64: =IF(Rankings!G59<=2,1,0) -> 1 | H64: =IF(Rankings!H59<=2,1,0) -> 0 | I64: =IF(Rankings!I59<=2,1,0) -> 0 | J64: =IF(Rankings!J59<=2,1,0) -> 0 | K64: =SUM(C64:J64) -> 2 | L64: =SUMPRODUCT(C64:J64,Returns!B68:I68)/K64 -> 0.14332023 | M64: 0 | N64: 0 | O64: =L64+M64+N64 -> 0.14332023 | P64: =P63*(1+O64) -> 3.0144831 | Q64: =MAX($P$5:P64) -> 3.1505472 | R64: =P64/Q64-1 -> -0.043187454 | S64: =O64-Benchmark_RF!D64 -> 0.1377653
A65: 68 | B65: =Returns!A69 -> 44044 | C65: =IF(Rankings!C71<=2,1,0) -> 0 | D65: =IF(Rankings!D71<=2,1,0) -> 0 | E65: =IF(Rankings!E71<=2,1,0) -> 0 | F65: =IF(Rankings!F71<=2,1,0) -> 1 | G65: =IF(Rankings!G71<=2,1,0) -> 1 | H65: =IF(Rankings!H71<=2,1,0) -> 0 | I65: =IF(Rankings!I71<=2,1,0) -> 0 | J65: =IF(Rankings!J71<=2,1,0) -> 0 | K65: =SUM(C65:J65) -> 2 | L65: =SUMPRODUCT(C65:J65,Returns!B69:I69)/K65 -> 0.0091443175 | M65: =-2*Assumptions!$B$13 -> -0.007 | N65: =-Assumptions!$B$16*MAX(0,(1+O53)*(1+O54)*(1+O55)*(1+O56)*(1+O57)*(1+O58)*(1+O59)*(1+O60)*(1+O61)*(1+O62)*(1+O63)*(1+O64)-1) -> -0.030036576 | O65: =L65+M65+N65 -> -0.027892258 | P65: =P64*(1+O65) -> 2.9304024 | Q65: =MAX($P$5:P65) -> 3.1505472 | R65: =P65/Q65-1 -> -0.069875116 | S65: =O65-Benchmark_RF!D65 -> -0.033618118
A66: 69 | B66: =Returns!A70 -> 44075 | C66: =IF(Rankings!C71<=2,1,0) -> 0 | D66: =IF(Rankings!D71<=2,1,0) -> 0 | E66: =IF(Rankings!E71<=2,1,0) -> 0 | F66: =IF(Rankings!F71<=2,1,0) -> 1 | G66: =IF(Rankings!G71<=2,1,0) -> 1 | H66: =IF(Rankings!H71<=2,1,0) -> 0 | I66: =IF(Rankings!I71<=2,1,0) -> 0 | J66: =IF(Rankings!J71<=2,1,0) -> 0 | K66: =SUM(C66:J66) -> 2 | L66: =SUMPRODUCT(C66:J66,Returns!B70:I70)/K66 -> 0.036518222 | M66: 0 | N66: 0 | O66: =L66+M66+N66 -> 0.036518222 | P66: =P65*(1+O66) -> 3.0374155 | Q66: =MAX($P$5:P66) -> 3.1505472 | R66: =P66/Q66-1 -> -0.035908609 | S66: =O66-Benchmark_RF!D66 -> 0.030787119
A67: 70 | B67: =Returns!A71 -> 44105 | C67: =IF(Rankings!C71<=2,1,0) -> 0 | D67: =IF(Rankings!D71<=2,1,0) -> 0 | E67: =IF(Rankings!E71<=2,1,0) -> 0 | F67: =IF(Rankings!F71<=2,1,0) -> 1 | G67: =IF(Rankings!G71<=2,1,0) -> 1 | H67: =IF(Rankings!H71<=2,1,0) -> 0 | I67: =IF(Rankings!I71<=2,1,0) -> 0 | J67: =IF(Rankings!J71<=2,1,0) -> 0 | K67: =SUM(C67:J67) -> 2 | L67: =SUMPRODUCT(C67:J67,Returns!B71:I71)/K67 -> -0.0051337602 | M67: 0 | N67: 0 | O67: =L67+M67+N67 -> -0.0051337602 | P67: =P66*(1+O67) -> 3.0218221 | Q67: =MAX($P$5:P67) -> 3.1505472 | R67: =P67/Q67-1 -> -0.040858023 | S67: =O67-Benchmark_RF!D67 -> -0.010911571
A68: 71 | B68: =Returns!A72 -> 44136 | C68: =IF(Rankings!C71<=2,1,0) -> 0 | D68: =IF(Rankings!D71<=2,1,0) -> 0 | E68: =IF(Rankings!E71<=2,1,0) -> 0 | F68: =IF(Rankings!F71<=2,1,0) -> 1 | G68: =IF(Rankings!G71<=2,1,0) -> 1 | H68: =IF(Rankings!H71<=2,1,0) -> 0 | I68: =IF(Rankings!I71<=2,1,0) -> 0 | J68: =IF(Rankings!J71<=2,1,0) -> 0 | K68: =SUM(C68:J68) -> 2 | L68: =SUMPRODUCT(C68:J68,Returns!B72:I72)/K68 -> 0.018015317 | M68: 0 | N68: 0 | O68: =L68+M68+N68 -> 0.018015317 | P68: =P67*(1+O68) -> 3.0762612 | Q68: =MAX($P$5:P68) -> 3.1505472 | R68: =P68/Q68-1 -> -0.023578776 | S68: =O68-Benchmark_RF!D68 -> 0.01225143
A69: 72 | B69: =Returns!A73 -> 44166 | C69: =IF(Rankings!C71<=2,1,0) -> 0 | D69: =IF(Rankings!D71<=2,1,0) -> 0 | E69: =IF(Rankings!E71<=2,1,0) -> 0 | F69: =IF(Rankings!F71<=2,1,0) -> 1 | G69: =IF(Rankings!G71<=2,1,0) -> 1 | H69: =IF(Rankings!H71<=2,1,0) -> 0 | I69: =IF(Rankings!I71<=2,1,0) -> 0 | J69: =IF(Rankings!J71<=2,1,0) -> 0 | K69: =SUM(C69:J69) -> 2 | L69: =SUMPRODUCT(C69:J69,Returns!B73:I73)/K69 -> 0.064882388 | M69: 0 | N69: 0 | O69: =L69+M69+N69 -> 0.064882388 | P69: =P68*(1+O69) -> 3.2758564 | Q69: =MAX($P$5:P69) -> 3.2758564 | R69: =P69/Q69-1 -> 0 | S69: =O69-Benchmark_RF!D69 -> 0.059142912
A70: 73 | B70: =Returns!A74 -> 44197 | C70: =IF(Rankings!C71<=2,1,0) -> 0 | D70: =IF(Rankings!D71<=2,1,0) -> 0 | E70: =IF(Rankings!E71<=2,1,0) -> 0 | F70: =IF(Rankings!F71<=2,1,0) -> 1 | G70: =IF(Rankings!G71<=2,1,0) -> 1 | H70: =IF(Rankings!H71<=2,1,0) -> 0 | I70: =IF(Rankings!I71<=2,1,0) -> 0 | J70: =IF(Rankings!J71<=2,1,0) -> 0 | K70: =SUM(C70:J70) -> 2 | L70: =SUMPRODUCT(C70:J70,Returns!B74:I74)/K70 -> 0.035451277 | M70: 0 | N70: 0 | O70: =L70+M70+N70 -> 0.035451277 | P70: =P69*(1+O70) -> 3.3919897 | Q70: =MAX($P$5:P70) -> 3.3919897 | R70: =P70/Q70-1 -> 0 | S70: =O70-Benchmark_RF!D70 -> 0.029678395
A71: 74 | B71: =Returns!A75 -> 44228 | C71: =IF(Rankings!C71<=2,1,0) -> 0 | D71: =IF(Rankings!D71<=2,1,0) -> 0 | E71: =IF(Rankings!E71<=2,1,0) -> 0 | F71: =IF(Rankings!F71<=2,1,0) -> 1 | G71: =IF(Rankings!G71<=2,1,0) -> 1 | H71: =IF(Rankings!H71<=2,1,0) -> 0 | I71: =IF(Rankings!I71<=2,1,0) -> 0 | J71: =IF(Rankings!J71<=2,1,0) -> 0 | K71: =SUM(C71:J71) -> 2 | L71: =SUMPRODUCT(C71:J71,Returns!B75:I75)/K71 -> 0.083648968 | M71: 0 | N71: 0 | O71: =L71+M71+N71 -> 0.083648968 | P71: =P70*(1+O71) -> 3.6757261 | Q71: =MAX($P$5:P71) -> 3.6757261 | R71: =P71/Q71-1 -> 0 | S71: =O71-Benchmark_RF!D71 -> 0.077845663
A72: 75 | B72: =Returns!A76 -> 44256 | C72: =IF(Rankings!C71<=2,1,0) -> 0 | D72: =IF(Rankings!D71<=2,1,0) -> 0 | E72: =IF(Rankings!E71<=2,1,0) -> 0 | F72: =IF(Rankings!F71<=2,1,0) -> 1 | G72: =IF(Rankings!G71<=2,1,0) -> 1 | H72: =IF(Rankings!H71<=2,1,0) -> 0 | I72: =IF(Rankings!I71<=2,1,0) -> 0 | J72: =IF(Rankings!J71<=2,1,0) -> 0 | K72: =SUM(C72:J72) -> 2 | L72: =SUMPRODUCT(C72:J72,Returns!B76:I76)/K72 -> -0.067175659 | M72: 0 | N72: 0 | O72: =L72+M72+N72 -> -0.067175659 | P72: =P71*(1+O72) -> 3.4288068 | Q72: =MAX($P$5:P72) -> 3.6757261 | R72: =P72/Q72-1 -> -0.067175659 | S72: =O72-Benchmark_RF!D72 -> -0.073165814
A73: 76 | B73: =Returns!A77 -> 44287 | C73: =IF(Rankings!C71<=2,1,0) -> 0 | D73: =IF(Rankings!D71<=2,1,0) -> 0 | E73: =IF(Rankings!E71<=2,1,0) -> 0 | F73: =IF(Rankings!F71<=2,1,0) -> 1 | G73: =IF(Rankings!G71<=2,1,0) -> 1 | H73: =IF(Rankings!H71<=2,1,0) -> 0 | I73: =IF(Rankings!I71<=2,1,0) -> 0 | J73: =IF(Rankings!J71<=2,1,0) -> 0 | K73: =SUM(C73:J73) -> 2 | L73: =SUMPRODUCT(C73:J73,Returns!B77:I77)/K73 -> -0.016699703 | M73: 0 | N73: 0 | O73: =L73+M73+N73 -> -0.016699703 | P73: =P72*(1+O73) -> 3.3715467 | Q73: =MAX($P$5:P73) -> 3.6757261 | R73: =P73/Q73-1 -> -0.082753549 | S73: =O73-Benchmark_RF!D73 -> -0.0226481
A74: 77 | B74: =Returns!A78 -> 44317 | C74: =IF(Rankings!C71<=2,1,0) -> 0 | D74: =IF(Rankings!D71<=2,1,0) -> 0 | E74: =IF(Rankings!E71<=2,1,0) -> 0 | F74: =IF(Rankings!F71<=2,1,0) -> 1 | G74: =IF(Rankings!G71<=2,1,0) -> 1 | H74: =IF(Rankings!H71<=2,1,0) -> 0 | I74: =IF(Rankings!I71<=2,1,0) -> 0 | J74: =IF(Rankings!J71<=2,1,0) -> 0 | K74: =SUM(C74:J74) -> 2 | L74: =SUMPRODUCT(C74:J74,Returns!B78:I78)/K74 -> 0.067279603 | M74: 0 | N74: 0 | O74: =L74+M74+N74 -> 0.067279603 | P74: =P73*(1+O74) -> 3.598383 | Q74: =MAX($P$5:P74) -> 3.6757261 | R74: =P74/Q74-1 -> -0.021041572 | S74: =O74-Benchmark_RF!D74 -> 0.061357988
A75: 78 | B75: =Returns!A79 -> 44348 | C75: =IF(Rankings!C71<=2,1,0) -> 0 | D75: =IF(Rankings!D71<=2,1,0) -> 0 | E75: =IF(Rankings!E71<=2,1,0) -> 0 | F75: =IF(Rankings!F71<=2,1,0) -> 1 | G75: =IF(Rankings!G71<=2,1,0) -> 1 | H75: =IF(Rankings!H71<=2,1,0) -> 0 | I75: =IF(Rankings!I71<=2,1,0) -> 0 | J75: =IF(Rankings!J71<=2,1,0) -> 0 | K75: =SUM(C75:J75) -> 2 | L75: =SUMPRODUCT(C75:J75,Returns!B79:I79)/K75 -> -0.051009812 | M75: 0 | N75: 0 | O75: =L75+M75+N75 -> -0.051009812 | P75: =P74*(1+O75) -> 3.4148302 | Q75: =MAX($P$5:P75) -> 3.6757261 | R75: =P75/Q75-1 -> -0.070978058 | S75: =O75-Benchmark_RF!D75 -> -0.05689495
A76: 79 | B76: =Returns!A80 -> 44378 | C76: =IF(Rankings!C71<=2,1,0) -> 0 | D76: =IF(Rankings!D71<=2,1,0) -> 0 | E76: =IF(Rankings!E71<=2,1,0) -> 0 | F76: =IF(Rankings!F71<=2,1,0) -> 1 | G76: =IF(Rankings!G71<=2,1,0) -> 1 | H76: =IF(Rankings!H71<=2,1,0) -> 0 | I76: =IF(Rankings!I71<=2,1,0) -> 0 | J76: =IF(Rankings!J71<=2,1,0) -> 0 | K76: =SUM(C76:J76) -> 2 | L76: =SUMPRODUCT(C76:J76,Returns!B80:I80)/K76 -> 0.013544668 | M76: 0 | N76: 0 | O76: =L76+M76+N76 -> 0.013544668 | P76: =P75*(1+O76) -> 3.4610829 | Q76: =MAX($P$5:P76) -> 3.6757261 | R76: =P76/Q76-1 -> -0.058394764 | S76: =O76-Benchmark_RF!D76 -> 0.0077086049
A77: 80 | B77: =Returns!A81 -> 44409 | C77: =IF(Rankings!C83<=2,1,0) -> 0 | D77: =IF(Rankings!D83<=2,1,0) -> 1 | E77: =IF(Rankings!E83<=2,1,0) -> 0 | F77: =IF(Rankings!F83<=2,1,0) -> 1 | G77: =IF(Rankings!G83<=2,1,0) -> 0 | H77: =IF(Rankings!H83<=2,1,0) -> 0 | I77: =IF(Rankings!I83<=2,1,0) -> 0 | J77: =IF(Rankings!J83<=2,1,0) -> 0 | K77: =SUM(C77:J77) -> 2 | L77: =SUMPRODUCT(C77:J77,Returns!B81:I81)/K77 -> 0.12659882 | M77: =-2*Assumptions!$B$13 -> -0.007 | N77: =-Assumptions!$B$16*MAX(0,(1+O65)*(1+O66)*(1+O67)*(1+O68)*(1+O69)*(1+O70)*(1+O71)*(1+O72)*(1+O73)*(1+O74)*(1+O75)*(1+O76)-1) -> -0.022222706 | O77: =L77+M77+N77 -> 0.097376116 | P77: =P76*(1+O77) -> 3.7981098 | Q77: =MAX($P$5:P77) -> 3.7981098 | R77: =P77/Q77-1 -> 0 | S77: =O77-Benchmark_RF!D77 -> 0.091542555
A78: 81 | B78: =Returns!A82 -> 44440 | C78: =IF(Rankings!C83<=2,1,0) -> 0 | D78: =IF(Rankings!D83<=2,1,0) -> 1 | E78: =IF(Rankings!E83<=2,1,0) -> 0 | F78: =IF(Rankings!F83<=2,1,0) -> 1 | G78: =IF(Rankings!G83<=2,1,0) -> 0 | H78: =IF(Rankings!H83<=2,1,0) -> 0 | I78: =IF(Rankings!I83<=2,1,0) -> 0 | J78: =IF(Rankings!J83<=2,1,0) -> 0 | K78: =SUM(C78:J78) -> 2 | L78: =SUMPRODUCT(C78:J78,Returns!B82:I82)/K78 -> -0.014243458 | M78: 0 | N78: 0 | O78: =L78+M78+N78 -> -0.014243458 | P78: =P77*(1+O78) -> 3.7440115 | Q78: =MAX($P$5:P78) -> 3.7981098 | R78: =P78/Q78-1 -> -0.014243458 | S78: =O78-Benchmark_RF!D78 -> -0.02034381
A79: 82 | B79: =Returns!A83 -> 44470 | C79: =IF(Rankings!C83<=2,1,0) -> 0 | D79: =IF(Rankings!D83<=2,1,0) -> 1 | E79: =IF(Rankings!E83<=2,1,0) -> 0 | F79: =IF(Rankings!F83<=2,1,0) -> 1 | G79: =IF(Rankings!G83<=2,1,0) -> 0 | H79: =IF(Rankings!H83<=2,1,0) -> 0 | I79: =IF(Rankings!I83<=2,1,0) -> 0 | J79: =IF(Rankings!J83<=2,1,0) -> 0 | K79: =SUM(C79:J79) -> 2 | L79: =SUMPRODUCT(C79:J79,Returns!B83:I83)/K79 -> 0.011311984 | M79: 0 | N79: 0 | O79: =L79+M79+N79 -> 0.011311984 | P79: =P78*(1+O79) -> 3.7863637 | Q79: =MAX($P$5:P79) -> 3.7981098 | R79: =P79/Q79-1 -> -0.0030925953 | S79: =O79-Benchmark_RF!D79 -> 0.0047423106
A80: 83 | B80: =Returns!A84 -> 44501 | C80: =IF(Rankings!C83<=2,1,0) -> 0 | D80: =IF(Rankings!D83<=2,1,0) -> 1 | E80: =IF(Rankings!E83<=2,1,0) -> 0 | F80: =IF(Rankings!F83<=2,1,0) -> 1 | G80: =IF(Rankings!G83<=2,1,0) -> 0 | H80: =IF(Rankings!H83<=2,1,0) -> 0 | I80: =IF(Rankings!I83<=2,1,0) -> 0 | J80: =IF(Rankings!J83<=2,1,0) -> 0 | K80: =SUM(C80:J80) -> 2 | L80: =SUMPRODUCT(C80:J80,Returns!B84:I84)/K80 -> 0.038785904 | M80: 0 | N80: 0 | O80: =L80+M80+N80 -> 0.038785904 | P80: =P79*(1+O80) -> 3.9332213 | Q80: =MAX($P$5:P80) -> 3.9332213 | R80: =P80/Q80-1 -> 0 | S80: =O80-Benchmark_RF!D80 -> 0.031964179
A81: 84 | B81: =Returns!A85 -> 44531 | C81: =IF(Rankings!C83<=2,1,0) -> 0 | D81: =IF(Rankings!D83<=2,1,0) -> 1 | E81: =IF(Rankings!E83<=2,1,0) -> 0 | F81: =IF(Rankings!F83<=2,1,0) -> 1 | G81: =IF(Rankings!G83<=2,1,0) -> 0 | H81: =IF(Rankings!H83<=2,1,0) -> 0 | I81: =IF(Rankings!I83<=2,1,0) -> 0 | J81: =IF(Rankings!J83<=2,1,0) -> 0 | K81: =SUM(C81:J81) -> 2 | L81: =SUMPRODUCT(C81:J81,Returns!B85:I85)/K81 -> -0.061568833 | M81: 0 | N81: 0 | O81: =L81+M81+N81 -> -0.061568833 | P81: =P80*(1+O81) -> 3.6910574 | Q81: =MAX($P$5:P81) -> 3.9332213 | R81: =P81/Q81-1 -> -0.061568833 | S81: =O81-Benchmark_RF!D81 -> -0.069838246
A82: 85 | B82: =Returns!A86 -> 44562 | C82: =IF(Rankings!C83<=2,1,0) -> 0 | D82: =IF(Rankings!D83<=2,1,0) -> 1 | E82: =IF(Rankings!E83<=2,1,0) -> 0 | F82: =IF(Rankings!F83<=2,1,0) -> 1 | G82: =IF(Rankings!G83<=2,1,0) -> 0 | H82: =IF(Rankings!H83<=2,1,0) -> 0 | I82: =IF(Rankings!I83<=2,1,0) -> 0 | J82: =IF(Rankings!J83<=2,1,0) -> 0 | K82: =SUM(C82:J82) -> 2 | L82: =SUMPRODUCT(C82:J82,Returns!B86:I86)/K82 -> 0.036339795 | M82: 0 | N82: 0 | O82: =L82+M82+N82 -> 0.036339795 | P82: =P81*(1+O82) -> 3.8251897 | Q82: =MAX($P$5:P82) -> 3.9332213 | R82: =P82/Q82-1 -> -0.027466437 | S82: =O82-Benchmark_RF!D82 -> 0.028210771
A83: 86 | B83: =Returns!A87 -> 44593 | C83: =IF(Rankings!C83<=2,1,0) -> 0 | D83: =IF(Rankings!D83<=2,1,0) -> 1 | E83: =IF(Rankings!E83<=2,1,0) -> 0 | F83: =IF(Rankings!F83<=2,1,0) -> 1 | G83: =IF(Rankings!G83<=2,1,0) -> 0 | H83: =IF(Rankings!H83<=2,1,0) -> 0 | I83: =IF(Rankings!I83<=2,1,0) -> 0 | J83: =IF(Rankings!J83<=2,1,0) -> 0 | K83: =SUM(C83:J83) -> 2 | L83: =SUMPRODUCT(C83:J83,Returns!B87:I87)/K83 -> -0.0025289841 | M83: 0 | N83: 0 | O83: =L83+M83+N83 -> -0.0025289841 | P83: =P82*(1+O83) -> 3.8155159 | Q83: =MAX($P$5:P83) -> 3.9332213 | R83: =P83/Q83-1 -> -0.029925959 | S83: =O83-Benchmark_RF!D83 -> -0.010795581
A84: 87 | B84: =Returns!A88 -> 44621 | C84: =IF(Rankings!C83<=2,1,0) -> 0 | D84: =IF(Rankings!D83<=2,1,0) -> 1 | E84: =IF(Rankings!E83<=2,1,0) -> 0 | F84: =IF(Rankings!F83<=2,1,0) -> 1 | G84: =IF(Rankings!G83<=2,1,0) -> 0 | H84: =IF(Rankings!H83<=2,1,0) -> 0 | I84: =IF(Rankings!I83<=2,1,0) -> 0 | J84: =IF(Rankings!J83<=2,1,0) -> 0 | K84: =SUM(C84:J84) -> 2 | L84: =SUMPRODUCT(C84:J84,Returns!B88:I88)/K84 -> -0.068034692 | M84: 0 | N84: 0 | O84: =L84+M84+N84 -> -0.068034692 | P84: =P83*(1+O84) -> 3.5559284 | Q84: =MAX($P$5:P84) -> 3.9332213 | R84: =P84/Q84-1 -> -0.095924647 | S84: =O84-Benchmark_RF!D84 -> -0.077335967
A85: 88 | B85: =Returns!A89 -> 44652 | C85: =IF(Rankings!C83<=2,1,0) -> 0 | D85: =IF(Rankings!D83<=2,1,0) -> 1 | E85: =IF(Rankings!E83<=2,1,0) -> 0 | F85: =IF(Rankings!F83<=2,1,0) -> 1 | G85: =IF(Rankings!G83<=2,1,0) -> 0 | H85: =IF(Rankings!H83<=2,1,0) -> 0 | I85: =IF(Rankings!I83<=2,1,0) -> 0 | J85: =IF(Rankings!J83<=2,1,0) -> 0 | K85: =SUM(C85:J85) -> 2 | L85: =SUMPRODUCT(C85:J85,Returns!B89:I89)/K85 -> 0.054192402 | M85: 0 | N85: 0 | O85: =L85+M85+N85 -> 0.054192402 | P85: =P84*(1+O85) -> 3.7486327 | Q85: =MAX($P$5:P85) -> 3.9332213 | R85: =P85/Q85-1 -> -0.046930632 | S85: =O85-Benchmark_RF!D85 -> 0.043070587
A86: 89 | B86: =Returns!A90 -> 44682 | C86: =IF(Rankings!C83<=2,1,0) -> 0 | D86: =IF(Rankings!D83<=2,1,0) -> 1 | E86: =IF(Rankings!E83<=2,1,0) -> 0 | F86: =IF(Rankings!F83<=2,1,0) -> 1 | G86: =IF(Rankings!G83<=2,1,0) -> 0 | H86: =IF(Rankings!H83<=2,1,0) -> 0 | I86: =IF(Rankings!I83<=2,1,0) -> 0 | J86: =IF(Rankings!J83<=2,1,0) -> 0 | K86: =SUM(C86:J86) -> 2 | L86: =SUMPRODUCT(C86:J86,Returns!B90:I90)/K86 -> -0.090351644 | M86: 0 | N86: 0 | O86: =L86+M86+N86 -> -0.090351644 | P86: =P85*(1+O86) -> 3.4099376 | Q86: =MAX($P$5:P86) -> 3.9332213 | R86: =P86/Q86-1 -> -0.13304202 | S86: =O86-Benchmark_RF!D86 -> -0.1016422
A87: 90 | B87: =Returns!A91 -> 44713 | C87: =IF(Rankings!C83<=2,1,0) -> 0 | D87: =IF(Rankings!D83<=2,1,0) -> 1 | E87: =IF(Rankings!E83<=2,1,0) -> 0 | F87: =IF(Rankings!F83<=2,1,0) -> 1 | G87: =IF(Rankings!G83<=2,1,0) -> 0 | H87: =IF(Rankings!H83<=2,1,0) -> 0 | I87: =IF(Rankings!I83<=2,1,0) -> 0 | J87: =IF(Rankings!J83<=2,1,0) -> 0 | K87: =SUM(C87:J87) -> 2 | L87: =SUMPRODUCT(C87:J87,Returns!B91:I91)/K87 -> -0.10886506 | M87: 0 | N87: 0 | O87: =L87+M87+N87 -> -0.10886506 | P87: =P86*(1+O87) -> 3.0387145 | Q87: =MAX($P$5:P87) -> 3.9332213 | R87: =P87/Q87-1 -> -0.22742345 | S87: =O87-Benchmark_RF!D87 -> -0.12063861
A88: 91 | B88: =Returns!A92 -> 44743 | C88: =IF(Rankings!C83<=2,1,0) -> 0 | D88: =IF(Rankings!D83<=2,1,0) -> 1 | E88: =IF(Rankings!E83<=2,1,0) -> 0 | F88: =IF(Rankings!F83<=2,1,0) -> 1 | G88: =IF(Rankings!G83<=2,1,0) -> 0 | H88: =IF(Rankings!H83<=2,1,0) -> 0 | I88: =IF(Rankings!I83<=2,1,0) -> 0 | J88: =IF(Rankings!J83<=2,1,0) -> 0 | K88: =SUM(C88:J88) -> 2 | L88: =SUMPRODUCT(C88:J88,Returns!B92:I92)/K88 -> 0.022401011 | M88: 0 | N88: 0 | O88: =L88+M88+N88 -> 0.022401011 | P88: =P87*(1+O88) -> 3.1067848 | Q88: =MAX($P$5:P88) -> 3.9332213 | R88: =P88/Q88-1 -> -0.21011696 | S88: =O88-Benchmark_RF!D88 -> 0.01022538
A89: 92 | B89: =Returns!A93 -> 44774 | C89: =IF(Rankings!C95<=2,1,0) -> 0 | D89: =IF(Rankings!D95<=2,1,0) -> 0 | E89: =IF(Rankings!E95<=2,1,0) -> 0 | F89: =IF(Rankings!F95<=2,1,0) -> 0 | G89: =IF(Rankings!G95<=2,1,0) -> 1 | H89: =IF(Rankings!H95<=2,1,0) -> 0 | I89: =IF(Rankings!I95<=2,1,0) -> 1 | J89: =IF(Rankings!J95<=2,1,0) -> 0 | K89: =SUM(C89:J89) -> 2 | L89: =SUMPRODUCT(C89:J89,Returns!B93:I93)/K89 -> 0.1654702 | M89: =-2*Assumptions!$B$13 -> -0.007 | N89: =-Assumptions!$B$16*MAX(0,(1+O77)*(1+O78)*(1+O79)*(1+O80)*(1+O81)*(1+O82)*(1+O83)*(1+O84)*(1+O85)*(1+O86)*(1+O87)*(1+O88)-1) -> 0 | O89: =L89+M89+N89 -> 0.1584702 | P89: =P88*(1+O89) -> 3.5991176 | Q89: =MAX($P$5:P89) -> 3.9332213 | R89: =P89/Q89-1 -> -0.08494403 | S89: =O89-Benchmark_RF!D89 -> 0.14622166
A90: 93 | B90: =Returns!A94 -> 44805 | C90: =IF(Rankings!C95<=2,1,0) -> 0 | D90: =IF(Rankings!D95<=2,1,0) -> 0 | E90: =IF(Rankings!E95<=2,1,0) -> 0 | F90: =IF(Rankings!F95<=2,1,0) -> 0 | G90: =IF(Rankings!G95<=2,1,0) -> 1 | H90: =IF(Rankings!H95<=2,1,0) -> 0 | I90: =IF(Rankings!I95<=2,1,0) -> 1 | J90: =IF(Rankings!J95<=2,1,0) -> 0 | K90: =SUM(C90:J90) -> 2 | L90: =SUMPRODUCT(C90:J90,Returns!B94:I94)/K90 -> -0.062547657 | M90: 0 | N90: 0 | O90: =L90+M90+N90 -> -0.062547657 | P90: =P89*(1+O90) -> 3.3740012 | Q90: =MAX($P$5:P90) -> 3.9332213 | R90: =P90/Q90-1 -> -0.14217864 | S90: =O90-Benchmark_RF!D90 -> -0.074970973
A91: 94 | B91: =Returns!A95 -> 44835 | C91: =IF(Rankings!C95<=2,1,0) -> 0 | D91: =IF(Rankings!D95<=2,1,0) -> 0 | E91: =IF(Rankings!E95<=2,1,0) -> 0 | F91: =IF(Rankings!F95<=2,1,0) -> 0 | G91: =IF(Rankings!G95<=2,1,0) -> 1 | H91: =IF(Rankings!H95<=2,1,0) -> 0 | I91: =IF(Rankings!I95<=2,1,0) -> 1 | J91: =IF(Rankings!J95<=2,1,0) -> 0 | K91: =SUM(C91:J91) -> 2 | L91: =SUMPRODUCT(C91:J91,Returns!B95:I95)/K91 -> -0.077449948 | M91: 0 | N91: 0 | O91: =L91+M91+N91 -> -0.077449948 | P91: =P90*(1+O91) -> 3.112685 | Q91: =MAX($P$5:P91) -> 3.9332213 | R91: =P91/Q91-1 -> -0.20861686 | S91: =O91-Benchmark_RF!D91 -> -0.089654753
A92: 95 | B92: =Returns!A96 -> 44866 | C92: =IF(Rankings!C95<=2,1,0) -> 0 | D92: =IF(Rankings!D95<=2,1,0) -> 0 | E92: =IF(Rankings!E95<=2,1,0) -> 0 | F92: =IF(Rankings!F95<=2,1,0) -> 0 | G92: =IF(Rankings!G95<=2,1,0) -> 1 | H92: =IF(Rankings!H95<=2,1,0) -> 0 | I92: =IF(Rankings!I95<=2,1,0) -> 1 | J92: =IF(Rankings!J95<=2,1,0) -> 0 | K92: =SUM(C92:J92) -> 2 | L92: =SUMPRODUCT(C92:J92,Returns!B96:I96)/K92 -> 0.054530775 | M92: 0 | N92: 0 | O92: =L92+M92+N92 -> 0.054530775 | P92: =P91*(1+O92) -> 3.2824221 | Q92: =MAX($P$5:P92) -> 3.9332213 | R92: =P92/Q92-1 -> -0.16546212 | S92: =O92-Benchmark_RF!D92 -> 0.0414478
A93: 96 | B93: =Returns!A97 -> 44896 | C93: =IF(Rankings!C95<=2,1,0) -> 0 | D93: =IF(Rankings!D95<=2,1,0) -> 0 | E93: =IF(Rankings!E95<=2,1,0) -> 0 | F93: =IF(Rankings!F95<=2,1,0) -> 0 | G93: =IF(Rankings!G95<=2,1,0) -> 1 | H93: =IF(Rankings!H95<=2,1,0) -> 0 | I93: =IF(Rankings!I95<=2,1,0) -> 1 | J93: =IF(Rankings!J95<=2,1,0) -> 0 | K93: =SUM(C93:J93) -> 2 | L93: =SUMPRODUCT(C93:J93,Returns!B97:I97)/K93 -> -0.11564626 | M93: 0 | N93: 0 | O93: =L93+M93+N93 -> -0.11564626 | P93: =P92*(1+O93) -> 2.9028223 | Q93: =MAX($P$5:P93) -> 3.9332213 | R93: =P93/Q93-1 -> -0.26197331 | S93: =O93-Benchmark_RF!D93 -> -0.12878701
A94: 97 | B94: =Returns!A98 -> 44927 | C94: =IF(Rankings!C95<=2,1,0) -> 0 | D94: =IF(Rankings!D95<=2,1,0) -> 0 | E94: =IF(Rankings!E95<=2,1,0) -> 0 | F94: =IF(Rankings!F95<=2,1,0) -> 0 | G94: =IF(Rankings!G95<=2,1,0) -> 1 | H94: =IF(Rankings!H95<=2,1,0) -> 0 | I94: =IF(Rankings!I95<=2,1,0) -> 1 | J94: =IF(Rankings!J95<=2,1,0) -> 0 | K94: =SUM(C94:J94) -> 2 | L94: =SUMPRODUCT(C94:J94,Returns!B98:I98)/K94 -> -0.044582199 | M94: 0 | N94: 0 | O94: =L94+M94+N94 -> -0.044582199 | P94: =P93*(1+O94) -> 2.7734081 | Q94: =MAX($P$5:P94) -> 3.9332213 | R94: =P94/Q94-1 -> -0.29487616 | S94: =O94-Benchmark_RF!D94 -> -0.058341655
A95: 98 | B95: =Returns!A99 -> 44958 | C95: =IF(Rankings!C95<=2,1,0) -> 0 | D95: =IF(Rankings!D95<=2,1,0) -> 0 | E95: =IF(Rankings!E95<=2,1,0) -> 0 | F95: =IF(Rankings!F95<=2,1,0) -> 0 | G95: =IF(Rankings!G95<=2,1,0) -> 1 | H95: =IF(Rankings!H95<=2,1,0) -> 0 | I95: =IF(Rankings!I95<=2,1,0) -> 1 | J95: =IF(Rankings!J95<=2,1,0) -> 0 | K95: =SUM(C95:J95) -> 2 | L95: =SUMPRODUCT(C95:J95,Returns!B99:I99)/K95 -> 0.049205697 | M95: 0 | N95: 0 | O95: =L95+M95+N95 -> 0.049205697 | P95: =P94*(1+O95) -> 2.9098756 | Q95: =MAX($P$5:P95) -> 3.9332213 | R95: =P95/Q95-1 -> -0.26018005 | S95: =O95-Benchmark_RF!D95 -> 0.034412373
A96: 99 | B96: =Returns!A100 -> 44986 | C96: =IF(Rankings!C95<=2,1,0) -> 0 | D96: =IF(Rankings!D95<=2,1,0) -> 0 | E96: =IF(Rankings!E95<=2,1,0) -> 0 | F96: =IF(Rankings!F95<=2,1,0) -> 0 | G96: =IF(Rankings!G95<=2,1,0) -> 1 | H96: =IF(Rankings!H95<=2,1,0) -> 0 | I96: =IF(Rankings!I95<=2,1,0) -> 1 | J96: =IF(Rankings!J95<=2,1,0) -> 0 | K96: =SUM(C96:J96) -> 2 | L96: =SUMPRODUCT(C96:J96,Returns!B100:I100)/K96 -> -0.074871415 | M96: 0 | N96: 0 | O96: =L96+M96+N96 -> -0.074871415 | P96: =P95*(1+O96) -> 2.6920091 | Q96: =MAX($P$5:P96) -> 3.9332213 | R96: =P96/Q96-1 -> -0.31557142 | S96: =O96-Benchmark_RF!D96 -> -0.090925257
A97: 100 | B97: =Returns!A101 -> 45017 | C97: =IF(Rankings!C95<=2,1,0) -> 0 | D97: =IF(Rankings!D95<=2,1,0) -> 0 | E97: =IF(Rankings!E95<=2,1,0) -> 0 | F97: =IF(Rankings!F95<=2,1,0) -> 0 | G97: =IF(Rankings!G95<=2,1,0) -> 1 | H97: =IF(Rankings!H95<=2,1,0) -> 0 | I97: =IF(Rankings!I95<=2,1,0) -> 1 | J97: =IF(Rankings!J95<=2,1,0) -> 0 | K97: =SUM(C97:J97) -> 2 | L97: =SUMPRODUCT(C97:J97,Returns!B101:I101)/K97 -> 0.084196039 | M97: 0 | N97: 0 | O97: =L97+M97+N97 -> 0.084196039 | P97: =P96*(1+O97) -> 2.9186656 | Q97: =MAX($P$5:P97) -> 3.9332213 | R97: =P97/Q97-1 -> -0.25794524 | S97: =O97-Benchmark_RF!D97 -> 0.067500965
A98: 101 | B98: =Returns!A102 -> 45047 | C98: =IF(Rankings!C95<=2,1,0) -> 0 | D98: =IF(Rankings!D95<=2,1,0) -> 0 | E98: =IF(Rankings!E95<=2,1,0) -> 0 | F98: =IF(Rankings!F95<=2,1,0) -> 0 | G98: =IF(Rankings!G95<=2,1,0) -> 1 | H98: =IF(Rankings!H95<=2,1,0) -> 0 | I98: =IF(Rankings!I95<=2,1,0) -> 1 | J98: =IF(Rankings!J95<=2,1,0) -> 0 | K98: =SUM(C98:J98) -> 2 | L98: =SUMPRODUCT(C98:J98,Returns!B102:I102)/K98 -> 0.096573365 | M98: 0 | N98: 0 | O98: =L98+M98+N98 -> 0.096573365 | P98: =P97*(1+O98) -> 3.2005309 | Q98: =MAX($P$5:P98) -> 3.9332213 | R98: =P98/Q98-1 -> -0.18628252 | S98: =O98-Benchmark_RF!D98 -> 0.079878292
A99: 102 | B99: =Returns!A103 -> 45078 | C99: =IF(Rankings!C95<=2,1,0) -> 0 | D99: =IF(Rankings!D95<=2,1,0) -> 0 | E99: =IF(Rankings!E95<=2,1,0) -> 0 | F99: =IF(Rankings!F95<=2,1,0) -> 0 | G99: =IF(Rankings!G95<=2,1,0) -> 1 | H99: =IF(Rankings!H95<=2,1,0) -> 0 | I99: =IF(Rankings!I95<=2,1,0) -> 1 | J99: =IF(Rankings!J95<=2,1,0) -> 0 | K99: =SUM(C99:J99) -> 2 | L99: =SUMPRODUCT(C99:J99,Returns!B103:I103)/K99 -> 0.027318771 | M99: 0 | N99: 0 | O99: =L99+M99+N99 -> 0.027318771 | P99: =P98*(1+O99) -> 3.2879655 | Q99: =MAX($P$5:P99) -> 3.9332213 | R99: =P99/Q99-1 -> -0.16405276 | S99: =O99-Benchmark_RF!D99 -> 0.010616752
A100: 103 | B100: =Returns!A104 -> 45108 | C100: =IF(Rankings!C95<=2,1,0) -> 0 | D100: =IF(Rankings!D95<=2,1,0) -> 0 | E100: =IF(Rankings!E95<=2,1,0) -> 0 | F100: =IF(Rankings!F95<=2,1,0) -> 0 | G100: =IF(Rankings!G95<=2,1,0) -> 1 | H100: =IF(Rankings!H95<=2,1,0) -> 0 | I100: =IF(Rankings!I95<=2,1,0) -> 1 | J100: =IF(Rankings!J95<=2,1,0) -> 0 | K100: =SUM(C100:J100) -> 2 | L100: =SUMPRODUCT(C100:J100,Returns!B104:I104)/K100 -> 0.26155482 | M100: 0 | N100: 0 | O100: =L100+M100+N100 -> 0.26155482 | P100: =P99*(1+O100) -> 4.1479487 | Q100: =MAX($P$5:P100) -> 4.1479487 | R100: =P100/Q100-1 -> 0 | S100: =O100-Benchmark_RF!D100 -> 0.24422472
A101: 104 | B101: =Returns!A105 -> 45139 | C101: =IF(Rankings!C107<=2,1,0) -> 0 | D101: =IF(Rankings!D107<=2,1,0) -> 0 | E101: =IF(Rankings!E107<=2,1,0) -> 0 | F101: =IF(Rankings!F107<=2,1,0) -> 1 | G101: =IF(Rankings!G107<=2,1,0) -> 0 | H101: =IF(Rankings!H107<=2,1,0) -> 1 | I101: =IF(Rankings!I107<=2,1,0) -> 0 | J101: =IF(Rankings!J107<=2,1,0) -> 0 | K101: =SUM(C101:J101) -> 2 | L101: =SUMPRODUCT(C101:J101,Returns!B105:I105)/K101 -> -0.091581652 | M101: =-2*Assumptions!$B$13 -> -0.007 | N101: =-Assumptions!$B$16*MAX(0,(1+O89)*(1+O90)*(1+O91)*(1+O92)*(1+O93)*(1+O94)*(1+O95)*(1+O96)*(1+O97)*(1+O98)*(1+O99)*(1+O100)-1) -> -0.050268878 | O101: =L101+M101+N101 -> -0.14885053 | P101: =P100*(1+O101) -> 3.5305243 | Q101: =MAX($P$5:P101) -> 4.1479487 | R101: =P101/Q101-1 -> -0.14885053 | S101: =O101-Benchmark_RF!D101 -> -0.16616172
...

Sheet S_Top2_SemiAnnual
A1: Scenario: Top 2 stocks, SemiAnnual rebalancing (hold 6 months)
A2: Holdings flag in each row = lookup of Rankings at the governing formation-month (decision row), held constant until next rebalance. Decision i -> holding starts month i+1.
A4: Month (j) | B4: Date | C4: OGDC | D4: MEBL | E4: EFERT | F4: MCB | G4: LUCK | H4: FFC | I4: SAZEW | J4: MARI | K4: Held N | L4: Gross Return | M4: Txn Cost | N4: CGT | O4: Net Return | P4: Growth of Rs.1 | Q4: Running Max | R4: Drawdown | S4: Excess Return
A5: 8 | B5: =Returns!A9 -> 42217 | C5: =IF(Rankings!C11<=2,1,0) -> 0 | D5: =IF(Rankings!D11<=2,1,0) -> 0 | E5: =IF(Rankings!E11<=2,1,0) -> 0 | F5: =IF(Rankings!F11<=2,1,0) -> 0 | G5: =IF(Rankings!G11<=2,1,0) -> 1 | H5: =IF(Rankings!H11<=2,1,0) -> 1 | I5: =IF(Rankings!I11<=2,1,0) -> 0 | J5: =IF(Rankings!J11<=2,1,0) -> 0 | K5: =SUM(C5:J5) -> 2 | L5: =SUMPRODUCT(C5:J5,Returns!B9:I9)/K5 -> -0.056681129 | M5: =-2*Assumptions!$B$13 -> -0.007 | N5: 0 | O5: =L5+M5+N5 -> -0.063681129 | P5: =1*(1+O5) -> 0.93631887 | Q5: =MAX($P$5:P5) -> 0.93631887 | R5: =P5/Q5-1 -> 0 | S5: =O5-Benchmark_RF!D5 -> -0.06928106
A6: 9 | B6: =Returns!A10 -> 42248 | C6: =IF(Rankings!C11<=2,1,0) -> 0 | D6: =IF(Rankings!D11<=2,1,0) -> 0 | E6: =IF(Rankings!E11<=2,1,0) -> 0 | F6: =IF(Rankings!F11<=2,1,0) -> 0 | G6: =IF(Rankings!G11<=2,1,0) -> 1 | H6: =IF(Rankings!H11<=2,1,0) -> 1 | I6: =IF(Rankings!I11<=2,1,0) -> 0 | J6: =IF(Rankings!J11<=2,1,0) -> 0 | K6: =SUM(C6:J6) -> 2 | L6: =SUMPRODUCT(C6:J6,Returns!B10:I10)/K6 -> -0.050873779 | M6: 0 | N6: 0 | O6: =L6+M6+N6 -> -0.050873779 | P6: =P5*(1+O6) -> 0.88868479 | Q6: =MAX($P$5:P6) -> 0.93631887 | R6: =P6/Q6-1 -> -0.050873779 | S6: =O6-Benchmark_RF!D6 -> -0.056108962
A7: 10 | B7: =Returns!A11 -> 42278 | C7: =IF(Rankings!C11<=2,1,0) -> 0 | D7: =IF(Rankings!D11<=2,1,0) -> 0 | E7: =IF(Rankings!E11<=2,1,0) -> 0 | F7: =IF(Rankings!F11<=2,1,0) -> 0 | G7: =IF(Rankings!G11<=2,1,0) -> 1 | H7: =IF(Rankings!H11<=2,1,0) -> 1 | I7: =IF(Rankings!I11<=2,1,0) -> 0 | J7: =IF(Rankings!J11<=2,1,0) -> 0 | K7: =SUM(C7:J7) -> 2 | L7: =SUMPRODUCT(C7:J7,Returns!B11:I11)/K7 -> 0.01976487 | M7: 0 | N7: 0 | O7: =L7+M7+N7 -> 0.01976487 | P7: =P6*(1+O7) -> 0.90624953 | Q7: =MAX($P$5:P7) -> 0.93631887 | R7: =P7/Q7-1 -> -0.032114423 | S7: =O7-Benchmark_RF!D7 -> 0.014657635
A8: 11 | B8: =Returns!A12 -> 42309 | C8: =IF(Rankings!C11<=2,1,0) -> 0 | D8: =IF(Rankings!D11<=2,1,0) -> 0 | E8: =IF(Rankings!E11<=2,1,0) -> 0 | F8: =IF(Rankings!F11<=2,1,0) -> 0 | G8: =IF(Rankings!G11<=2,1,0) -> 1 | H8: =IF(Rankings!H11<=2,1,0) -> 1 | I8: =IF(Rankings!I11<=2,1,0) -> 0 | J8: =IF(Rankings!J11<=2,1,0) -> 0 | K8: =SUM(C8:J8) -> 2 | L8: =SUMPRODUCT(C8:J8,Returns!B12:I12)/K8 -> -0.076639329 | M8: 0 | N8: 0 | O8: =L8+M8+N8 -> -0.076639329 | P8: =P7*(1+O8) -> 0.83679517 | Q8: =MAX($P$5:P8) -> 0.93631887 | R8: =P8/Q8-1 -> -0.10629252 | S8: =O8-Benchmark_RF!D8 -> -0.081798001
A9: 12 | B9: =Returns!A13 -> 42339 | C9: =IF(Rankings!C11<=2,1,0) -> 0 | D9: =IF(Rankings!D11<=2,1,0) -> 0 | E9: =IF(Rankings!E11<=2,1,0) -> 0 | F9: =IF(Rankings!F11<=2,1,0) -> 0 | G9: =IF(Rankings!G11<=2,1,0) -> 1 | H9: =IF(Rankings!H11<=2,1,0) -> 1 | I9: =IF(Rankings!I11<=2,1,0) -> 0 | J9: =IF(Rankings!J11<=2,1,0) -> 0 | K9: =SUM(C9:J9) -> 2 | L9: =SUMPRODUCT(C9:J9,Returns!B13:I13)/K9 -> 0.0036517747 | M9: 0 | N9: 0 | O9: =L9+M9+N9 -> 0.0036517747 | P9: =P8*(1+O9) -> 0.83985096 | Q9: =MAX($P$5:P9) -> 0.93631887 | R9: =P9/Q9-1 -> -0.10302891 | S9: =O9-Benchmark_RF!D9 -> -0.0014819305
A10: 13 | B10: =Returns!A14 -> 42370 | C10: =IF(Rankings!C11<=2,1,0) -> 0 | D10: =IF(Rankings!D11<=2,1,0) -> 0 | E10: =IF(Rankings!E11<=2,1,0) -> 0 | F10: =IF(Rankings!F11<=2,1,0) -> 0 | G10: =IF(Rankings!G11<=2,1,0) -> 1 | H10: =IF(Rankings!H11<=2,1,0) -> 1 | I10: =IF(Rankings!I11<=2,1,0) -> 0 | J10: =IF(Rankings!J11<=2,1,0) -> 0 | K10: =SUM(C10:J10) -> 2 | L10: =SUMPRODUCT(C10:J10,Returns!B14:I14)/K10 -> -0.039326761 | M10: 0 | N10: 0 | O10: =L10+M10+N10 -> -0.039326761 | P10: =P9*(1+O10) -> 0.80682234 | Q10: =MAX($P$5:P10) -> 0.93631887 | R10: =P10/Q10-1 -> -0.13830387 | S10: =O10-Benchmark_RF!D10 -> -0.044321964
A11: 14 | B11: =Returns!A15 -> 42401 | C11: =IF(Rankings!C17<=2,1,0) -> 1 | D11: =IF(Rankings!D17<=2,1,0) -> 0 | E11: =IF(Rankings!E17<=2,1,0) -> 0 | F11: =IF(Rankings!F17<=2,1,0) -> 0 | G11: =IF(Rankings!G17<=2,1,0) -> 0 | H11: =IF(Rankings!H17<=2,1,0) -> 0 | I11: =IF(Rankings!I17<=2,1,0) -> 1 | J11: =IF(Rankings!J17<=2,1,0) -> 0 | K11: =SUM(C11:J11) -> 2 | L11: =SUMPRODUCT(C11:J11,Returns!B15:I15)/K11 -> -0.025393423 | M11: =-2*Assumptions!$B$13 -> -0.007 | N11: =-Assumptions!$B$16*MAX(0,(1+O5)*(1+O6)*(1+O7)*(1+O8)*(1+O9)*(1+O10)-1) -> 0 | O11: =L11+M11+N11 -> -0.032393423 | P11: =P10*(1+O11) -> 0.78068661 | Q11: =MAX($P$5:P11) -> 0.93631887 | R11: =P11/Q11-1 -> -0.16621716 | S11: =O11-Benchmark_RF!D11 -> -0.037429954
A12: 15 | B12: =Returns!A16 -> 42430 | C12: =IF(Rankings!C17<=2,1,0) -> 1 | D12: =IF(Rankings!D17<=2,1,0) -> 0 | E12: =IF(Rankings!E17<=2,1,0) -> 0 | F12: =IF(Rankings!F17<=2,1,0) -> 0 | G12: =IF(Rankings!G17<=2,1,0) -> 0 | H12: =IF(Rankings!H17<=2,1,0) -> 0 | I12: =IF(Rankings!I17<=2,1,0) -> 1 | J12: =IF(Rankings!J17<=2,1,0) -> 0 | K12: =SUM(C12:J12) -> 2 | L12: =SUMPRODUCT(C12:J12,Returns!B16:I16)/K12 -> 0.074093776 | M12: 0 | N12: 0 | O12: =L12+M12+N12 -> 0.074093776 | P12: =P11*(1+O12) -> 0.83853063 | Q12: =MAX($P$5:P12) -> 0.93631887 | R12: =P12/Q12-1 -> -0.10443904 | S12: =O12-Benchmark_RF!D12 -> 0.069092263
A13: 16 | B13: =Returns!A17 -> 42461 | C13: =IF(Rankings!C17<=2,1,0) -> 1 | D13: =IF(Rankings!D17<=2,1,0) -> 0 | E13: =IF(Rankings!E17<=2,1,0) -> 0 | F13: =IF(Rankings!F17<=2,1,0) -> 0 | G13: =IF(Rankings!G17<=2,1,0) -> 0 | H13: =IF(Rankings!H17<=2,1,0) -> 0 | I13: =IF(Rankings!I17<=2,1,0) -> 1 | J13: =IF(Rankings!J17<=2,1,0) -> 0 | K13: =SUM(C13:J13) -> 2 | L13: =SUMPRODUCT(C13:J13,Returns!B17:I17)/K13 -> 0.12657556 | M13: 0 | N13: 0 | O13: =L13+M13+N13 -> 0.12657556 | P13: =P12*(1+O13) -> 0.94466811 | Q13: =MAX($P$5:P13) -> 0.94466811 | R13: =P13/Q13-1 -> 0 | S13: =O13-Benchmark_RF!D13 -> 0.12157404
A14: 17 | B14: =Returns!A18 -> 42491 | C14: =IF(Rankings!C17<=2,1,0) -> 1 | D14: =IF(Rankings!D17<=2,1,0) -> 0 | E14: =IF(Rankings!E17<=2,1,0) -> 0 | F14: =IF(Rankings!F17<=2,1,0) -> 0 | G14: =IF(Rankings!G17<=2,1,0) -> 0 | H14: =IF(Rankings!H17<=2,1,0) -> 0 | I14: =IF(Rankings!I17<=2,1,0) -> 1 | J14: =IF(Rankings!J17<=2,1,0) -> 0 | K14: =SUM(C14:J14) -> 2 | L14: =SUMPRODUCT(C14:J14,Returns!B18:I18)/K14 -> -0.0080766836 | M14: 0 | N14: 0 | O14: =L14+M14+N14 -> -0.0080766836 | P14: =P13*(1+O14) -> 0.93703832 | Q14: =MAX($P$5:P14) -> 0.94466811 | R14: =P14/Q14-1 -> -0.0080766836 | S14: =O14-Benchmark_RF!D14 -> -0.012934359
A15: 18 | B15: =Returns!A19 -> 42522 | C15: =IF(Rankings!C17<=2,1,0) -> 1 | D15: =IF(Rankings!D17<=2,1,0) -> 0 | E15: =IF(Rankings!E17<=2,1,0) -> 0 | F15: =IF(Rankings!F17<=2,1,0) -> 0 | G15: =IF(Rankings!G17<=2,1,0) -> 0 | H15: =IF(Rankings!H17<=2,1,0) -> 0 | I15: =IF(Rankings!I17<=2,1,0) -> 1 | J15: =IF(Rankings!J17<=2,1,0) -> 0 | K15: =SUM(C15:J15) -> 2 | L15: =SUMPRODUCT(C15:J15,Returns!B19:I19)/K15 -> -0.005479964 | M15: 0 | N15: 0 | O15: =L15+M15+N15 -> -0.005479964 | P15: =P14*(1+O15) -> 0.93190338 | Q15: =MAX($P$5:P15) -> 0.94466811 | R15: =P15/Q15-1 -> -0.013512388 | S15: =O15-Benchmark_RF!D15 -> -0.010268323
A16: 19 | B16: =Returns!A20 -> 42552 | C16: =IF(Rankings!C17<=2,1,0) -> 1 | D16: =IF(Rankings!D17<=2,1,0) -> 0 | E16: =IF(Rankings!E17<=2,1,0) -> 0 | F16: =IF(Rankings!F17<=2,1,0) -> 0 | G16: =IF(Rankings!G17<=2,1,0) -> 0 | H16: =IF(Rankings!H17<=2,1,0) -> 0 | I16: =IF(Rankings!I17<=2,1,0) -> 1 | J16: =IF(Rankings!J17<=2,1,0) -> 0 | K16: =SUM(C16:J16) -> 2 | L16: =SUMPRODUCT(C16:J16,Returns!B20:I20)/K16 -> 0.022111827 | M16: 0 | N16: 0 | O16: =L16+M16+N16 -> 0.022111827 | P16: =P15*(1+O16) -> 0.95250947 | Q16: =MAX($P$5:P16) -> 0.95250947 | R16: =P16/Q16-1 -> 0 | S16: =O16-Benchmark_RF!D16 -> 0.017412463
A17: 20 | B17: =Returns!A21 -> 42583 | C17: =IF(Rankings!C23<=2,1,0) -> 0 | D17: =IF(Rankings!D23<=2,1,0) -> 0 | E17: =IF(Rankings!E23<=2,1,0) -> 0 | F17: =IF(Rankings!F23<=2,1,0) -> 1 | G17: =IF(Rankings!G23<=2,1,0) -> 0 | H17: =IF(Rankings!H23<=2,1,0) -> 0 | I17: =IF(Rankings!I23<=2,1,0) -> 1 | J17: =IF(Rankings!J23<=2,1,0) -> 0 | K17: =SUM(C17:J17) -> 2 | L17: =SUMPRODUCT(C17:J17,Returns!B21:I21)/K17 -> 0.042663683 | M17: =-2*Assumptions!$B$13 -> -0.007 | N17: =-Assumptions!$B$16*MAX(0,(1+O11)*(1+O12)*(1+O13)*(1+O14)*(1+O15)*(1+O16)-1) -> -0.027085354 | O17: =L17+M17+N17 -> 0.0085783287 | P17: =P16*(1+O17) -> 0.96068041 | Q17: =MAX($P$5:P17) -> 0.96068041 | R17: =P17/Q17-1 -> 0 | S17: =O17-Benchmark_RF!D17 -> 0.0038214438
A18: 21 | B18: =Returns!A22 -> 42614 | C18: =IF(Rankings!C23<=2,1,0) -> 0 | D18: =IF(Rankings!D23<=2,1,0) -> 0 | E18: =IF(Rankings!E23<=2,1,0) -> 0 | F18: =IF(Rankings!F23<=2,1,0) -> 1 | G18: =IF(Rankings!G23<=2,1,0) -> 0 | H18: =IF(Rankings!H23<=2,1,0) -> 0 | I18: =IF(Rankings!I23<=2,1,0) -> 1 | J18: =IF(Rankings!J23<=2,1,0) -> 0 | K18: =SUM(C18:J18) -> 2 | L18: =SUMPRODUCT(C18:J18,Returns!B22:I22)/K18 -> 0.30210015 | M18: 0 | N18: 0 | O18: =L18+M18+N18 -> 0.30210015 | P18: =P17*(1+O18) -> 1.2509021 | Q18: =MAX($P$5:P18) -> 1.2509021 | R18: =P18/Q18-1 -> 0 | S18: =O18-Benchmark_RF!D18 -> 0.29734326
A19: 22 | B19: =Returns!A23 -> 42644 | C19: =IF(Rankings!C23<=2,1,0) -> 0 | D19: =IF(Rankings!D23<=2,1,0) -> 0 | E19: =IF(Rankings!E23<=2,1,0) -> 0 | F19: =IF(Rankings!F23<=2,1,0) -> 1 | G19: =IF(Rankings!G23<=2,1,0) -> 0 | H19: =IF(Rankings!H23<=2,1,0) -> 0 | I19: =IF(Rankings!I23<=2,1,0) -> 1 | J19: =IF(Rankings!J23<=2,1,0) -> 0 | K19: =SUM(C19:J19) -> 2 | L19: =SUMPRODUCT(C19:J19,Returns!B23:I23)/K19 -> 0.10422243 | M19: 0 | N19: 0 | O19: =L19+M19+N19 -> 0.10422243 | P19: =P18*(1+O19) -> 1.3812742 | Q19: =MAX($P$5:P19) -> 1.3812742 | R19: =P19/Q19-1 -> 0 | S19: =O19-Benchmark_RF!D19 -> 0.099449724
A20: 23 | B20: =Returns!A24 -> 42675 | C20: =IF(Rankings!C23<=2,1,0) -> 0 | D20: =IF(Rankings!D23<=2,1,0) -> 0 | E20: =IF(Rankings!E23<=2,1,0) -> 0 | F20: =IF(Rankings!F23<=2,1,0) -> 1 | G20: =IF(Rankings!G23<=2,1,0) -> 0 | H20: =IF(Rankings!H23<=2,1,0) -> 0 | I20: =IF(Rankings!I23<=2,1,0) -> 1 | J20: =IF(Rankings!J23<=2,1,0) -> 0 | K20: =SUM(C20:J20) -> 2 | L20: =SUMPRODUCT(C20:J20,Returns!B24:I24)/K20 -> 0.22200623 | M20: 0 | N20: 0 | O20: =L20+M20+N20 -> 0.22200623 | P20: =P19*(1+O20) -> 1.6879256 | Q20: =MAX($P$5:P20) -> 1.6879256 | R20: =P20/Q20-1 -> 0 | S20: =O20-Benchmark_RF!D20 -> 0.21717819
A21: 24 | B21: =Returns!A25 -> 42705 | C21: =IF(Rankings!C23<=2,1,0) -> 0 | D21: =IF(Rankings!D23<=2,1,0) -> 0 | E21: =IF(Rankings!E23<=2,1,0) -> 0 | F21: =IF(Rankings!F23<=2,1,0) -> 1 | G21: =IF(Rankings!G23<=2,1,0) -> 0 | H21: =IF(Rankings!H23<=2,1,0) -> 0 | I21: =IF(Rankings!I23<=2,1,0) -> 1 | J21: =IF(Rankings!J23<=2,1,0) -> 0 | K21: =SUM(C21:J21) -> 2 | L21: =SUMPRODUCT(C21:J21,Returns!B25:I25)/K21 -> 0.0085534527 | M21: 0 | N21: 0 | O21: =L21+M21+N21 -> 0.0085534527 | P21: =P20*(1+O21) -> 1.7023632 | Q21: =MAX($P$5:P21) -> 1.7023632 | R21: =P21/Q21-1 -> 0 | S21: =O21-Benchmark_RF!D21 -> 0.003713635
A22: 25 | B22: =Returns!A26 -> 42736 | C22: =IF(Rankings!C23<=2,1,0) -> 0 | D22: =IF(Rankings!D23<=2,1,0) -> 0 | E22: =IF(Rankings!E23<=2,1,0) -> 0 | F22: =IF(Rankings!F23<=2,1,0) -> 1 | G22: =IF(Rankings!G23<=2,1,0) -> 0 | H22: =IF(Rankings!H23<=2,1,0) -> 0 | I22: =IF(Rankings!I23<=2,1,0) -> 1 | J22: =IF(Rankings!J23<=2,1,0) -> 0 | K22: =SUM(C22:J22) -> 2 | L22: =SUMPRODUCT(C22:J22,Returns!B26:I26)/K22 -> -0.0048449545 | M22: 0 | N22: 0 | O22: =L22+M22+N22 -> -0.0048449545 | P22: =P21*(1+O22) -> 1.6941153 | Q22: =MAX($P$5:P22) -> 1.7023632 | R22: =P22/Q22-1 -> -0.0048449545 | S22: =O22-Benchmark_RF!D22 -> -0.0096193177
A23: 26 | B23: =Returns!A27 -> 42767 | C23: =IF(Rankings!C29<=2,1,0) -> 1 | D23: =IF(Rankings!D29<=2,1,0) -> 0 | E23: =IF(Rankings!E29<=2,1,0) -> 0 | F23: =IF(Rankings!F29<=2,1,0) -> 0 | G23: =IF(Rankings!G29<=2,1,0) -> 0 | H23: =IF(Rankings!H29<=2,1,0) -> 1 | I23: =IF(Rankings!I29<=2,1,0) -> 0 | J23: =IF(Rankings!J29<=2,1,0) -> 0 | K23: =SUM(C23:J23) -> 2 | L23: =SUMPRODUCT(C23:J23,Returns!B27:I27)/K23 -> -0.044622449 | M23: =-2*Assumptions!$B$13 -> -0.007 | N23: =-Assumptions!$B$16*MAX(0,(1+O17)*(1+O18)*(1+O19)*(1+O20)*(1+O21)*(1+O22)-1) -> -0.11678716 | O23: =L23+M23+N23 -> -0.16840961 | P23: =P22*(1+O23) -> 1.40881 | Q23: =MAX($P$5:P23) -> 1.7023632 | R23: =P23/Q23-1 -> -0.17243863 | S23: =O23-Benchmark_RF!D23 -> -0.1732311
A24: 27 | B24: =Returns!A28 -> 42795 | C24: =IF(Rankings!C29<=2,1,0) -> 1 | D24: =IF(Rankings!D29<=2,1,0) -> 0 | E24: =IF(Rankings!E29<=2,1,0) -> 0 | F24: =IF(Rankings!F29<=2,1,0) -> 0 | G24: =IF(Rankings!G29<=2,1,0) -> 0 | H24: =IF(Rankings!H29<=2,1,0) -> 1 | I24: =IF(Rankings!I29<=2,1,0) -> 0 | J24: =IF(Rankings!J29<=2,1,0) -> 0 | K24: =SUM(C24:J24) -> 2 | L24: =SUMPRODUCT(C24:J24,Returns!B28:I28)/K24 -> -0.045573838 | M24: 0 | N24: 0 | O24: =L24+M24+N24 -> -0.045573838 | P24: =P23*(1+O24) -> 1.3446052 | Q24: =MAX($P$5:P24) -> 1.7023632 | R24: =P24/Q24-1 -> -0.21015378 | S24: =O24-Benchmark_RF!D24 -> -0.050419108
A25: 28 | B25: =Returns!A29 -> 42826 | C25: =IF(Rankings!C29<=2,1,0) -> 1 | D25: =IF(Rankings!D29<=2,1,0) -> 0 | E25: =IF(Rankings!E29<=2,1,0) -> 0 | F25: =IF(Rankings!F29<=2,1,0) -> 0 | G25: =IF(Rankings!G29<=2,1,0) -> 0 | H25: =IF(Rankings!H29<=2,1,0) -> 1 | I25: =IF(Rankings!I29<=2,1,0) -> 0 | J25: =IF(Rankings!J29<=2,1,0) -> 0 | K25: =SUM(C25:J25) -> 2 | L25: =SUMPRODUCT(C25:J25,Returns!B29:I29)/K25 -> -0.016658428 | M25: 0 | N25: 0 | O25: =L25+M25+N25 -> -0.016658428 | P25: =P24*(1+O25) -> 1.3222061 | Q25: =MAX($P$5:P25) -> 1.7023632 | R25: =P25/Q25-1 -> -0.22331138 | S25: =O25-Benchmark_RF!D25 -> -0.021514207
A26: 29 | B26: =Returns!A30 -> 42856 | C26: =IF(Rankings!C29<=2,1,0) -> 1 | D26: =IF(Rankings!D29<=2,1,0) -> 0 | E26: =IF(Rankings!E29<=2,1,0) -> 0 | F26: =IF(Rankings!F29<=2,1,0) -> 0 | G26: =IF(Rankings!G29<=2,1,0) -> 0 | H26: =IF(Rankings!H29<=2,1,0) -> 1 | I26: =IF(Rankings!I29<=2,1,0) -> 0 | J26: =IF(Rankings!J29<=2,1,0) -> 0 | K26: =SUM(C26:J26) -> 2 | L26: =SUMPRODUCT(C26:J26,Returns!B30:I30)/K26 -> 0.071877688 | M26: 0 | N26: 0 | O26: =L26+M26+N26 -> 0.071877688 | P26: =P25*(1+O26) -> 1.4172433 | Q26: =MAX($P$5:P26) -> 1.7023632 | R26: =P26/Q26-1 -> -0.16748479 | S26: =O26-Benchmark_RF!D26 -> 0.067021909
A27: 30 | B27: =Returns!A31 -> 42887 | C27: =IF(Rankings!C29<=2,1,0) -> 1 | D27: =IF(Rankings!D29<=2,1,0) -> 0 | E27: =IF(Rankings!E29<=2,1,0) -> 0 | F27: =IF(Rankings!F29<=2,1,0) -> 0 | G27: =IF(Rankings!G29<=2,1,0) -> 0 | H27: =IF(Rankings!H29<=2,1,0) -> 1 | I27: =IF(Rankings!I29<=2,1,0) -> 0 | J27: =IF(Rankings!J29<=2,1,0) -> 0 | K27: =SUM(C27:J27) -> 2 | L27: =SUMPRODUCT(C27:J27,Returns!B31:I31)/K27 -> -0.17375065 | M27: 0 | N27: 0 | O27: =L27+M27+N27 -> -0.17375065 | P27: =P26*(1+O27) -> 1.1709963 | Q27: =MAX($P$5:P27) -> 1.7023632 | R27: =P27/Q27-1 -> -0.31213485 | S27: =O27-Benchmark_RF!D27 -> -0.17861109
A28: 31 | B28: =Returns!A32 -> 42917 | C28: =IF(Rankings!C29<=2,1,0) -> 1 | D28: =IF(Rankings!D29<=2,1,0) -> 0 | E28: =IF(Rankings!E29<=2,1,0) -> 0 | F28: =IF(Rankings!F29<=2,1,0) -> 0 | G28: =IF(Rankings!G29<=2,1,0) -> 0 | H28: =IF(Rankings!H29<=2,1,0) -> 1 | I28: =IF(Rankings!I29<=2,1,0) -> 0 | J28: =IF(Rankings!J29<=2,1,0) -> 0 | K28: =SUM(C28:J28) -> 2 | L28: =SUMPRODUCT(C28:J28,Returns!B32:I32)/K28 -> 0.041819272 | M28: 0 | N28: 0 | O28: =L28+M28+N28 -> 0.041819272 | P28: =P27*(1+O28) -> 1.2199665 | Q28: =MAX($P$5:P28) -> 1.7023632 | R28: =P28/Q28-1 -> -0.28336883 | S28: =O28-Benchmark_RF!D28 -> 0.03695891
A29: 32 | B29: =Returns!A33 -> 42948 | C29: =IF(Rankings!C35<=2,1,0) -> 0 | D29: =IF(Rankings!D35<=2,1,0) -> 0 | E29: =IF(Rankings!E35<=2,1,0) -> 0 | F29: =IF(Rankings!F35<=2,1,0) -> 0 | G29: =IF(Rankings!G35<=2,1,0) -> 0 | H29: =IF(Rankings!H35<=2,1,0) -> 1 | I29: =IF(Rankings!I35<=2,1,0) -> 1 | J29: =IF(Rankings!J35<=2,1,0) -> 0 | K29: =SUM(C29:J29) -> 2 | L29: =SUMPRODUCT(C29:J29,Returns!B33:I33)/K29 -> -0.21319483 | M29: =-2*Assumptions!$B$13 -> -0.007 | N29: =-Assumptions!$B$16*MAX(0,(1+O23)*(1+O24)*(1+O25)*(1+O26)*(1+O27)*(1+O28)-1) -> 0 | O29: =L29+M29+N29 -> -0.22019483 | P29: =P28*(1+O29) -> 0.95133621 | Q29: =MAX($P$5:P29) -> 1.7023632 | R29: =P29/Q29-1 -> -0.44116731 | S29: =O29-Benchmark_RF!D29 -> -0.22505464
A30: 33 | B30: =Returns!A34 -> 42979 | C30: =IF(Rankings!C35<=2,1,0) -> 0 | D30: =IF(Rankings!D35<=2,1,0) -> 0 | E30: =IF(Rankings!E35<=2,1,0) -> 0 | F30: =IF(Rankings!F35<=2,1,0) -> 0 | G30: =IF(Rankings!G35<=2,1,0) -> 0 | H30: =IF(Rankings!H35<=2,1,0) -> 1 | I30: =IF(Rankings!I35<=2,1,0) -> 1 | J30: =IF(Rankings!J35<=2,1,0) -> 0 | K30: =SUM(C30:J30) -> 2 | L30: =SUMPRODUCT(C30:J30,Returns!B34:I34)/K30 -> 0.10265278 | M30: 0 | N30: 0 | O30: =L30+M30+N30 -> 0.10265278 | P30: =P29*(1+O30) -> 1.0489935 | Q30: =MAX($P$5:P30) -> 1.7023632 | R30: =P30/Q30-1 -> -0.38380158 | S30: =O30-Benchmark_RF!D30 -> 0.09779234
A31: 34 | B31: =Returns!A35 -> 43009 | C31: =IF(Rankings!C35<=2,1,0) -> 0 | D31: =IF(Rankings!D35<=2,1,0) -> 0 | E31: =IF(Rankings!E35<=2,1,0) -> 0 | F31: =IF(Rankings!F35<=2,1,0) -> 0 | G31: =IF(Rankings!G35<=2,1,0) -> 0 | H31: =IF(Rankings!H35<=2,1,0) -> 1 | I31: =IF(Rankings!I35<=2,1,0) -> 1 | J31: =IF(Rankings!J35<=2,1,0) -> 0 | K31: =SUM(C31:J31) -> 2 | L31: =SUMPRODUCT(C31:J31,Returns!B35:I35)/K31 -> -0.045651394 | M31: 0 | N31: 0 | O31: =L31+M31+N31 -> -0.045651394 | P31: =P30*(1+O31) -> 1.0011055 | Q31: =MAX($P$5:P31) -> 1.7023632 | R31: =P31/Q31-1 -> -0.4119319 | S31: =O31-Benchmark_RF!D31 -> -0.050511834
A32: 35 | B32: =Returns!A36 -> 43040 | C32: =IF(Rankings!C35<=2,1,0) -> 0 | D32: =IF(Rankings!D35<=2,1,0) -> 0 | E32: =IF(Rankings!E35<=2,1,0) -> 0 | F32: =IF(Rankings!F35<=2,1,0) -> 0 | G32: =IF(Rankings!G35<=2,1,0) -> 0 | H32: =IF(Rankings!H35<=2,1,0) -> 1 | I32: =IF(Rankings!I35<=2,1,0) -> 1 | J32: =IF(Rankings!J35<=2,1,0) -> 0 | K32: =SUM(C32:J32) -> 2 | L32: =SUMPRODUCT(C32:J32,Returns!B36:I36)/K32 -> 0.25527342 | M32: 0 | N32: 0 | O32: =L32+M32+N32 -> 0.25527342 | P32: =P31*(1+O32) -> 1.2566611 | Q32: =MAX($P$5:P32) -> 1.7023632 | R32: =P32/Q32-1 -> -0.26181374 | S32: =O32-Benchmark_RF!D32 -> 0.25041306
A33: 36 | B33: =Returns!A37 -> 43070 | C33: =IF(Rankings!C35<=2,1,0) -> 0 | D33: =IF(Rankings!D35<=2,1,0) -> 0 | E33: =IF(Rankings!E35<=2,1,0) -> 0 | F33: =IF(Rankings!F35<=2,1,0) -> 0 | G33: =IF(Rankings!G35<=2,1,0) -> 0 | H33: =IF(Rankings!H35<=2,1,0) -> 1 | I33: =IF(Rankings!I35<=2,1,0) -> 1 | J33: =IF(Rankings!J35<=2,1,0) -> 0 | K33: =SUM(C33:J33) -> 2 | L33: =SUMPRODUCT(C33:J33,Returns!B37:I37)/K33 -> -0.029051268 | M33: 0 | N33: 0 | O33: =L33+M33+N33 -> -0.029051268 | P33: =P32*(1+O33) -> 1.2201535 | Q33: =MAX($P$5:P33) -> 1.7023632 | R33: =P33/Q33-1 -> -0.28325899 | S33: =O33-Benchmark_RF!D33 -> -0.033911708
A34: 37 | B34: =Returns!A38 -> 43101 | C34: =IF(Rankings!C35<=2,1,0) -> 0 | D34: =IF(Rankings!D35<=2,1,0) -> 0 | E34: =IF(Rankings!E35<=2,1,0) -> 0 | F34: =IF(Rankings!F35<=2,1,0) -> 0 | G34: =IF(Rankings!G35<=2,1,0) -> 0 | H34: =IF(Rankings!H35<=2,1,0) -> 1 | I34: =IF(Rankings!I35<=2,1,0) -> 1 | J34: =IF(Rankings!J35<=2,1,0) -> 0 | K34: =SUM(C34:J34) -> 2 | L34: =SUMPRODUCT(C34:J34,Returns!B38:I38)/K34 -> 0.058860759 | M34: 0 | N34: 0 | O34: =L34+M34+N34 -> 0.058860759 | P34: =P33*(1+O34) -> 1.2919727 | Q34: =MAX($P$5:P34) -> 1.7023632 | R34: =P34/Q34-1 -> -0.24107107 | S34: =O34-Benchmark_RF!D34 -> 0.053835347
A35: 38 | B35: =Returns!A39 -> 43132 | C35: =IF(Rankings!C41<=2,1,0) -> 0 | D35: =IF(Rankings!D41<=2,1,0) -> 1 | E35: =IF(Rankings!E41<=2,1,0) -> 0 | F35: =IF(Rankings!F41<=2,1,0) -> 0 | G35: =IF(Rankings!G41<=2,1,0) -> 1 | H35: =IF(Rankings!H41<=2,1,0) -> 0 | I35: =IF(Rankings!I41<=2,1,0) -> 0 | J35: =IF(Rankings!J41<=2,1,0) -> 0 | K35: =SUM(C35:J35) -> 2 | L35: =SUMPRODUCT(C35:J35,Returns!B39:I39)/K35 -> -0.024763237 | M35: =-2*Assumptions!$B$13 -> -0.007 | N35: =-Assumptions!$B$16*MAX(0,(1+O29)*(1+O30)*(1+O31)*(1+O32)*(1+O33)*(1+O34)-1) -> -0.0088534589 | O35: =L35+M35+N35 -> -0.040616696 | P35: =P34*(1+O35) -> 1.239497 | Q35: =MAX($P$5:P35) -> 1.7023632 | R35: =P35/Q35-1 -> -0.27189626 | S35: =O35-Benchmark_RF!D35 -> -0.045667498
A36: 39 | B36: =Returns!A40 -> 43160 | C36: =IF(Rankings!C41<=2,1,0) -> 0 | D36: =IF(Rankings!D41<=2,1,0) -> 1 | E36: =IF(Rankings!E41<=2,1,0) -> 0 | F36: =IF(Rankings!F41<=2,1,0) -> 0 | G36: =IF(Rankings!G41<=2,1,0) -> 1 | H36: =IF(Rankings!H41<=2,1,0) -> 0 | I36: =IF(Rankings!I41<=2,1,0) -> 0 | J36: =IF(Rankings!J41<=2,1,0) -> 0 | K36: =SUM(C36:J36) -> 2 | L36: =SUMPRODUCT(C36:J36,Returns!B40:I40)/K36 -> 0.10337764 | M36: 0 | N36: 0 | O36: =L36+M36+N36 -> 0.10337764 | P36: =P35*(1+O36) -> 1.3676333 | Q36: =MAX($P$5:P36) -> 1.7023632 | R36: =P36/Q36-1 -> -0.19662661 | S36: =O36-Benchmark_RF!D36 -> 0.098305633
A37: 40 | B37: =Returns!A41 -> 43191 | C37: =IF(Rankings!C41<=2,1,0) -> 0 | D37: =IF(Rankings!D41<=2,1,0) -> 1 | E37: =IF(Rankings!E41<=2,1,0) -> 0 | F37: =IF(Rankings!F41<=2,1,0) -> 0 | G37: =IF(Rankings!G41<=2,1,0) -> 1 | H37: =IF(Rankings!H41<=2,1,0) -> 0 | I37: =IF(Rankings!I41<=2,1,0) -> 0 | J37: =IF(Rankings!J41<=2,1,0) -> 0 | K37: =SUM(C37:J37) -> 2 | L37: =SUMPRODUCT(C37:J37,Returns!B41:I41)/K37 -> -0.026920272 | M37: 0 | N37: 0 | O37: =L37+M37+N37 -> -0.026920272 | P37: =P36*(1+O37) -> 1.3308162 | Q37: =MAX($P$5:P37) -> 1.7023632 | R37: =P37/Q37-1 -> -0.21825364 | S37: =O37-Benchmark_RF!D37 -> -0.03197478
A38: 41 | B38: =Returns!A42 -> 43221 | C38: =IF(Rankings!C41<=2,1,0) -> 0 | D38: =IF(Rankings!D41<=2,1,0) -> 1 | E38: =IF(Rankings!E41<=2,1,0) -> 0 | F38: =IF(Rankings!F41<=2,1,0) -> 0 | G38: =IF(Rankings!G41<=2,1,0) -> 1 | H38: =IF(Rankings!H41<=2,1,0) -> 0 | I38: =IF(Rankings!I41<=2,1,0) -> 0 | J38: =IF(Rankings!J41<=2,1,0) -> 0 | K38: =SUM(C38:J38) -> 2 | L38: =SUMPRODUCT(C38:J38,Returns!B42:I42)/K38 -> -0.10844159 | M38: 0 | N38: 0 | O38: =L38+M38+N38 -> -0.10844159 | P38: =P37*(1+O38) -> 1.1865004 | Q38: =MAX($P$5:P38) -> 1.7023632 | R38: =P38/Q38-1 -> -0.30302746 | S38: =O38-Benchmark_RF!D38 -> -0.11351312
A39: 42 | B39: =Returns!A43 -> 43252 | C39: =IF(Rankings!C41<=2,1,0) -> 0 | D39: =IF(Rankings!D41<=2,1,0) -> 1 | E39: =IF(Rankings!E41<=2,1,0) -> 0 | F39: =IF(Rankings!F41<=2,1,0) -> 0 | G39: =IF(Rankings!G41<=2,1,0) -> 1 | H39: =IF(Rankings!H41<=2,1,0) -> 0 | I39: =IF(Rankings!I41<=2,1,0) -> 0 | J39: =IF(Rankings!J41<=2,1,0) -> 0 | K39: =SUM(C39:J39) -> 2 | L39: =SUMPRODUCT(C39:J39,Returns!B43:I43)/K39 -> 0.0091904777 | M39: 0 | N39: 0 | O39: =L39+M39+N39 -> 0.0091904777 | P39: =P38*(1+O39) -> 1.1974049 | Q39: =MAX($P$5:P39) -> 1.7023632 | R39: =P39/Q39-1 -> -0.29662195 | S39: =O39-Benchmark_RF!D39 -> 0.003724891
A40: 43 | B40: =Returns!A44 -> 43282 | C40: =IF(Rankings!C41<=2,1,0) -> 0 | D40: =IF(Rankings!D41<=2,1,0) -> 1 | E40: =IF(Rankings!E41<=2,1,0) -> 0 | F40: =IF(Rankings!F41<=2,1,0) -> 0 | G40: =IF(Rankings!G41<=2,1,0) -> 1 | H40: =IF(Rankings!H41<=2,1,0) -> 0 | I40: =IF(Rankings!I41<=2,1,0) -> 0 | J40: =IF(Rankings!J41<=2,1,0) -> 0 | K40: =SUM(C40:J40) -> 2 | L40: =SUMPRODUCT(C40:J40,Returns!B44:I44)/K40 -> 0.091203597 | M40: 0 | N40: 0 | O40: =L40+M40+N40 -> 0.091203597 | P40: =P39*(1+O40) -> 1.3066126 | Q40: =MAX($P$5:P40) -> 1.7023632 | R40: =P40/Q40-1 -> -0.23247134 | S40: =O40-Benchmark_RF!D40 -> 0.084986254
A41: 44 | B41: =Returns!A45 -> 43313 | C41: =IF(Rankings!C47<=2,1,0) -> 1 | D41: =IF(Rankings!D47<=2,1,0) -> 0 | E41: =IF(Rankings!E47<=2,1,0) -> 0 | F41: =IF(Rankings!F47<=2,1,0) -> 0 | G41: =IF(Rankings!G47<=2,1,0) -> 0 | H41: =IF(Rankings!H47<=2,1,0) -> 1 | I41: =IF(Rankings!I47<=2,1,0) -> 0 | J41: =IF(Rankings!J47<=2,1,0) -> 0 | K41: =SUM(C41:J41) -> 2 | L41: =SUMPRODUCT(C41:J41,Returns!B45:I45)/K41 -> -0.0044257353 | M41: =-2*Assumptions!$B$13 -> -0.007 | N41: =-Assumptions!$B$16*MAX(0,(1+O35)*(1+O36)*(1+O37)*(1+O38)*(1+O39)*(1+O40)-1) -> -0.0016997115 | O41: =L41+M41+N41 -> -0.013125447 | P41: =P40*(1+O41) -> 1.2894627 | Q41: =MAX($P$5:P41) -> 1.7023632 | R41: =P41/Q41-1 -> -0.24254549 | S41: =O41-Benchmark_RF!D41 -> -0.019365128
A42: 45 | B42: =Returns!A46 -> 43344 | C42: =IF(Rankings!C47<=2,1,0) -> 1 | D42: =IF(Rankings!D47<=2,1,0) -> 0 | E42: =IF(Rankings!E47<=2,1,0) -> 0 | F42: =IF(Rankings!F47<=2,1,0) -> 0 | G42: =IF(Rankings!G47<=2,1,0) -> 0 | H42: =IF(Rankings!H47<=2,1,0) -> 1 | I42: =IF(Rankings!I47<=2,1,0) -> 0 | J42: =IF(Rankings!J47<=2,1,0) -> 0 | K42: =SUM(C42:J42) -> 2 | L42: =SUMPRODUCT(C42:J42,Returns!B46:I46)/K42 -> 0.0027633255 | M42: 0 | N42: 0 | O42: =L42+M42+N42 -> 0.0027633255 | P42: =P41*(1+O42) -> 1.2930259 | Q42: =MAX($P$5:P42) -> 1.7023632 | R42: =P42/Q42-1 -> -0.2404524 | S42: =O42-Benchmark_RF!D42 -> -0.003476356
A43: 46 | B43: =Returns!A47 -> 43374 | C43: =IF(Rankings!C47<=2,1,0) -> 1 | D43: =IF(Rankings!D47<=2,1,0) -> 0 | E43: =IF(Rankings!E47<=2,1,0) -> 0 | F43: =IF(Rankings!F47<=2,1,0) -> 0 | G43: =IF(Rankings!G47<=2,1,0) -> 0 | H43: =IF(Rankings!H47<=2,1,0) -> 1 | I43: =IF(Rankings!I47<=2,1,0) -> 0 | J43: =IF(Rankings!J47<=2,1,0) -> 0 | K43: =SUM(C43:J43) -> 2 | L43: =SUMPRODUCT(C43:J43,Returns!B47:I47)/K43 -> 0.020208866 | M43: 0 | N43: 0 | O43: =L43+M43+N43 -> 0.020208866 | P43: =P42*(1+O43) -> 1.3191565 | Q43: =MAX($P$5:P43) -> 1.7023632 | R43: =P43/Q43-1 -> -0.2251028 | S43: =O43-Benchmark_RF!D43 -> 0.013161928
A44: 47 | B44: =Returns!A48 -> 43405 | C44: =IF(Rankings!C47<=2,1,0) -> 1 | D44: =IF(Rankings!D47<=2,1,0) -> 0 | E44: =IF(Rankings!E47<=2,1,0) -> 0 | F44: =IF(Rankings!F47<=2,1,0) -> 0 | G44: =IF(Rankings!G47<=2,1,0) -> 0 | H44: =IF(Rankings!H47<=2,1,0) -> 1 | I44: =IF(Rankings!I47<=2,1,0) -> 0 | J44: =IF(Rankings!J47<=2,1,0) -> 0 | K44: =SUM(C44:J44) -> 2 | L44: =SUMPRODUCT(C44:J44,Returns!B48:I48)/K44 -> -0.031861779 | M44: 0 | N44: 0 | O44: =L44+M44+N44 -> -0.031861779 | P44: =P43*(1+O44) -> 1.2771258 | Q44: =MAX($P$5:P44) -> 1.7023632 | R44: =P44/Q44-1 -> -0.24979241 | S44: =O44-Benchmark_RF!D44 -> -0.0389135
A45: 48 | B45: =Returns!A49 -> 43435 | C45: =IF(Rankings!C47<=2,1,0) -> 1 | D45: =IF(Rankings!D47<=2,1,0) -> 0 | E45: =IF(Rankings!E47<=2,1,0) -> 0 | F45: =IF(Rankings!F47<=2,1,0) -> 0 | G45: =IF(Rankings!G47<=2,1,0) -> 0 | H45: =IF(Rankings!H47<=2,1,0) -> 1 | I45: =IF(Rankings!I47<=2,1,0) -> 0 | J45: =IF(Rankings!J47<=2,1,0) -> 0 | K45: =SUM(C45:J45) -> 2 | L45: =SUMPRODUCT(C45:J45,Returns!B49:I49)/K45 -> -0.095163809 | M45: 0 | N45: 0 | O45: =L45+M45+N45 -> -0.095163809 | P45: =P44*(1+O45) -> 1.1555897 | Q45: =MAX($P$5:P45) -> 1.7023632 | R45: =P45/Q45-1 -> -0.32118502 | S45: =O45-Benchmark_RF!D45 -> -0.10336416
A46: 49 | B46: =Returns!A50 -> 43466 | C46: =IF(Rankings!C47<=2,1,0) -> 1 | D46: =IF(Rankings!D47<=2,1,0) -> 0 | E46: =IF(Rankings!E47<=2,1,0) -> 0 | F46: =IF(Rankings!F47<=2,1,0) -> 0 | G46: =IF(Rankings!G47<=2,1,0) -> 0 | H46: =IF(Rankings!H47<=2,1,0) -> 1 | I46: =IF(Rankings!I47<=2,1,0) -> 0 | J46: =IF(Rankings!J47<=2,1,0) -> 0 | K46: =SUM(C46:J46) -> 2 | L46: =SUMPRODUCT(C46:J46,Returns!B50:I50)/K46 -> 0.16000743 | M46: 0 | N46: 0 | O46: =L46+M46+N46 -> 0.16000743 | P46: =P45*(1+O46) -> 1.3404926 | Q46: =MAX($P$5:P46) -> 1.7023632 | R46: =P46/Q46-1 -> -0.21256958 | S46: =O46-Benchmark_RF!D46 -> 0.15180373
A47: 50 | B47: =Returns!A51 -> 43497 | C47: =IF(Rankings!C53<=2,1,0) -> 1 | D47: =IF(Rankings!D53<=2,1,0) -> 0 | E47: =IF(Rankings!E53<=2,1,0) -> 0 | F47: =IF(Rankings!F53<=2,1,0) -> 0 | G47: =IF(Rankings!G53<=2,1,0) -> 1 | H47: =IF(Rankings!H53<=2,1,0) -> 0 | I47: =IF(Rankings!I53<=2,1,0) -> 0 | J47: =IF(Rankings!J53<=2,1,0) -> 0 | K47: =SUM(C47:J47) -> 2 | L47: =SUMPRODUCT(C47:J47,Returns!B51:I51)/K47 -> -0.0058530812 | M47: =-2*Assumptions!$B$13 -> -0.007 | N47: =-Assumptions!$B$16*MAX(0,(1+O41)*(1+O42)*(1+O43)*(1+O44)*(1+O45)*(1+O46)-1) -> -0.0038894493 | O47: =L47+M47+N47 -> -0.016742531 | P47: =P46*(1+O47) -> 1.3180493 | Q47: =MAX($P$5:P47) -> 1.7023632 | R47: =P47/Q47-1 -> -0.22575316 | S47: =O47-Benchmark_RF!D47 -> -0.025135549
A48: 51 | B48: =Returns!A52 -> 43525 | C48: =IF(Rankings!C53<=2,1,0) -> 1 | D48: =IF(Rankings!D53<=2,1,0) -> 0 | E48: =IF(Rankings!E53<=2,1,0) -> 0 | F48: =IF(Rankings!F53<=2,1,0) -> 0 | G48: =IF(Rankings!G53<=2,1,0) -> 1 | H48: =IF(Rankings!H53<=2,1,0) -> 0 | I48: =IF(Rankings!I53<=2,1,0) -> 0 | J48: =IF(Rankings!J53<=2,1,0) -> 0 | K48: =SUM(C48:J48) -> 2 | L48: =SUMPRODUCT(C48:J48,Returns!B52:I52)/K48 -> -0.047397777 | M48: 0 | N48: 0 | O48: =L48+M48+N48 -> -0.047397777 | P48: =P47*(1+O48) -> 1.2555767 | Q48: =MAX($P$5:P48) -> 1.7023632 | R48: =P48/Q48-1 -> -0.26245073 | S48: =O48-Benchmark_RF!D48 -> -0.055785474
A49: 52 | B49: =Returns!A53 -> 43556 | C49: =IF(Rankings!C53<=2,1,0) -> 1 | D49: =IF(Rankings!D53<=2,1,0) -> 0 | E49: =IF(Rankings!E53<=2,1,0) -> 0 | F49: =IF(Rankings!F53<=2,1,0) -> 0 | G49: =IF(Rankings!G53<=2,1,0) -> 1 | H49: =IF(Rankings!H53<=2,1,0) -> 0 | I49: =IF(Rankings!I53<=2,1,0) -> 0 | J49: =IF(Rankings!J53<=2,1,0) -> 0 | K49: =SUM(C49:J49) -> 2 | L49: =SUMPRODUCT(C49:J49,Returns!B53:I53)/K49 -> -0.074289725 | M49: 0 | N49: 0 | O49: =L49+M49+N49 -> -0.074289725 | P49: =P48*(1+O49) -> 1.1623003 | Q49: =MAX($P$5:P49) -> 1.7023632 | R49: =P49/Q49-1 -> -0.31724307 | S49: =O49-Benchmark_RF!D49 -> -0.082986673
A50: 53 | B50: =Returns!A54 -> 43586 | C50: =IF(Rankings!C53<=2,1,0) -> 1 | D50: =IF(Rankings!D53<=2,1,0) -> 0 | E50: =IF(Rankings!E53<=2,1,0) -> 0 | F50: =IF(Rankings!F53<=2,1,0) -> 0 | G50: =IF(Rankings!G53<=2,1,0) -> 1 | H50: =IF(Rankings!H53<=2,1,0) -> 0 | I50: =IF(Rankings!I53<=2,1,0) -> 0 | J50: =IF(Rankings!J53<=2,1,0) -> 0 | K50: =SUM(C50:J50) -> 2 | L50: =SUMPRODUCT(C50:J50,Returns!B54:I54)/K50 -> 0.035703398 | M50: 0 | N50: 0 | O50: =L50+M50+N50 -> 0.035703398 | P50: =P49*(1+O50) -> 1.2037984 | Q50: =MAX($P$5:P50) -> 1.7023632 | R50: =P50/Q50-1 -> -0.29286632 | S50: =O50-Benchmark_RF!D50 -> 0.025783955
A51: 54 | B51: =Returns!A55 -> 43617 | C51: =IF(Rankings!C53<=2,1,0) -> 1 | D51: =IF(Rankings!D53<=2,1,0) -> 0 | E51: =IF(Rankings!E53<=2,1,0) -> 0 | F51: =IF(Rankings!F53<=2,1,0) -> 0 | G51: =IF(Rankings!G53<=2,1,0) -> 1 | H51: =IF(Rankings!H53<=2,1,0) -> 0 | I51: =IF(Rankings!I53<=2,1,0) -> 0 | J51: =IF(Rankings!J53<=2,1,0) -> 0 | K51: =SUM(C51:J51) -> 2 | L51: =SUMPRODUCT(C51:J51,Returns!B55:I55)/K51 -> -0.073022263 | M51: 0 | N51: 0 | O51: =L51+M51+N51 -> -0.073022263 | P51: =P50*(1+O51) -> 1.1158943 | Q51: =MAX($P$5:P51) -> 1.7023632 | R51: =P51/Q51-1 -> -0.34450283 | S51: =O51-Benchmark_RF!D51 -> -0.083063781
A52: 55 | B52: =Returns!A56 -> 43647 | C52: =IF(Rankings!C53<=2,1,0) -> 1 | D52: =IF(Rankings!D53<=2,1,0) -> 0 | E52: =IF(Rankings!E53<=2,1,0) -> 0 | F52: =IF(Rankings!F53<=2,1,0) -> 0 | G52: =IF(Rankings!G53<=2,1,0) -> 1 | H52: =IF(Rankings!H53<=2,1,0) -> 0 | I52: =IF(Rankings!I53<=2,1,0) -> 0 | J52: =IF(Rankings!J53<=2,1,0) -> 0 | K52: =SUM(C52:J52) -> 2 | L52: =SUMPRODUCT(C52:J52,Returns!B56:I56)/K52 -> -0.016037429 | M52: 0 | N52: 0 | O52: =L52+M52+N52 -> -0.016037429 | P52: =P51*(1+O52) -> 1.0979982 | Q52: =MAX($P$5:P52) -> 1.7023632 | R52: =P52/Q52-1 -> -0.35501531 | S52: =O52-Benchmark_RF!D52 -> -0.026828156
A53: 56 | B53: =Returns!A57 -> 43678 | C53: =IF(Rankings!C59<=2,1,0) -> 1 | D53: =IF(Rankings!D59<=2,1,0) -> 0 | E53: =IF(Rankings!E59<=2,1,0) -> 0 | F53: =IF(Rankings!F59<=2,1,0) -> 0 | G53: =IF(Rankings!G59<=2,1,0) -> 1 | H53: =IF(Rankings!H59<=2,1,0) -> 0 | I53: =IF(Rankings!I59<=2,1,0) -> 0 | J53: =IF(Rankings!J59<=2,1,0) -> 0 | K53: =SUM(C53:J53) -> 2 | L53: =SUMPRODUCT(C53:J53,Returns!B57:I57)/K53 -> -0.12575351 | M53: =-2*Assumptions!$B$13 -> -0.007 | N53: =-Assumptions!$B$16*MAX(0,(1+O47)*(1+O48)*(1+O49)*(1+O50)*(1+O51)*(1+O52)-1) -> 0 | O53: =L53+M53+N53 -> -0.13275351 | P53: =P52*(1+O53) -> 0.95223508 | Q53: =MAX($P$5:P53) -> 1.7023632 | R53: =P53/Q53-1 -> -0.4406393 | S53: =O53-Benchmark_RF!D53 -> -0.14354668
A54: 57 | B54: =Returns!A58 -> 43709 | C54: =IF(Rankings!C59<=2,1,0) -> 1 | D54: =IF(Rankings!D59<=2,1,0) -> 0 | E54: =IF(Rankings!E59<=2,1,0) -> 0 | F54: =IF(Rankings!F59<=2,1,0) -> 0 | G54: =IF(Rankings!G59<=2,1,0) -> 1 | H54: =IF(Rankings!H59<=2,1,0) -> 0 | I54: =IF(Rankings!I59<=2,1,0) -> 0 | J54: =IF(Rankings!J59<=2,1,0) -> 0 | K54: =SUM(C54:J54) -> 2 | L54: =SUMPRODUCT(C54:J54,Returns!B58:I58)/K54 -> 0.081285585 | M54: 0 | N54: 0 | O54: =L54+M54+N54 -> 0.081285585 | P54: =P53*(1+O54) -> 1.0296381 | Q54: =MAX($P$5:P54) -> 1.7023632 | R54: =P54/Q54-1 -> -0.39517134 | S54: =O54-Benchmark_RF!D54 -> 0.070515447
A55: 58 | B55: =Returns!A59 -> 43739 | C55: =IF(Rankings!C59<=2,1,0) -> 1 | D55: =IF(Rankings!D59<=2,1,0) -> 0 | E55: =IF(Rankings!E59<=2,1,0) -> 0 | F55: =IF(Rankings!F59<=2,1,0) -> 0 | G55: =IF(Rankings!G59<=2,1,0) -> 1 | H55: =IF(Rankings!H59<=2,1,0) -> 0 | I55: =IF(Rankings!I59<=2,1,0) -> 0 | J55: =IF(Rankings!J59<=2,1,0) -> 0 | K55: =SUM(C55:J55) -> 2 | L55: =SUMPRODUCT(C55:J55,Returns!B59:I59)/K55 -> 0.03024912 | M55: 0 | N55: 0 | O55: =L55+M55+N55 -> 0.03024912 | P55: =P54*(1+O55) -> 1.0607837 | Q55: =MAX($P$5:P55) -> 1.7023632 | R55: =P55/Q55-1 -> -0.3768758 | S55: =O55-Benchmark_RF!D55 -> 0.019825913
A56: 59 | B56: =Returns!A60 -> 43770 | C56: =IF(Rankings!C59<=2,1,0) -> 1 | D56: =IF(Rankings!D59<=2,1,0) -> 0 | E56: =IF(Rankings!E59<=2,1,0) -> 0 | F56: =IF(Rankings!F59<=2,1,0) -> 0 | G56: =IF(Rankings!G59<=2,1,0) -> 1 | H56: =IF(Rankings!H59<=2,1,0) -> 0 | I56: =IF(Rankings!I59<=2,1,0) -> 0 | J56: =IF(Rankings!J59<=2,1,0) -> 0 | K56: =SUM(C56:J56) -> 2 | L56: =SUMPRODUCT(C56:J56,Returns!B60:I60)/K56 -> 0.1128608 | M56: 0 | N56: 0 | O56: =L56+M56+N56 -> 0.1128608 | P56: =P55*(1+O56) -> 1.1805046 | Q56: =MAX($P$5:P56) -> 1.7023632 | R56: =P56/Q56-1 -> -0.3065495 | S56: =O56-Benchmark_RF!D56 -> 0.1022813
A57: 60 | B57: =Returns!A61 -> 43800 | C57: =IF(Rankings!C59<=2,1,0) -> 1 | D57: =IF(Rankings!D59<=2,1,0) -> 0 | E57: =IF(Rankings!E59<=2,1,0) -> 0 | F57: =IF(Rankings!F59<=2,1,0) -> 0 | G57: =IF(Rankings!G59<=2,1,0) -> 1 | H57: =IF(Rankings!H59<=2,1,0) -> 0 | I57: =IF(Rankings!I59<=2,1,0) -> 0 | J57: =IF(Rankings!J59<=2,1,0) -> 0 | K57: =SUM(C57:J57) -> 2 | L57: =SUMPRODUCT(C57:J57,Returns!B61:I61)/K57 -> 0.046760683 | M57: 0 | N57: 0 | O57: =L57+M57+N57 -> 0.046760683 | P57: =P56*(1+O57) -> 1.2357058 | Q57: =MAX($P$5:P57) -> 1.7023632 | R57: =P57/Q57-1 -> -0.27412328 | S57: =O57-Benchmark_RF!D57 -> 0.036192014
A58: 61 | B58: =Returns!A62 -> 43831 | C58: =IF(Rankings!C59<=2,1,0) -> 1 | D58: =IF(Rankings!D59<=2,1,0) -> 0 | E58: =IF(Rankings!E59<=2,1,0) -> 0 | F58: =IF(Rankings!F59<=2,1,0) -> 0 | G58: =IF(Rankings!G59<=2,1,0) -> 1 | H58: =IF(Rankings!H59<=2,1,0) -> 0 | I58: =IF(Rankings!I59<=2,1,0) -> 0 | J58: =IF(Rankings!J59<=2,1,0) -> 0 | K58: =SUM(C58:J58) -> 2 | L58: =SUMPRODUCT(C58:J58,Returns!B62:I62)/K58 -> 0.043506416 | M58: 0 | N58: 0 | O58: =L58+M58+N58 -> 0.043506416 | P58: =P57*(1+O58) -> 1.289467 | Q58: =MAX($P$5:P58) -> 1.7023632 | R58: =P58/Q58-1 -> -0.24254299 | S58: =O58-Benchmark_RF!D58 -> 0.03298059
A59: 62 | B59: =Returns!A63 -> 43862 | C59: =IF(Rankings!C65<=2,1,0) -> 0 | D59: =IF(Rankings!D65<=2,1,0) -> 0 | E59: =IF(Rankings!E65<=2,1,0) -> 0 | F59: =IF(Rankings!F65<=2,1,0) -> 0 | G59: =IF(Rankings!G65<=2,1,0) -> 0 | H59: =IF(Rankings!H65<=2,1,0) -> 0 | I59: =IF(Rankings!I65<=2,1,0) -> 1 | J59: =IF(Rankings!J65<=2,1,0) -> 1 | K59: =SUM(C59:J59) -> 2 | L59: =SUMPRODUCT(C59:J59,Returns!B63:I63)/K59 -> -0.010381829 | M59: =-2*Assumptions!$B$13 -> -0.007 | N59: =-Assumptions!$B$16*MAX(0,(1+O53)*(1+O54)*(1+O55)*(1+O56)*(1+O57)*(1+O58)-1) -> -0.026156976 | O59: =L59+M59+N59 -> -0.043538804 | P59: =P58*(1+O59) -> 1.2333251 | Q59: =MAX($P$5:P59) -> 1.7023632 | R59: =P59/Q59-1 -> -0.27552176 | S59: =O59-Benchmark_RF!D59 -> -0.054059135
A60: 63 | B60: =Returns!A64 -> 43891 | C60: =IF(Rankings!C65<=2,1,0) -> 0 | D60: =IF(Rankings!D65<=2,1,0) -> 0 | E60: =IF(Rankings!E65<=2,1,0) -> 0 | F60: =IF(Rankings!F65<=2,1,0) -> 0 | G60: =IF(Rankings!G65<=2,1,0) -> 0 | H60: =IF(Rankings!H65<=2,1,0) -> 0 | I60: =IF(Rankings!I65<=2,1,0) -> 1 | J60: =IF(Rankings!J65<=2,1,0) -> 1 | K60: =SUM(C60:J60) -> 2 | L60: =SUMPRODUCT(C60:J60,Returns!B64:I64)/K60 -> -0.34875891 | M60: 0 | N60: 0 | O60: =L60+M60+N60 -> -0.34875891 | P60: =P59*(1+O60) -> 0.80319198 | Q60: =MAX($P$5:P60) -> 1.7023632 | R60: =P60/Q60-1 -> -0.52819 | S60: =O60-Benchmark_RF!D60 -> -0.35765799
A61: 64 | B61: =Returns!A65 -> 43922 | C61: =IF(Rankings!C65<=2,1,0) -> 0 | D61: =IF(Rankings!D65<=2,1,0) -> 0 | E61: =IF(Rankings!E65<=2,1,0) -> 0 | F61: =IF(Rankings!F65<=2,1,0) -> 0 | G61: =IF(Rankings!G65<=2,1,0) -> 0 | H61: =IF(Rankings!H65<=2,1,0) -> 0 | I61: =IF(Rankings!I65<=2,1,0) -> 1 | J61: =IF(Rankings!J65<=2,1,0) -> 1 | K61: =SUM(C61:J61) -> 2 | L61: =SUMPRODUCT(C61:J61,Returns!B65:I65)/K61 -> 0.074438786 | M61: 0 | N61: 0 | O61: =L61+M61+N61 -> 0.074438786 | P61: =P60*(1+O61) -> 0.86298062 | Q61: =MAX($P$5:P61) -> 1.7023632 | R61: =P61/Q61-1 -> -0.49306904 | S61: =O61-Benchmark_RF!D61 -> 0.06783872
A62: 65 | B62: =Returns!A66 -> 43952 | C62: =IF(Rankings!C65<=2,1,0) -> 0 | D62: =IF(Rankings!D65<=2,1,0) -> 0 | E62: =IF(Rankings!E65<=2,1,0) -> 0 | F62: =IF(Rankings!F65<=2,1,0) -> 0 | G62: =IF(Rankings!G65<=2,1,0) -> 0 | H62: =IF(Rankings!H65<=2,1,0) -> 0 | I62: =IF(Rankings!I65<=2,1,0) -> 1 | J62: =IF(Rankings!J65<=2,1,0) -> 1 | K62: =SUM(C62:J62) -> 2 | L62: =SUMPRODUCT(C62:J62,Returns!B66:I66)/K62 -> 0.20583769 | M62: 0 | N62: 0 | O62: =L62+M62+N62 -> 0.20583769 | P62: =P61*(1+O62) -> 1.0406146 | Q62: =MAX($P$5:P62) -> 1.7023632 | R62: =P62/Q62-1 -> -0.38872354 | S62: =O62-Benchmark_RF!D62 -> 0.19930998
A63: 66 | B63: =Returns!A67 -> 43983 | C63: =IF(Rankings!C65<=2,1,0) -> 0 | D63: =IF(Rankings!D65<=2,1,0) -> 0 | E63: =IF(Rankings!E65<=2,1,0) -> 0 | F63: =IF(Rankings!F65<=2,1,0) -> 0 | G63: =IF(Rankings!G65<=2,1,0) -> 0 | H63: =IF(Rankings!H65<=2,1,0) -> 0 | I63: =IF(Rankings!I65<=2,1,0) -> 1 | J63: =IF(Rankings!J65<=2,1,0) -> 1 | K63: =SUM(C63:J63) -> 2 | L63: =SUMPRODUCT(C63:J63,Returns!B67:I67)/K63 -> 0.064054108 | M63: 0 | N63: 0 | O63: =L63+M63+N63 -> 0.064054108 | P63: =P62*(1+O63) -> 1.1072702 | Q63: =MAX($P$5:P63) -> 1.7023632 | R63: =P63/Q63-1 -> -0.34956877 | S63: =O63-Benchmark_RF!D63 -> 0.058518462
A64: 67 | B64: =Returns!A68 -> 44013 | C64: =IF(Rankings!C65<=2,1,0) -> 0 | D64: =IF(Rankings!D65<=2,1,0) -> 0 | E64: =IF(Rankings!E65<=2,1,0) -> 0 | F64: =IF(Rankings!F65<=2,1,0) -> 0 | G64: =IF(Rankings!G65<=2,1,0) -> 0 | H64: =IF(Rankings!H65<=2,1,0) -> 0 | I64: =IF(Rankings!I65<=2,1,0) -> 1 | J64: =IF(Rankings!J65<=2,1,0) -> 1 | K64: =SUM(C64:J64) -> 2 | L64: =SUMPRODUCT(C64:J64,Returns!B68:I68)/K64 -> 0.13962737 | M64: 0 | N64: 0 | O64: =L64+M64+N64 -> 0.13962737 | P64: =P63*(1+O64) -> 1.2618754 | Q64: =MAX($P$5:P64) -> 1.7023632 | R64: =P64/Q64-1 -> -0.25875077 | S64: =O64-Benchmark_RF!D64 -> 0.13407243
A65: 68 | B65: =Returns!A69 -> 44044 | C65: =IF(Rankings!C71<=2,1,0) -> 0 | D65: =IF(Rankings!D71<=2,1,0) -> 0 | E65: =IF(Rankings!E71<=2,1,0) -> 0 | F65: =IF(Rankings!F71<=2,1,0) -> 1 | G65: =IF(Rankings!G71<=2,1,0) -> 1 | H65: =IF(Rankings!H71<=2,1,0) -> 0 | I65: =IF(Rankings!I71<=2,1,0) -> 0 | J65: =IF(Rankings!J71<=2,1,0) -> 0 | K65: =SUM(C65:J65) -> 2 | L65: =SUMPRODUCT(C65:J65,Returns!B69:I69)/K65 -> 0.0091443175 | M65: =-2*Assumptions!$B$13 -> -0.007 | N65: =-Assumptions!$B$16*MAX(0,(1+O59)*(1+O60)*(1+O61)*(1+O62)*(1+O63)*(1+O64)-1) -> 0 | O65: =L65+M65+N65 -> 0.0021443175 | P65: =P64*(1+O65) -> 1.2645813 | Q65: =MAX($P$5:P65) -> 1.7023632 | R65: =P65/Q65-1 -> -0.2571613 | S65: =O65-Benchmark_RF!D65 -> -0.0035815427
A66: 69 | B66: =Returns!A70 -> 44075 | C66: =IF(Rankings!C71<=2,1,0) -> 0 | D66: =IF(Rankings!D71<=2,1,0) -> 0 | E66: =IF(Rankings!E71<=2,1,0) -> 0 | F66: =IF(Rankings!F71<=2,1,0) -> 1 | G66: =IF(Rankings!G71<=2,1,0) -> 1 | H66: =IF(Rankings!H71<=2,1,0) -> 0 | I66: =IF(Rankings!I71<=2,1,0) -> 0 | J66: =IF(Rankings!J71<=2,1,0) -> 0 | K66: =SUM(C66:J66) -> 2 | L66: =SUMPRODUCT(C66:J66,Returns!B70:I70)/K66 -> 0.036518222 | M66: 0 | N66: 0 | O66: =L66+M66+N66 -> 0.036518222 | P66: =P65*(1+O66) -> 1.3107615 | Q66: =MAX($P$5:P66) -> 1.7023632 | R66: =P66/Q66-1 -> -0.23003415 | S66: =O66-Benchmark_RF!D66 -> 0.030787119
A67: 70 | B67: =Returns!A71 -> 44105 | C67: =IF(Rankings!C71<=2,1,0) -> 0 | D67: =IF(Rankings!D71<=2,1,0) -> 0 | E67: =IF(Rankings!E71<=2,1,0) -> 0 | F67: =IF(Rankings!F71<=2,1,0) -> 1 | G67: =IF(Rankings!G71<=2,1,0) -> 1 | H67: =IF(Rankings!H71<=2,1,0) -> 0 | I67: =IF(Rankings!I71<=2,1,0) -> 0 | J67: =IF(Rankings!J71<=2,1,0) -> 0 | K67: =SUM(C67:J67) -> 2 | L67: =SUMPRODUCT(C67:J67,Returns!B71:I71)/K67 -> -0.0051337602 | M67: 0 | N67: 0 | O67: =L67+M67+N67 -> -0.0051337602 | P67: =P66*(1+O67) -> 1.3040324 | Q67: =MAX($P$5:P67) -> 1.7023632 | R67: =P67/Q67-1 -> -0.23398697 | S67: =O67-Benchmark_RF!D67 -> -0.010911571
A68: 71 | B68: =Returns!A72 -> 44136 | C68: =IF(Rankings!C71<=2,1,0) -> 0 | D68: =IF(Rankings!D71<=2,1,0) -> 0 | E68: =IF(Rankings!E71<=2,1,0) -> 0 | F68: =IF(Rankings!F71<=2,1,0) -> 1 | G68: =IF(Rankings!G71<=2,1,0) -> 1 | H68: =IF(Rankings!H71<=2,1,0) -> 0 | I68: =IF(Rankings!I71<=2,1,0) -> 0 | J68: =IF(Rankings!J71<=2,1,0) -> 0 | K68: =SUM(C68:J68) -> 2 | L68: =SUMPRODUCT(C68:J68,Returns!B72:I72)/K68 -> 0.018015317 | M68: 0 | N68: 0 | O68: =L68+M68+N68 -> 0.018015317 | P68: =P67*(1+O68) -> 1.327525 | Q68: =MAX($P$5:P68) -> 1.7023632 | R68: =P68/Q68-1 -> -0.220187 | S68: =O68-Benchmark_RF!D68 -> 0.01225143
A69: 72 | B69: =Returns!A73 -> 44166 | C69: =IF(Rankings!C71<=2,1,0) -> 0 | D69: =IF(Rankings!D71<=2,1,0) -> 0 | E69: =IF(Rankings!E71<=2,1,0) -> 0 | F69: =IF(Rankings!F71<=2,1,0) -> 1 | G69: =IF(Rankings!G71<=2,1,0) -> 1 | H69: =IF(Rankings!H71<=2,1,0) -> 0 | I69: =IF(Rankings!I71<=2,1,0) -> 0 | J69: =IF(Rankings!J71<=2,1,0) -> 0 | K69: =SUM(C69:J69) -> 2 | L69: =SUMPRODUCT(C69:J69,Returns!B73:I73)/K69 -> 0.064882388 | M69: 0 | N69: 0 | O69: =L69+M69+N69 -> 0.064882388 | P69: =P68*(1+O69) -> 1.413658 | Q69: =MAX($P$5:P69) -> 1.7023632 | R69: =P69/Q69-1 -> -0.16959087 | S69: =O69-Benchmark_RF!D69 -> 0.059142912
A70: 73 | B70: =Returns!A74 -> 44197 | C70: =IF(Rankings!C71<=2,1,0) -> 0 | D70: =IF(Rankings!D71<=2,1,0) -> 0 | E70: =IF(Rankings!E71<=2,1,0) -> 0 | F70: =IF(Rankings!F71<=2,1,0) -> 1 | G70: =IF(Rankings!G71<=2,1,0) -> 1 | H70: =IF(Rankings!H71<=2,1,0) -> 0 | I70: =IF(Rankings!I71<=2,1,0) -> 0 | J70: =IF(Rankings!J71<=2,1,0) -> 0 | K70: =SUM(C70:J70) -> 2 | L70: =SUMPRODUCT(C70:J70,Returns!B74:I74)/K70 -> 0.035451277 | M70: 0 | N70: 0 | O70: =L70+M70+N70 -> 0.035451277 | P70: =P69*(1+O70) -> 1.4637739 | Q70: =MAX($P$5:P70) -> 1.7023632 | R70: =P70/Q70-1 -> -0.14015181 | S70: =O70-Benchmark_RF!D70 -> 0.029678395
A71: 74 | B71: =Returns!A75 -> 44228 | C71: =IF(Rankings!C77<=2,1,0) -> 1 | D71: =IF(Rankings!D77<=2,1,0) -> 0 | E71: =IF(Rankings!E77<=2,1,0) -> 0 | F71: =IF(Rankings!F77<=2,1,0) -> 0 | G71: =IF(Rankings!G77<=2,1,0) -> 0 | H71: =IF(Rankings!H77<=2,1,0) -> 1 | I71: =IF(Rankings!I77<=2,1,0) -> 0 | J71: =IF(Rankings!J77<=2,1,0) -> 0 | K71: =SUM(C71:J71) -> 2 | L71: =SUMPRODUCT(C71:J71,Returns!B75:I75)/K71 -> -0.006602012 | M71: =-2*Assumptions!$B$13 -> -0.007 | N71: =-Assumptions!$B$16*MAX(0,(1+O65)*(1+O66)*(1+O67)*(1+O68)*(1+O69)*(1+O70)-1) -> -0.023999815 | O71: =L71+M71+N71 -> -0.037601827 | P71: =P70*(1+O71) -> 1.4087334 | Q71: =MAX($P$5:P71) -> 1.7023632 | R71: =P71/Q71-1 -> -0.17248367 | S71: =O71-Benchmark_RF!D71 -> -0.043405133
A72: 75 | B72: =Returns!A76 -> 44256 | C72: =IF(Rankings!C77<=2,1,0) -> 1 | D72: =IF(Rankings!D77<=2,1,0) -> 0 | E72: =IF(Rankings!E77<=2,1,0) -> 0 | F72: =IF(Rankings!F77<=2,1,0) -> 0 | G72: =IF(Rankings!G77<=2,1,0) -> 0 | H72: =IF(Rankings!H77<=2,1,0) -> 1 | I72: =IF(Rankings!I77<=2,1,0) -> 0 | J72: =IF(Rankings!J77<=2,1,0) -> 0 | K72: =SUM(C72:J72) -> 2 | L72: =SUMPRODUCT(C72:J72,Returns!B76:I76)/K72 -> -0.045848372 | M72: 0 | N72: 0 | O72: =L72+M72+N72 -> -0.045848372 | P72: =P71*(1+O72) -> 1.3441452 | Q72: =MAX($P$5:P72) -> 1.7023632 | R72: =P72/Q72-1 -> -0.21042395 | S72: =O72-Benchmark_RF!D72 -> -0.051838527
A73: 76 | B73: =Returns!A77 -> 44287 | C73: =IF(Rankings!C77<=2,1,0) -> 1 | D73: =IF(Rankings!D77<=2,1,0) -> 0 | E73: =IF(Rankings!E77<=2,1,0) -> 0 | F73: =IF(Rankings!F77<=2,1,0) -> 0 | G73: =IF(Rankings!G77<=2,1,0) -> 0 | H73: =IF(Rankings!H77<=2,1,0) -> 1 | I73: =IF(Rankings!I77<=2,1,0) -> 0 | J73: =IF(Rankings!J77<=2,1,0) -> 0 | K73: =SUM(C73:J73) -> 2 | L73: =SUMPRODUCT(C73:J73,Returns!B77:I77)/K73 -> -0.046916446 | M73: 0 | N73: 0 | O73: =L73+M73+N73 -> -0.046916446 | P73: =P72*(1+O73) -> 1.2810827 | Q73: =MAX($P$5:P73) -> 1.7023632 | R73: =P73/Q73-1 -> -0.24746805 | S73: =O73-Benchmark_RF!D73 -> -0.052864843
A74: 77 | B74: =Returns!A78 -> 44317 | C74: =IF(Rankings!C77<=2,1,0) -> 1 | D74: =IF(Rankings!D77<=2,1,0) -> 0 | E74: =IF(Rankings!E77<=2,1,0) -> 0 | F74: =IF(Rankings!F77<=2,1,0) -> 0 | G74: =IF(Rankings!G77<=2,1,0) -> 0 | H74: =IF(Rankings!H77<=2,1,0) -> 1 | I74: =IF(Rankings!I77<=2,1,0) -> 0 | J74: =IF(Rankings!J77<=2,1,0) -> 0 | K74: =SUM(C74:J74) -> 2 | L74: =SUMPRODUCT(C74:J74,Returns!B78:I78)/K74 -> 0.046545788 | M74: 0 | N74: 0 | O74: =L74+M74+N74 -> 0.046545788 | P74: =P73*(1+O74) -> 1.3407117 | Q74: =MAX($P$5:P74) -> 1.7023632 | R74: =P74/Q74-1 -> -0.21244086 | S74: =O74-Benchmark_RF!D74 -> 0.040624173
A75: 78 | B75: =Returns!A79 -> 44348 | C75: =IF(Rankings!C77<=2,1,0) -> 1 | D75: =IF(Rankings!D77<=2,1,0) -> 0 | E75: =IF(Rankings!E77<=2,1,0) -> 0 | F75: =IF(Rankings!F77<=2,1,0) -> 0 | G75: =IF(Rankings!G77<=2,1,0) -> 0 | H75: =IF(Rankings!H77<=2,1,0) -> 1 | I75: =IF(Rankings!I77<=2,1,0) -> 0 | J75: =IF(Rankings!J77<=2,1,0) -> 0 | K75: =SUM(C75:J75) -> 2 | L75: =SUMPRODUCT(C75:J75,Returns!B79:I79)/K75 -> -0.017369022 | M75: 0 | N75: 0 | O75: =L75+M75+N75 -> -0.017369022 | P75: =P74*(1+O75) -> 1.3174249 | Q75: =MAX($P$5:P75) -> 1.7023632 | R75: =P75/Q75-1 -> -0.22611999 | S75: =O75-Benchmark_RF!D75 -> -0.02325416
A76: 79 | B76: =Returns!A80 -> 44378 | C76: =IF(Rankings!C77<=2,1,0) -> 1 | D76: =IF(Rankings!D77<=2,1,0) -> 0 | E76: =IF(Rankings!E77<=2,1,0) -> 0 | F76: =IF(Rankings!F77<=2,1,0) -> 0 | G76: =IF(Rankings!G77<=2,1,0) -> 0 | H76: =IF(Rankings!H77<=2,1,0) -> 1 | I76: =IF(Rankings!I77<=2,1,0) -> 0 | J76: =IF(Rankings!J77<=2,1,0) -> 0 | K76: =SUM(C76:J76) -> 2 | L76: =SUMPRODUCT(C76:J76,Returns!B80:I80)/K76 -> -0.0075474257 | M76: 0 | N76: 0 | O76: =L76+M76+N76 -> -0.0075474257 | P76: =P75*(1+O76) -> 1.3074817 | Q76: =MAX($P$5:P76) -> 1.7023632 | R76: =P76/Q76-1 -> -0.23196079 | S76: =O76-Benchmark_RF!D76 -> -0.013383489
A77: 80 | B77: =Returns!A81 -> 44409 | C77: =IF(Rankings!C83<=2,1,0) -> 0 | D77: =IF(Rankings!D83<=2,1,0) -> 1 | E77: =IF(Rankings!E83<=2,1,0) -> 0 | F77: =IF(Rankings!F83<=2,1,0) -> 1 | G77: =IF(Rankings!G83<=2,1,0) -> 0 | H77: =IF(Rankings!H83<=2,1,0) -> 0 | I77: =IF(Rankings!I83<=2,1,0) -> 0 | J77: =IF(Rankings!J83<=2,1,0) -> 0 | K77: =SUM(C77:J77) -> 2 | L77: =SUMPRODUCT(C77:J77,Returns!B81:I81)/K77 -> 0.12659882 | M77: =-2*Assumptions!$B$13 -> -0.007 | N77: =-Assumptions!$B$16*MAX(0,(1+O71)*(1+O72)*(1+O73)*(1+O74)*(1+O75)*(1+O76)-1) -> 0 | O77: =L77+M77+N77 -> 0.11959882 | P77: =P76*(1+O77) -> 1.463855 | Q77: =MAX($P$5:P77) -> 1.7023632 | R77: =P77/Q77-1 -> -0.1401042 | S77: =O77-Benchmark_RF!D77 -> 0.11376526
A78: 81 | B78: =Returns!A82 -> 44440 | C78: =IF(Rankings!C83<=2,1,0) -> 0 | D78: =IF(Rankings!D83<=2,1,0) -> 1 | E78: =IF(Rankings!E83<=2,1,0) -> 0 | F78: =IF(Rankings!F83<=2,1,0) -> 1 | G78: =IF(Rankings!G83<=2,1,0) -> 0 | H78: =IF(Rankings!H83<=2,1,0) -> 0 | I78: =IF(Rankings!I83<=2,1,0) -> 0 | J78: =IF(Rankings!J83<=2,1,0) -> 0 | K78: =SUM(C78:J78) -> 2 | L78: =SUMPRODUCT(C78:J78,Returns!B82:I82)/K78 -> -0.014243458 | M78: 0 | N78: 0 | O78: =L78+M78+N78 -> -0.014243458 | P78: =P77*(1+O78) -> 1.4430046 | Q78: =MAX($P$5:P78) -> 1.7023632 | R78: =P78/Q78-1 -> -0.15235209 | S78: =O78-Benchmark_RF!D78 -> -0.02034381
A79: 82 | B79: =Returns!A83 -> 44470 | C79: =IF(Rankings!C83<=2,1,0) -> 0 | D79: =IF(Rankings!D83<=2,1,0) -> 1 | E79: =IF(Rankings!E83<=2,1,0) -> 0 | F79: =IF(Rankings!F83<=2,1,0) -> 1 | G79: =IF(Rankings!G83<=2,1,0) -> 0 | H79: =IF(Rankings!H83<=2,1,0) -> 0 | I79: =IF(Rankings!I83<=2,1,0) -> 0 | J79: =IF(Rankings!J83<=2,1,0) -> 0 | K79: =SUM(C79:J79) -> 2 | L79: =SUMPRODUCT(C79:J79,Returns!B83:I83)/K79 -> 0.011311984 | M79: 0 | N79: 0 | O79: =L79+M79+N79 -> 0.011311984 | P79: =P78*(1+O79) -> 1.4593279 | Q79: =MAX($P$5:P79) -> 1.7023632 | R79: =P79/Q79-1 -> -0.14276351 | S79: =O79-Benchmark_RF!D79 -> 0.0047423106
A80: 83 | B80: =Returns!A84 -> 44501 | C80: =IF(Rankings!C83<=2,1,0) -> 0 | D80: =IF(Rankings!D83<=2,1,0) -> 1 | E80: =IF(Rankings!E83<=2,1,0) -> 0 | F80: =IF(Rankings!F83<=2,1,0) -> 1 | G80: =IF(Rankings!G83<=2,1,0) -> 0 | H80: =IF(Rankings!H83<=2,1,0) -> 0 | I80: =IF(Rankings!I83<=2,1,0) -> 0 | J80: =IF(Rankings!J83<=2,1,0) -> 0 | K80: =SUM(C80:J80) -> 2 | L80: =SUMPRODUCT(C80:J80,Returns!B84:I84)/K80 -> 0.038785904 | M80: 0 | N80: 0 | O80: =L80+M80+N80 -> 0.038785904 | P80: =P79*(1+O80) -> 1.5159292 | Q80: =MAX($P$5:P80) -> 1.7023632 | R80: =P80/Q80-1 -> -0.10951482 | S80: =O80-Benchmark_RF!D80 -> 0.031964179
A81: 84 | B81: =Returns!A85 -> 44531 | C81: =IF(Rankings!C83<=2,1,0) -> 0 | D81: =IF(Rankings!D83<=2,1,0) -> 1 | E81: =IF(Rankings!E83<=2,1,0) -> 0 | F81: =IF(Rankings!F83<=2,1,0) -> 1 | G81: =IF(Rankings!G83<=2,1,0) -> 0 | H81: =IF(Rankings!H83<=2,1,0) -> 0 | I81: =IF(Rankings!I83<=2,1,0) -> 0 | J81: =IF(Rankings!J83<=2,1,0) -> 0 | K81: =SUM(C81:J81) -> 2 | L81: =SUMPRODUCT(C81:J81,Returns!B85:I85)/K81 -> -0.061568833 | M81: 0 | N81: 0 | O81: =L81+M81+N81 -> -0.061568833 | P81: =P80*(1+O81) -> 1.4225952 | Q81: =MAX($P$5:P81) -> 1.7023632 | R81: =P81/Q81-1 -> -0.16434096 | S81: =O81-Benchmark_RF!D81 -> -0.069838246
A82: 85 | B82: =Returns!A86 -> 44562 | C82: =IF(Rankings!C83<=2,1,0) -> 0 | D82: =IF(Rankings!D83<=2,1,0) -> 1 | E82: =IF(Rankings!E83<=2,1,0) -> 0 | F82: =IF(Rankings!F83<=2,1,0) -> 1 | G82: =IF(Rankings!G83<=2,1,0) -> 0 | H82: =IF(Rankings!H83<=2,1,0) -> 0 | I82: =IF(Rankings!I83<=2,1,0) -> 0 | J82: =IF(Rankings!J83<=2,1,0) -> 0 | K82: =SUM(C82:J82) -> 2 | L82: =SUMPRODUCT(C82:J82,Returns!B86:I86)/K82 -> 0.036339795 | M82: 0 | N82: 0 | O82: =L82+M82+N82 -> 0.036339795 | P82: =P81*(1+O82) -> 1.474292 | Q82: =MAX($P$5:P82) -> 1.7023632 | R82: =P82/Q82-1 -> -0.13397328 | S82: =O82-Benchmark_RF!D82 -> 0.028210771
A83: 86 | B83: =Returns!A87 -> 44593 | C83: =IF(Rankings!C89<=2,1,0) -> 1 | D83: =IF(Rankings!D89<=2,1,0) -> 0 | E83: =IF(Rankings!E89<=2,1,0) -> 0 | F83: =IF(Rankings!F89<=2,1,0) -> 0 | G83: =IF(Rankings!G89<=2,1,0) -> 0 | H83: =IF(Rankings!H89<=2,1,0) -> 0 | I83: =IF(Rankings!I89<=2,1,0) -> 1 | J83: =IF(Rankings!J89<=2,1,0) -> 0 | K83: =SUM(C83:J83) -> 2 | L83: =SUMPRODUCT(C83:J83,Returns!B87:I87)/K83 -> -0.035272345 | M83: =-2*Assumptions!$B$13 -> -0.007 | N83: =-Assumptions!$B$16*MAX(0,(1+O77)*(1+O78)*(1+O79)*(1+O80)*(1+O81)*(1+O82)-1) -> -0.019137209 | O83: =L83+M83+N83 -> -0.061409554 | P83: =P82*(1+O83) -> 1.3837564 | Q83: =MAX($P$5:P83) -> 1.7023632 | R83: =P83/Q83-1 -> -0.18715559 | S83: =O83-Benchmark_RF!D83 -> -0.069676151
A84: 87 | B84: =Returns!A88 -> 44621 | C84: =IF(Rankings!C89<=2,1,0) -> 1 | D84: =IF(Rankings!D89<=2,1,0) -> 0 | E84: =IF(Rankings!E89<=2,1,0) -> 0 | F84: =IF(Rankings!F89<=2,1,0) -> 0 | G84: =IF(Rankings!G89<=2,1,0) -> 0 | H84: =IF(Rankings!H89<=2,1,0) -> 0 | I84: =IF(Rankings!I89<=2,1,0) -> 1 | J84: =IF(Rankings!J89<=2,1,0) -> 0 | K84: =SUM(C84:J84) -> 2 | L84: =SUMPRODUCT(C84:J84,Returns!B88:I88)/K84 -> -0.0808353 | M84: 0 | N84: 0 | O84: =L84+M84+N84 -> -0.0808353 | P84: =P83*(1+O84) -> 1.2719001 | Q84: =MAX($P$5:P84) -> 1.7023632 | R84: =P84/Q84-1 -> -0.25286211 | S84: =O84-Benchmark_RF!D84 -> -0.090136575
A85: 88 | B85: =Returns!A89 -> 44652 | C85: =IF(Rankings!C89<=2,1,0) -> 1 | D85: =IF(Rankings!D89<=2,1,0) -> 0 | E85: =IF(Rankings!E89<=2,1,0) -> 0 | F85: =IF(Rankings!F89<=2,1,0) -> 0 | G85: =IF(Rankings!G89<=2,1,0) -> 0 | H85: =IF(Rankings!H89<=2,1,0) -> 0 | I85: =IF(Rankings!I89<=2,1,0) -> 1 | J85: =IF(Rankings!J89<=2,1,0) -> 0 | K85: =SUM(C85:J85) -> 2 | L85: =SUMPRODUCT(C85:J85,Returns!B89:I89)/K85 -> 0.010946837 | M85: 0 | N85: 0 | O85: =L85+M85+N85 -> 0.010946837 | P85: =P84*(1+O85) -> 1.2858233 | Q85: =MAX($P$5:P85) -> 1.7023632 | R85: =P85/Q85-1 -> -0.24468332 | S85: =O85-Benchmark_RF!D85 -> -0.00017497831
A86: 89 | B86: =Returns!A90 -> 44682 | C86: =IF(Rankings!C89<=2,1,0) -> 1 | D86: =IF(Rankings!D89<=2,1,0) -> 0 | E86: =IF(Rankings!E89<=2,1,0) -> 0 | F86: =IF(Rankings!F89<=2,1,0) -> 0 | G86: =IF(Rankings!G89<=2,1,0) -> 0 | H86: =IF(Rankings!H89<=2,1,0) -> 0 | I86: =IF(Rankings!I89<=2,1,0) -> 1 | J86: =IF(Rankings!J89<=2,1,0) -> 0 | K86: =SUM(C86:J86) -> 2 | L86: =SUMPRODUCT(C86:J86,Returns!B90:I90)/K86 -> -0.081337537 | M86: 0 | N86: 0 | O86: =L86+M86+N86 -> -0.081337537 | P86: =P85*(1+O86) -> 1.1812376 | Q86: =MAX($P$5:P86) -> 1.7023632 | R86: =P86/Q86-1 -> -0.30611892 | S86: =O86-Benchmark_RF!D86 -> -0.092628096
A87: 90 | B87: =Returns!A91 -> 44713 | C87: =IF(Rankings!C89<=2,1,0) -> 1 | D87: =IF(Rankings!D89<=2,1,0) -> 0 | E87: =IF(Rankings!E89<=2,1,0) -> 0 | F87: =IF(Rankings!F89<=2,1,0) -> 0 | G87: =IF(Rankings!G89<=2,1,0) -> 0 | H87: =IF(Rankings!H89<=2,1,0) -> 0 | I87: =IF(Rankings!I89<=2,1,0) -> 1 | J87: =IF(Rankings!J89<=2,1,0) -> 0 | K87: =SUM(C87:J87) -> 2 | L87: =SUMPRODUCT(C87:J87,Returns!B91:I91)/K87 -> -0.051370918 | M87: 0 | N87: 0 | O87: =L87+M87+N87 -> -0.051370918 | P87: =P86*(1+O87) -> 1.1205564 | Q87: =MAX($P$5:P87) -> 1.7023632 | R87: =P87/Q87-1 -> -0.34176422 | S87: =O87-Benchmark_RF!D87 -> -0.063144466
A88: 91 | B88: =Returns!A92 -> 44743 | C88: =IF(Rankings!C89<=2,1,0) -> 1 | D88: =IF(Rankings!D89<=2,1,0) -> 0 | E88: =IF(Rankings!E89<=2,1,0) -> 0 | F88: =IF(Rankings!F89<=2,1,0) -> 0 | G88: =IF(Rankings!G89<=2,1,0) -> 0 | H88: =IF(Rankings!H89<=2,1,0) -> 0 | I88: =IF(Rankings!I89<=2,1,0) -> 1 | J88: =IF(Rankings!J89<=2,1,0) -> 0 | K88: =SUM(C88:J88) -> 2 | L88: =SUMPRODUCT(C88:J88,Returns!B92:I92)/K88 -> -0.0024643281 | M88: 0 | N88: 0 | O88: =L88+M88+N88 -> -0.0024643281 | P88: =P87*(1+O88) -> 1.117795 | Q88: =MAX($P$5:P88) -> 1.7023632 | R88: =P88/Q88-1 -> -0.34338633 | S88: =O88-Benchmark_RF!D88 -> -0.014639959
A89: 92 | B89: =Returns!A93 -> 44774 | C89: =IF(Rankings!C95<=2,1,0) -> 0 | D89: =IF(Rankings!D95<=2,1,0) -> 0 | E89: =IF(Rankings!E95<=2,1,0) -> 0 | F89: =IF(Rankings!F95<=2,1,0) -> 0 | G89: =IF(Rankings!G95<=2,1,0) -> 1 | H89: =IF(Rankings!H95<=2,1,0) -> 0 | I89: =IF(Rankings!I95<=2,1,0) -> 1 | J89: =IF(Rankings!J95<=2,1,0) -> 0 | K89: =SUM(C89:J89) -> 2 | L89: =SUMPRODUCT(C89:J89,Returns!B93:I93)/K89 -> 0.1654702 | M89: =-2*Assumptions!$B$13 -> -0.007 | N89: =-Assumptions!$B$16*MAX(0,(1+O83)*(1+O84)*(1+O85)*(1+O86)*(1+O87)*(1+O88)-1) -> 0 | O89: =L89+M89+N89 -> 0.1584702 | P89: =P88*(1+O89) -> 1.2949321 | Q89: =MAX($P$5:P89) -> 1.7023632 | R89: =P89/Q89-1 -> -0.23933263 | S89: =O89-Benchmark_RF!D89 -> 0.14622166
A90: 93 | B90: =Returns!A94 -> 44805 | C90: =IF(Rankings!C95<=2,1,0) -> 0 | D90: =IF(Rankings!D95<=2,1,0) -> 0 | E90: =IF(Rankings!E95<=2,1,0) -> 0 | F90: =IF(Rankings!F95<=2,1,0) -> 0 | G90: =IF(Rankings!G95<=2,1,0) -> 1 | H90: =IF(Rankings!H95<=2,1,0) -> 0 | I90: =IF(Rankings!I95<=2,1,0) -> 1 | J90: =IF(Rankings!J95<=2,1,0) -> 0 | K90: =SUM(C90:J90) -> 2 | L90: =SUMPRODUCT(C90:J90,Returns!B94:I94)/K90 -> -0.062547657 | M90: 0 | N90: 0 | O90: =L90+M90+N90 -> -0.062547657 | P90: =P89*(1+O90) -> 1.2139372 | Q90: =MAX($P$5:P90) -> 1.7023632 | R90: =P90/Q90-1 -> -0.28691059 | S90: =O90-Benchmark_RF!D90 -> -0.074970973
A91: 94 | B91: =Returns!A95 -> 44835 | C91: =IF(Rankings!C95<=2,1,0) -> 0 | D91: =IF(Rankings!D95<=2,1,0) -> 0 | E91: =IF(Rankings!E95<=2,1,0) -> 0 | F91: =IF(Rankings!F95<=2,1,0) -> 0 | G91: =IF(Rankings!G95<=2,1,0) -> 1 | H91: =IF(Rankings!H95<=2,1,0) -> 0 | I91: =IF(Rankings!I95<=2,1,0) -> 1 | J91: =IF(Rankings!J95<=2,1,0) -> 0 | K91: =SUM(C91:J91) -> 2 | L91: =SUMPRODUCT(C91:J91,Returns!B95:I95)/K91 -> -0.077449948 | M91: 0 | N91: 0 | O91: =L91+M91+N91 -> -0.077449948 | P91: =P90*(1+O91) -> 1.1199178 | Q91: =MAX($P$5:P91) -> 1.7023632 | R91: =P91/Q91-1 -> -0.34213933 | S91: =O91-Benchmark_RF!D91 -> -0.089654753
A92: 95 | B92: =Returns!A96 -> 44866 | C92: =IF(Rankings!C95<=2,1,0) -> 0 | D92: =IF(Rankings!D95<=2,1,0) -> 0 | E92: =IF(Rankings!E95<=2,1,0) -> 0 | F92: =IF(Rankings!F95<=2,1,0) -> 0 | G92: =IF(Rankings!G95<=2,1,0) -> 1 | H92: =IF(Rankings!H95<=2,1,0) -> 0 | I92: =IF(Rankings!I95<=2,1,0) -> 1 | J92: =IF(Rankings!J95<=2,1,0) -> 0 | K92: =SUM(C92:J92) -> 2 | L92: =SUMPRODUCT(C92:J92,Returns!B96:I96)/K92 -> 0.054530775 | M92: 0 | N92: 0 | O92: =L92+M92+N92 -> 0.054530775 | P92: =P91*(1+O92) -> 1.1809878 | Q92: =MAX($P$5:P92) -> 1.7023632 | R92: =P92/Q92-1 -> -0.30626568 | S92: =O92-Benchmark_RF!D92 -> 0.0414478
A93: 96 | B93: =Returns!A97 -> 44896 | C93: =IF(Rankings!C95<=2,1,0) -> 0 | D93: =IF(Rankings!D95<=2,1,0) -> 0 | E93: =IF(Rankings!E95<=2,1,0) -> 0 | F93: =IF(Rankings!F95<=2,1,0) -> 0 | G93: =IF(Rankings!G95<=2,1,0) -> 1 | H93: =IF(Rankings!H95<=2,1,0) -> 0 | I93: =IF(Rankings!I95<=2,1,0) -> 1 | J93: =IF(Rankings!J95<=2,1,0) -> 0 | K93: =SUM(C93:J93) -> 2 | L93: =SUMPRODUCT(C93:J93,Returns!B97:I97)/K93 -> -0.11564626 | M93: 0 | N93: 0 | O93: =L93+M93+N93 -> -0.11564626 | P93: =P92*(1+O93) -> 1.044411 | Q93: =MAX($P$5:P93) -> 1.7023632 | R93: =P93/Q93-1 -> -0.38649346 | S93: =O93-Benchmark_RF!D93 -> -0.12878701
A94: 97 | B94: =Returns!A98 -> 44927 | C94: =IF(Rankings!C95<=2,1,0) -> 0 | D94: =IF(Rankings!D95<=2,1,0) -> 0 | E94: =IF(Rankings!E95<=2,1,0) -> 0 | F94: =IF(Rankings!F95<=2,1,0) -> 0 | G94: =IF(Rankings!G95<=2,1,0) -> 1 | H94: =IF(Rankings!H95<=2,1,0) -> 0 | I94: =IF(Rankings!I95<=2,1,0) -> 1 | J94: =IF(Rankings!J95<=2,1,0) -> 0 | K94: =SUM(C94:J94) -> 2 | L94: =SUMPRODUCT(C94:J94,Returns!B98:I98)/K94 -> -0.044582199 | M94: 0 | N94: 0 | O94: =L94+M94+N94 -> -0.044582199 | P94: =P93*(1+O94) -> 0.99784883 | Q94: =MAX($P$5:P94) -> 1.7023632 | R94: =P94/Q94-1 -> -0.41384493 | S94: =O94-Benchmark_RF!D94 -> -0.058341655
A95: 98 | B95: =Returns!A99 -> 44958 | C95: =IF(Rankings!C101<=2,1,0) -> 0 | D95: =IF(Rankings!D101<=2,1,0) -> 1 | E95: =IF(Rankings!E101<=2,1,0) -> 0 | F95: =IF(Rankings!F101<=2,1,0) -> 0 | G95: =IF(Rankings!G101<=2,1,0) -> 0 | H95: =IF(Rankings!H101<=2,1,0) -> 0 | I95: =IF(Rankings!I101<=2,1,0) -> 0 | J95: =IF(Rankings!J101<=2,1,0) -> 1 | K95: =SUM(C95:J95) -> 2 | L95: =SUMPRODUCT(C95:J95,Returns!B99:I99)/K95 -> -0.013613933 | M95: =-2*Assumptions!$B$13 -> -0.007 | N95: =-Assumptions!$B$16*MAX(0,(1+O89)*(1+O90)*(1+O91)*(1+O92)*(1+O93)*(1+O94)-1) -> 0 | O95: =L95+M95+N95 -> -0.020613933 | P95: =P94*(1+O95) -> 0.97727924 | Q95: =MAX($P$5:P95) -> 1.7023632 | R95: =P95/Q95-1 -> -0.42592789 | S95: =O95-Benchmark_RF!D95 -> -0.035407258
A96: 99 | B96: =Returns!A100 -> 44986 | C96: =IF(Rankings!C101<=2,1,0) -> 0 | D96: =IF(Rankings!D101<=2,1,0) -> 1 | E96: =IF(Rankings!E101<=2,1,0) -> 0 | F96: =IF(Rankings!F101<=2,1,0) -> 0 | G96: =IF(Rankings!G101<=2,1,0) -> 0 | H96: =IF(Rankings!H101<=2,1,0) -> 0 | I96: =IF(Rankings!I101<=2,1,0) -> 0 | J96: =IF(Rankings!J101<=2,1,0) -> 1 | K96: =SUM(C96:J96) -> 2 | L96: =SUMPRODUCT(C96:J96,Returns!B100:I100)/K96 -> 0.028462974 | M96: 0 | N96: 0 | O96: =L96+M96+N96 -> 0.028462974 | P96: =P95*(1+O96) -> 1.0050955 | Q96: =MAX($P$5:P96) -> 1.7023632 | R96: =P96/Q96-1 -> -0.40958809 | S96: =O96-Benchmark_RF!D96 -> 0.012409132
A97: 100 | B97: =Returns!A101 -> 45017 | C97: =IF(Rankings!C101<=2,1,0) -> 0 | D97: =IF(Rankings!D101<=2,1,0) -> 1 | E97: =IF(Rankings!E101<=2,1,0) -> 0 | F97: =IF(Rankings!F101<=2,1,0) -> 0 | G97: =IF(Rankings!G101<=2,1,0) -> 0 | H97: =IF(Rankings!H101<=2,1,0) -> 0 | I97: =IF(Rankings!I101<=2,1,0) -> 0 | J97: =IF(Rankings!J101<=2,1,0) -> 1 | K97: =SUM(C97:J97) -> 2 | L97: =SUMPRODUCT(C97:J97,Returns!B101:I101)/K97 -> 0.046549358 | M97: 0 | N97: 0 | O97: =L97+M97+N97 -> 0.046549358 | P97: =P96*(1+O97) -> 1.0518821 | Q97: =MAX($P$5:P97) -> 1.7023632 | R97: =P97/Q97-1 -> -0.3821048 | S97: =O97-Benchmark_RF!D97 -> 0.029854285
A98: 101 | B98: =Returns!A102 -> 45047 | C98: =IF(Rankings!C101<=2,1,0) -> 0 | D98: =IF(Rankings!D101<=2,1,0) -> 1 | E98: =IF(Rankings!E101<=2,1,0) -> 0 | F98: =IF(Rankings!F101<=2,1,0) -> 0 | G98: =IF(Rankings!G101<=2,1,0) -> 0 | H98: =IF(Rankings!H101<=2,1,0) -> 0 | I98: =IF(Rankings!I101<=2,1,0) -> 0 | J98: =IF(Rankings!J101<=2,1,0) -> 1 | K98: =SUM(C98:J98) -> 2 | L98: =SUMPRODUCT(C98:J98,Returns!B102:I102)/K98 -> -0.067661789 | M98: 0 | N98: 0 | O98: =L98+M98+N98 -> -0.067661789 | P98: =P97*(1+O98) -> 0.98070984 | Q98: =MAX($P$5:P98) -> 1.7023632 | R98: =P98/Q98-1 -> -0.42391269 | S98: =O98-Benchmark_RF!D98 -> -0.084356862
A99: 102 | B99: =Returns!A103 -> 45078 | C99: =IF(Rankings!C101<=2,1,0) -> 0 | D99: =IF(Rankings!D101<=2,1,0) -> 1 | E99: =IF(Rankings!E101<=2,1,0) -> 0 | F99: =IF(Rankings!F101<=2,1,0) -> 0 | G99: =IF(Rankings!G101<=2,1,0) -> 0 | H99: =IF(Rankings!H101<=2,1,0) -> 0 | I99: =IF(Rankings!I101<=2,1,0) -> 0 | J99: =IF(Rankings!J101<=2,1,0) -> 1 | K99: =SUM(C99:J99) -> 2 | L99: =SUMPRODUCT(C99:J99,Returns!B103:I103)/K99 -> -0.026440054 | M99: 0 | N99: 0 | O99: =L99+M99+N99 -> -0.026440054 | P99: =P98*(1+O99) -> 0.95477982 | Q99: =MAX($P$5:P99) -> 1.7023632 | R99: =P99/Q99-1 -> -0.43914447 | S99: =O99-Benchmark_RF!D99 -> -0.043142073
A100: 103 | B100: =Returns!A104 -> 45108 | C100: =IF(Rankings!C101<=2,1,0) -> 0 | D100: =IF(Rankings!D101<=2,1,0) -> 1 | E100: =IF(Rankings!E101<=2,1,0) -> 0 | F100: =IF(Rankings!F101<=2,1,0) -> 0 | G100: =IF(Rankings!G101<=2,1,0) -> 0 | H100: =IF(Rankings!H101<=2,1,0) -> 0 | I100: =IF(Rankings!I101<=2,1,0) -> 0 | J100: =IF(Rankings!J101<=2,1,0) -> 1 | K100: =SUM(C100:J100) -> 2 | L100: =SUMPRODUCT(C100:J100,Returns!B104:I104)/K100 -> 0.29946324 | M100: 0 | N100: 0 | O100: =L100+M100+N100 -> 0.29946324 | P100: =P99*(1+O100) -> 1.2407013 | Q100: =MAX($P$5:P100) -> 1.7023632 | R100: =P100/Q100-1 -> -0.27118886 | S100: =O100-Benchmark_RF!D100 -> 0.28213314
A101: 104 | B101: =Returns!A105 -> 45139 | C101: =IF(Rankings!C107<=2,1,0) -> 0 | D101: =IF(Rankings!D107<=2,1,0) -> 0 | E101: =IF(Rankings!E107<=2,1,0) -> 0 | F101: =IF(Rankings!F107<=2,1,0) -> 1 | G101: =IF(Rankings!G107<=2,1,0) -> 0 | H101: =IF(Rankings!H107<=2,1,0) -> 1 | I101: =IF(Rankings!I107<=2,1,0) -> 0 | J101: =IF(Rankings!J107<=2,1,0) -> 0 | K101: =SUM(C101:J101) -> 2 | L101: =SUMPRODUCT(C101:J101,Returns!B105:I105)/K101 -> -0.091581652 | M101: =-2*Assumptions!$B$13 -> -0.007 | N101: =-Assumptions!$B$16*MAX(0,(1+O95)*(1+O96)*(1+O97)*(1+O98)*(1+O99)*(1+O100)-1) -> -0.036506399 | O101: =L101+M101+N101 -> -0.13508805 | P101: =P100*(1+O101) -> 1.0730974 | Q101: =MAX($P$5:P101) -> 1.7023632 | R101: =P101/Q101-1 -> -0.36964254 | S101: =O101-Benchmark_RF!D101 -> -0.15239924
...

Sheet S_Top2_Quarterly
A1: Scenario: Top 2 stocks, Quarterly rebalancing (hold 3 months)
A2: Holdings flag in each row = lookup of Rankings at the governing formation-month (decision row), held constant until next rebalance. Decision i -> holding starts month i+1.
A4: Month (j) | B4: Date | C4: OGDC | D4: MEBL | E4: EFERT | F4: MCB | G4: LUCK | H4: FFC | I4: SAZEW | J4: MARI | K4: Held N | L4: Gross Return | M4: Txn Cost | N4: CGT | O4: Net Return | P4: Growth of Rs.1 | Q4: Running Max | R4: Drawdown | S4: Excess Return
A5: 8 | B5: =Returns!A9 -> 42217 | C5: =IF(Rankings!C11<=2,1,0) -> 0 | D5: =IF(Rankings!D11<=2,1,0) -> 0 | E5: =IF(Rankings!E11<=2,1,0) -> 0 | F5: =IF(Rankings!F11<=2,1,0) -> 0 | G5: =IF(Rankings!G11<=2,1,0) -> 1 | H5: =IF(Rankings!H11<=2,1,0) -> 1 | I5: =IF(Rankings!I11<=2,1,0) -> 0 | J5: =IF(Rankings!J11<=2,1,0) -> 0 | K5: =SUM(C5:J5) -> 2 | L5: =SUMPRODUCT(C5:J5,Returns!B9:I9)/K5 -> -0.056681129 | M5: =-2*Assumptions!$B$13 -> -0.007 | N5: 0 | O5: =L5+M5+N5 -> -0.063681129 | P5: =1*(1+O5) -> 0.93631887 | Q5: =MAX($P$5:P5) -> 0.93631887 | R5: =P5/Q5-1 -> 0 | S5: =O5-Benchmark_RF!D5 -> -0.06928106
A6: 9 | B6: =Returns!A10 -> 42248 | C6: =IF(Rankings!C11<=2,1,0) -> 0 | D6: =IF(Rankings!D11<=2,1,0) -> 0 | E6: =IF(Rankings!E11<=2,1,0) -> 0 | F6: =IF(Rankings!F11<=2,1,0) -> 0 | G6: =IF(Rankings!G11<=2,1,0) -> 1 | H6: =IF(Rankings!H11<=2,1,0) -> 1 | I6: =IF(Rankings!I11<=2,1,0) -> 0 | J6: =IF(Rankings!J11<=2,1,0) -> 0 | K6: =SUM(C6:J6) -> 2 | L6: =SUMPRODUCT(C6:J6,Returns!B10:I10)/K6 -> -0.050873779 | M6: 0 | N6: 0 | O6: =L6+M6+N6 -> -0.050873779 | P6: =P5*(1+O6) -> 0.88868479 | Q6: =MAX($P$5:P6) -> 0.93631887 | R6: =P6/Q6-1 -> -0.050873779 | S6: =O6-Benchmark_RF!D6 -> -0.056108962
A7: 10 | B7: =Returns!A11 -> 42278 | C7: =IF(Rankings!C11<=2,1,0) -> 0 | D7: =IF(Rankings!D11<=2,1,0) -> 0 | E7: =IF(Rankings!E11<=2,1,0) -> 0 | F7: =IF(Rankings!F11<=2,1,0) -> 0 | G7: =IF(Rankings!G11<=2,1,0) -> 1 | H7: =IF(Rankings!H11<=2,1,0) -> 1 | I7: =IF(Rankings!I11<=2,1,0) -> 0 | J7: =IF(Rankings!J11<=2,1,0) -> 0 | K7: =SUM(C7:J7) -> 2 | L7: =SUMPRODUCT(C7:J7,Returns!B11:I11)/K7 -> 0.01976487 | M7: 0 | N7: 0 | O7: =L7+M7+N7 -> 0.01976487 | P7: =P6*(1+O7) -> 0.90624953 | Q7: =MAX($P$5:P7) -> 0.93631887 | R7: =P7/Q7-1 -> -0.032114423 | S7: =O7-Benchmark_RF!D7 -> 0.014657635
A8: 11 | B8: =Returns!A12 -> 42309 | C8: =IF(Rankings!C14<=2,1,0) -> 1 | D8: =IF(Rankings!D14<=2,1,0) -> 0 | E8: =IF(Rankings!E14<=2,1,0) -> 0 | F8: =IF(Rankings!F14<=2,1,0) -> 1 | G8: =IF(Rankings!G14<=2,1,0) -> 0 | H8: =IF(Rankings!H14<=2,1,0) -> 0 | I8: =IF(Rankings!I14<=2,1,0) -> 0 | J8: =IF(Rankings!J14<=2,1,0) -> 0 | K8: =SUM(C8:J8) -> 2 | L8: =SUMPRODUCT(C8:J8,Returns!B12:I12)/K8 -> -0.14351227 | M8: =-2*Assumptions!$B$13 -> -0.007 | N8: =-Assumptions!$B$16*MAX(0,(1+O5)*(1+O6)*(1+O7)-1) -> 0 | O8: =L8+M8+N8 -> -0.15051227 | P8: =P7*(1+O8) -> 0.76984785 | Q8: =MAX($P$5:P8) -> 0.93631887 | R8: =P8/Q8-1 -> -0.17779308 | S8: =O8-Benchmark_RF!D8 -> -0.15567095
A9: 12 | B9: =Returns!A13 -> 42339 | C9: =IF(Rankings!C14<=2,1,0) -> 1 | D9: =IF(Rankings!D14<=2,1,0) -> 0 | E9: =IF(Rankings!E14<=2,1,0) -> 0 | F9: =IF(Rankings!F14<=2,1,0) -> 1 | G9: =IF(Rankings!G14<=2,1,0) -> 0 | H9: =IF(Rankings!H14<=2,1,0) -> 0 | I9: =IF(Rankings!I14<=2,1,0) -> 0 | J9: =IF(Rankings!J14<=2,1,0) -> 0 | K9: =SUM(C9:J9) -> 2 | L9: =SUMPRODUCT(C9:J9,Returns!B13:I13)/K9 -> 0.016912351 | M9: 0 | N9: 0 | O9: =L9+M9+N9 -> 0.016912351 | P9: =P8*(1+O9) -> 0.78286779 | Q9: =MAX($P$5:P9) -> 0.93631887 | R9: =P9/Q9-1 -> -0.16388763 | S9: =O9-Benchmark_RF!D9 -> 0.011778646
A10: 13 | B10: =Returns!A14 -> 42370 | C10: =IF(Rankings!C14<=2,1,0) -> 1 | D10: =IF(Rankings!D14<=2,1,0) -> 0 | E10: =IF(Rankings!E14<=2,1,0) -> 0 | F10: =IF(Rankings!F14<=2,1,0) -> 1 | G10: =IF(Rankings!G14<=2,1,0) -> 0 | H10: =IF(Rankings!H14<=2,1,0) -> 0 | I10: =IF(Rankings!I14<=2,1,0) -> 0 | J10: =IF(Rankings!J14<=2,1,0) -> 0 | K10: =SUM(C10:J10) -> 2 | L10: =SUMPRODUCT(C10:J10,Returns!B14:I14)/K10 -> -0.092617268 | M10: 0 | N10: 0 | O10: =L10+M10+N10 -> -0.092617268 | P10: =P9*(1+O10) -> 0.71036071 | Q10: =MAX($P$5:P10) -> 0.93631887 | R10: =P10/Q10-1 -> -0.24132607 | S10: =O10-Benchmark_RF!D10 -> -0.09761247
A11: 14 | B11: =Returns!A15 -> 42401 | C11: =IF(Rankings!C17<=2,1,0) -> 1 | D11: =IF(Rankings!D17<=2,1,0) -> 0 | E11: =IF(Rankings!E17<=2,1,0) -> 0 | F11: =IF(Rankings!F17<=2,1,0) -> 0 | G11: =IF(Rankings!G17<=2,1,0) -> 0 | H11: =IF(Rankings!H17<=2,1,0) -> 0 | I11: =IF(Rankings!I17<=2,1,0) -> 1 | J11: =IF(Rankings!J17<=2,1,0) -> 0 | K11: =SUM(C11:J11) -> 2 | L11: =SUMPRODUCT(C11:J11,Returns!B15:I15)/K11 -> -0.025393423 | M11: =-2*Assumptions!$B$13 -> -0.007 | N11: =-Assumptions!$B$16*MAX(0,(1+O8)*(1+O9)*(1+O10)-1) -> 0 | O11: =L11+M11+N11 -> -0.032393423 | P11: =P10*(1+O11) -> 0.6873497 | Q11: =MAX($P$5:P11) -> 0.93631887 | R11: =P11/Q11-1 -> -0.26590212 | S11: =O11-Benchmark_RF!D11 -> -0.037429954
A12: 15 | B12: =Returns!A16 -> 42430 | C12: =IF(Rankings!C17<=2,1,0) -> 1 | D12: =IF(Rankings!D17<=2,1,0) -> 0 | E12: =IF(Rankings!E17<=2,1,0) -> 0 | F12: =IF(Rankings!F17<=2,1,0) -> 0 | G12: =IF(Rankings!G17<=2,1,0) -> 0 | H12: =IF(Rankings!H17<=2,1,0) -> 0 | I12: =IF(Rankings!I17<=2,1,0) -> 1 | J12: =IF(Rankings!J17<=2,1,0) -> 0 | K12: =SUM(C12:J12) -> 2 | L12: =SUMPRODUCT(C12:J12,Returns!B16:I16)/K12 -> 0.074093776 | M12: 0 | N12: 0 | O12: =L12+M12+N12 -> 0.074093776 | P12: =P11*(1+O12) -> 0.73827803 | Q12: =MAX($P$5:P12) -> 0.93631887 | R12: =P12/Q12-1 -> -0.21151003 | S12: =O12-Benchmark_RF!D12 -> 0.069092263
A13: 16 | B13: =Returns!A17 -> 42461 | C13: =IF(Rankings!C17<=2,1,0) -> 1 | D13: =IF(Rankings!D17<=2,1,0) -> 0 | E13: =IF(Rankings!E17<=2,1,0) -> 0 | F13: =IF(Rankings!F17<=2,1,0) -> 0 | G13: =IF(Rankings!G17<=2,1,0) -> 0 | H13: =IF(Rankings!H17<=2,1,0) -> 0 | I13: =IF(Rankings!I17<=2,1,0) -> 1 | J13: =IF(Rankings!J17<=2,1,0) -> 0 | K13: =SUM(C13:J13) -> 2 | L13: =SUMPRODUCT(C13:J13,Returns!B17:I17)/K13 -> 0.12657556 | M13: 0 | N13: 0 | O13: =L13+M13+N13 -> 0.12657556 | P13: =P12*(1+O13) -> 0.83172599 | Q13: =MAX($P$5:P13) -> 0.93631887 | R13: =P13/Q13-1 -> -0.11170648 | S13: =O13-Benchmark_RF!D13 -> 0.12157404
A14: 17 | B14: =Returns!A18 -> 42491 | C14: =IF(Rankings!C20<=2,1,0) -> 0 | D14: =IF(Rankings!D20<=2,1,0) -> 0 | E14: =IF(Rankings!E20<=2,1,0) -> 0 | F14: =IF(Rankings!F20<=2,1,0) -> 1 | G14: =IF(Rankings!G20<=2,1,0) -> 0 | H14: =IF(Rankings!H20<=2,1,0) -> 0 | I14: =IF(Rankings!I20<=2,1,0) -> 1 | J14: =IF(Rankings!J20<=2,1,0) -> 0 | K14: =SUM(C14:J14) -> 2 | L14: =SUMPRODUCT(C14:J14,Returns!B18:I18)/K14 -> -0.050299253 | M14: =-2*Assumptions!$B$13 -> -0.007 | N14: =-Assumptions!$B$16*MAX(0,(1+O11)*(1+O12)*(1+O13)-1) -> -0.025627531 | O14: =L14+M14+N14 -> -0.082926784 | P14: =P13*(1+O14) -> 0.76275363 | Q14: =MAX($P$5:P14) -> 0.93631887 | R14: =P14/Q14-1 -> -0.1853698 | S14: =O14-Benchmark_RF!D14 -> -0.087784459
A15: 18 | B15: =Returns!A19 -> 42522 | C15: =IF(Rankings!C20<=2,1,0) -> 0 | D15: =IF(Rankings!D20<=2,1,0) -> 0 | E15: =IF(Rankings!E20<=2,1,0) -> 0 | F15: =IF(Rankings!F20<=2,1,0) -> 1 | G15: =IF(Rankings!G20<=2,1,0) -> 0 | H15: =IF(Rankings!H20<=2,1,0) -> 0 | I15: =IF(Rankings!I20<=2,1,0) -> 1 | J15: =IF(Rankings!J20<=2,1,0) -> 0 | K15: =SUM(C15:J15) -> 2 | L15: =SUMPRODUCT(C15:J15,Returns!B19:I19)/K15 -> 0.025205715 | M15: 0 | N15: 0 | O15: =L15+M15+N15 -> 0.025205715 | P15: =P14*(1+O15) -> 0.78197938 | Q15: =MAX($P$5:P15) -> 0.93631887 | R15: =P15/Q15-1 -> -0.16483647 | S15: =O15-Benchmark_RF!D15 -> 0.020417355
A16: 19 | B16: =Returns!A20 -> 42552 | C16: =IF(Rankings!C20<=2,1,0) -> 0 | D16: =IF(Rankings!D20<=2,1,0) -> 0 | E16: =IF(Rankings!E20<=2,1,0) -> 0 | F16: =IF(Rankings!F20<=2,1,0) -> 1 | G16: =IF(Rankings!G20<=2,1,0) -> 0 | H16: =IF(Rankings!H20<=2,1,0) -> 0 | I16: =IF(Rankings!I20<=2,1,0) -> 1 | J16: =IF(Rankings!J20<=2,1,0) -> 0 | K16: =SUM(C16:J16) -> 2 | L16: =SUMPRODUCT(C16:J16,Returns!B20:I20)/K16 -> 0.032169872 | M16: 0 | N16: 0 | O16: =L16+M16+N16 -> 0.032169872 | P16: =P15*(1+O16) -> 0.80713555 | Q16: =MAX($P$5:P16) -> 0.93631887 | R16: =P16/Q16-1 -> -0.13796936 | S16: =O16-Benchmark_RF!D16 -> 0.027470507
A17: 20 | B17: =Returns!A21 -> 42583 | C17: =IF(Rankings!C23<=2,1,0) -> 0 | D17: =IF(Rankings!D23<=2,1,0) -> 0 | E17: =IF(Rankings!E23<=2,1,0) -> 0 | F17: =IF(Rankings!F23<=2,1,0) -> 1 | G17: =IF(Rankings!G23<=2,1,0) -> 0 | H17: =IF(Rankings!H23<=2,1,0) -> 0 | I17: =IF(Rankings!I23<=2,1,0) -> 1 | J17: =IF(Rankings!J23<=2,1,0) -> 0 | K17: =SUM(C17:J17) -> 2 | L17: =SUMPRODUCT(C17:J17,Returns!B21:I21)/K17 -> 0.042663683 | M17: =-2*Assumptions!$B$13 -> -0.007 | N17: =-Assumptions!$B$16*MAX(0,(1+O14)*(1+O15)*(1+O16)-1) -> 0 | O17: =L17+M17+N17 -> 0.035663683 | P17: =P16*(1+O17) -> 0.83592098 | Q17: =MAX($P$5:P17) -> 0.93631887 | R17: =P17/Q17-1 -> -0.10722618 | S17: =O17-Benchmark_RF!D17 -> 0.030906798
A18: 21 | B18: =Returns!A22 -> 42614 | C18: =IF(Rankings!C23<=2,1,0) -> 0 | D18: =IF(Rankings!D23<=2,1,0) -> 0 | E18: =IF(Rankings!E23<=2,1,0) -> 0 | F18: =IF(Rankings!F23<=2,1,0) -> 1 | G18: =IF(Rankings!G23<=2,1,0) -> 0 | H18: =IF(Rankings!H23<=2,1,0) -> 0 | I18: =IF(Rankings!I23<=2,1,0) -> 1 | J18: =IF(Rankings!J23<=2,1,0) -> 0 | K18: =SUM(C18:J18) -> 2 | L18: =SUMPRODUCT(C18:J18,Returns!B22:I22)/K18 -> 0.30210015 | M18: 0 | N18: 0 | O18: =L18+M18+N18 -> 0.30210015 | P18: =P17*(1+O18) -> 1.0884528 | Q18: =MAX($P$5:P18) -> 1.0884528 | R18: =P18/Q18-1 -> 0 | S18: =O18-Benchmark_RF!D18 -> 0.29734326
A19: 22 | B19: =Returns!A23 -> 42644 | C19: =IF(Rankings!C23<=2,1,0) -> 0 | D19: =IF(Rankings!D23<=2,1,0) -> 0 | E19: =IF(Rankings!E23<=2,1,0) -> 0 | F19: =IF(Rankings!F23<=2,1,0) -> 1 | G19: =IF(Rankings!G23<=2,1,0) -> 0 | H19: =IF(Rankings!H23<=2,1,0) -> 0 | I19: =IF(Rankings!I23<=2,1,0) -> 1 | J19: =IF(Rankings!J23<=2,1,0) -> 0 | K19: =SUM(C19:J19) -> 2 | L19: =SUMPRODUCT(C19:J19,Returns!B23:I23)/K19 -> 0.10422243 | M19: 0 | N19: 0 | O19: =L19+M19+N19 -> 0.10422243 | P19: =P18*(1+O19) -> 1.201894 | Q19: =MAX($P$5:P19) -> 1.201894 | R19: =P19/Q19-1 -> 0 | S19: =O19-Benchmark_RF!D19 -> 0.099449724
A20: 23 | B20: =Returns!A24 -> 42675 | C20: =IF(Rankings!C26<=2,1,0) -> 0 | D20: =IF(Rankings!D26<=2,1,0) -> 0 | E20: =IF(Rankings!E26<=2,1,0) -> 0 | F20: =IF(Rankings!F26<=2,1,0) -> 0 | G20: =IF(Rankings!G26<=2,1,0) -> 0 | H20: =IF(Rankings!H26<=2,1,0) -> 1 | I20: =IF(Rankings!I26<=2,1,0) -> 1 | J20: =IF(Rankings!J26<=2,1,0) -> 0 | K20: =SUM(C20:J20) -> 2 | L20: =SUMPRODUCT(C20:J20,Returns!B24:I24)/K20 -> 0.20622902 | M20: =-2*Assumptions!$B$13 -> -0.007 | N20: =-Assumptions!$B$16*MAX(0,(1+O17)*(1+O18)*(1+O19)-1) -> -0.073362858 | O20: =L20+M20+N20 -> 0.12586616 | P20: =P19*(1+O20) -> 1.3531718 | Q20: =MAX($P$5:P20) -> 1.3531718 | R20: =P20/Q20-1 -> 0 | S20: =O20-Benchmark_RF!D20 -> 0.12103812
A21: 24 | B21: =Returns!A25 -> 42705 | C21: =IF(Rankings!C26<=2,1,0) -> 0 | D21: =IF(Rankings!D26<=2,1,0) -> 0 | E21: =IF(Rankings!E26<=2,1,0) -> 0 | F21: =IF(Rankings!F26<=2,1,0) -> 0 | G21: =IF(Rankings!G26<=2,1,0) -> 0 | H21: =IF(Rankings!H26<=2,1,0) -> 1 | I21: =IF(Rankings!I26<=2,1,0) -> 1 | J21: =IF(Rankings!J26<=2,1,0) -> 0 | K21: =SUM(C21:J21) -> 2 | L21: =SUMPRODUCT(C21:J21,Returns!B25:I25)/K21 -> -0.029855361 | M21: 0 | N21: 0 | O21: =L21+M21+N21 -> -0.029855361 | P21: =P20*(1+O21) -> 1.3127724 | Q21: =MAX($P$5:P21) -> 1.3531718 | R21: =P21/Q21-1 -> -0.029855361 | S21: =O21-Benchmark_RF!D21 -> -0.034695178
A22: 25 | B22: =Returns!A26 -> 42736 | C22: =IF(Rankings!C26<=2,1,0) -> 0 | D22: =IF(Rankings!D26<=2,1,0) -> 0 | E22: =IF(Rankings!E26<=2,1,0) -> 0 | F22: =IF(Rankings!F26<=2,1,0) -> 0 | G22: =IF(Rankings!G26<=2,1,0) -> 0 | H22: =IF(Rankings!H26<=2,1,0) -> 1 | I22: =IF(Rankings!I26<=2,1,0) -> 1 | J22: =IF(Rankings!J26<=2,1,0) -> 0 | K22: =SUM(C22:J22) -> 2 | L22: =SUMPRODUCT(C22:J22,Returns!B26:I26)/K22 -> 0.038461342 | M22: 0 | N22: 0 | O22: =L22+M22+N22 -> 0.038461342 | P22: =P21*(1+O22) -> 1.3632634 | Q22: =MAX($P$5:P22) -> 1.3632634 | R22: =P22/Q22-1 -> 0 | S22: =O22-Benchmark_RF!D22 -> 0.033686979
A23: 26 | B23: =Returns!A27 -> 42767 | C23: =IF(Rankings!C29<=2,1,0) -> 1 | D23: =IF(Rankings!D29<=2,1,0) -> 0 | E23: =IF(Rankings!E29<=2,1,0) -> 0 | F23: =IF(Rankings!F29<=2,1,0) -> 0 | G23: =IF(Rankings!G29<=2,1,0) -> 0 | H23: =IF(Rankings!H29<=2,1,0) -> 1 | I23: =IF(Rankings!I29<=2,1,0) -> 0 | J23: =IF(Rankings!J29<=2,1,0) -> 0 | K23: =SUM(C23:J23) -> 2 | L23: =SUMPRODUCT(C23:J23,Returns!B27:I27)/K23 -> -0.044622449 | M23: =-2*Assumptions!$B$13 -> -0.007 | N23: =-Assumptions!$B$16*MAX(0,(1+O20)*(1+O21)*(1+O22)-1) -> -0.020139381 | O23: =L23+M23+N23 -> -0.071761831 | P23: =P22*(1+O23) -> 1.2654331 | Q23: =MAX($P$5:P23) -> 1.3632634 | R23: =P23/Q23-1 -> -0.071761831 | S23: =O23-Benchmark_RF!D23 -> -0.076583313
A24: 27 | B24: =Returns!A28 -> 42795 | C24: =IF(Rankings!C29<=2,1,0) -> 1 | D24: =IF(Rankings!D29<=2,1,0) -> 0 | E24: =IF(Rankings!E29<=2,1,0) -> 0 | F24: =IF(Rankings!F29<=2,1,0) -> 0 | G24: =IF(Rankings!G29<=2,1,0) -> 0 | H24: =IF(Rankings!H29<=2,1,0) -> 1 | I24: =IF(Rankings!I29<=2,1,0) -> 0 | J24: =IF(Rankings!J29<=2,1,0) -> 0 | K24: =SUM(C24:J24) -> 2 | L24: =SUMPRODUCT(C24:J24,Returns!B28:I28)/K24 -> -0.045573838 | M24: 0 | N24: 0 | O24: =L24+M24+N24 -> -0.045573838 | P24: =P23*(1+O24) -> 1.2077625 | Q24: =MAX($P$5:P24) -> 1.3632634 | R24: =P24/Q24-1 -> -0.11406521 | S24: =O24-Benchmark_RF!D24 -> -0.050419108
A25: 28 | B25: =Returns!A29 -> 42826 | C25: =IF(Rankings!C29<=2,1,0) -> 1 | D25: =IF(Rankings!D29<=2,1,0) -> 0 | E25: =IF(Rankings!E29<=2,1,0) -> 0 | F25: =IF(Rankings!F29<=2,1,0) -> 0 | G25: =IF(Rankings!G29<=2,1,0) -> 0 | H25: =IF(Rankings!H29<=2,1,0) -> 1 | I25: =IF(Rankings!I29<=2,1,0) -> 0 | J25: =IF(Rankings!J29<=2,1,0) -> 0 | K25: =SUM(C25:J25) -> 2 | L25: =SUMPRODUCT(C25:J25,Returns!B29:I29)/K25 -> -0.016658428 | M25: 0 | N25: 0 | O25: =L25+M25+N25 -> -0.016658428 | P25: =P24*(1+O25) -> 1.187643 | Q25: =MAX($P$5:P25) -> 1.3632634 | R25: =P25/Q25-1 -> -0.12882349 | S25: =O25-Benchmark_RF!D25 -> -0.021514207
A26: 29 | B26: =Returns!A30 -> 42856 | C26: =IF(Rankings!C32<=2,1,0) -> 0 | D26: =IF(Rankings!D32<=2,1,0) -> 0 | E26: =IF(Rankings!E32<=2,1,0) -> 0 | F26: =IF(Rankings!F32<=2,1,0) -> 0 | G26: =IF(Rankings!G32<=2,1,0) -> 0 | H26: =IF(Rankings!H32<=2,1,0) -> 1 | I26: =IF(Rankings!I32<=2,1,0) -> 1 | J26: =IF(Rankings!J32<=2,1,0) -> 0 | K26: =SUM(C26:J26) -> 2 | L26: =SUMPRODUCT(C26:J26,Returns!B30:I30)/K26 -> 0.36259031 | M26: =-2*Assumptions!$B$13 -> -0.007 | N26: =-Assumptions!$B$16*MAX(0,(1+O23)*(1+O24)*(1+O25)-1) -> 0 | O26: =L26+M26+N26 -> 0.35559031 | P26: =P25*(1+O26) -> 1.6099574 | Q26: =MAX($P$5:P26) -> 1.6099574 | R26: =P26/Q26-1 -> 0 | S26: =O26-Benchmark_RF!D26 -> 0.35073454
A27: 30 | B27: =Returns!A31 -> 42887 | C27: =IF(Rankings!C32<=2,1,0) -> 0 | D27: =IF(Rankings!D32<=2,1,0) -> 0 | E27: =IF(Rankings!E32<=2,1,0) -> 0 | F27: =IF(Rankings!F32<=2,1,0) -> 0 | G27: =IF(Rankings!G32<=2,1,0) -> 0 | H27: =IF(Rankings!H32<=2,1,0) -> 1 | I27: =IF(Rankings!I32<=2,1,0) -> 1 | J27: =IF(Rankings!J32<=2,1,0) -> 0 | K27: =SUM(C27:J27) -> 2 | L27: =SUMPRODUCT(C27:J27,Returns!B31:I31)/K27 -> 0.098497509 | M27: 0 | N27: 0 | O27: =L27+M27+N27 -> 0.098497509 | P27: =P26*(1+O27) -> 1.7685342 | Q27: =MAX($P$5:P27) -> 1.7685342 | R27: =P27/Q27-1 -> 0 | S27: =O27-Benchmark_RF!D27 -> 0.093637068
A28: 31 | B28: =Returns!A32 -> 42917 | C28: =IF(Rankings!C32<=2,1,0) -> 0 | D28: =IF(Rankings!D32<=2,1,0) -> 0 | E28: =IF(Rankings!E32<=2,1,0) -> 0 | F28: =IF(Rankings!F32<=2,1,0) -> 0 | G28: =IF(Rankings!G32<=2,1,0) -> 0 | H28: =IF(Rankings!H32<=2,1,0) -> 1 | I28: =IF(Rankings!I32<=2,1,0) -> 1 | J28: =IF(Rankings!J32<=2,1,0) -> 0 | K28: =SUM(C28:J28) -> 2 | L28: =SUMPRODUCT(C28:J28,Returns!B32:I32)/K28 -> -0.10129727 | M28: 0 | N28: 0 | O28: =L28+M28+N28 -> -0.10129727 | P28: =P27*(1+O28) -> 1.5893865 | Q28: =MAX($P$5:P28) -> 1.7685342 | R28: =P28/Q28-1 -> -0.10129727 | S28: =O28-Benchmark_RF!D28 -> -0.10615763
A29: 32 | B29: =Returns!A33 -> 42948 | C29: =IF(Rankings!C35<=2,1,0) -> 0 | D29: =IF(Rankings!D35<=2,1,0) -> 0 | E29: =IF(Rankings!E35<=2,1,0) -> 0 | F29: =IF(Rankings!F35<=2,1,0) -> 0 | G29: =IF(Rankings!G35<=2,1,0) -> 0 | H29: =IF(Rankings!H35<=2,1,0) -> 1 | I29: =IF(Rankings!I35<=2,1,0) -> 1 | J29: =IF(Rankings!J35<=2,1,0) -> 0 | K29: =SUM(C29:J29) -> 2 | L29: =SUMPRODUCT(C29:J29,Returns!B33:I33)/K29 -> -0.21319483 | M29: =-2*Assumptions!$B$13 -> -0.007 | N29: =-Assumptions!$B$16*MAX(0,(1+O26)*(1+O27)*(1+O28)-1) -> -0.050740432 | O29: =L29+M29+N29 -> -0.27093526 | P29: =P28*(1+O29) -> 1.1587657 | Q29: =MAX($P$5:P29) -> 1.7685342 | R29: =P29/Q29-1 -> -0.34478753 | S29: =O29-Benchmark_RF!D29 -> -0.27579507
A30: 33 | B30: =Returns!A34 -> 42979 | C30: =IF(Rankings!C35<=2,1,0) -> 0 | D30: =IF(Rankings!D35<=2,1,0) -> 0 | E30: =IF(Rankings!E35<=2,1,0) -> 0 | F30: =IF(Rankings!F35<=2,1,0) -> 0 | G30: =IF(Rankings!G35<=2,1,0) -> 0 | H30: =IF(Rankings!H35<=2,1,0) -> 1 | I30: =IF(Rankings!I35<=2,1,0) -> 1 | J30: =IF(Rankings!J35<=2,1,0) -> 0 | K30: =SUM(C30:J30) -> 2 | L30: =SUMPRODUCT(C30:J30,Returns!B34:I34)/K30 -> 0.10265278 | M30: 0 | N30: 0 | O30: =L30+M30+N30 -> 0.10265278 | P30: =P29*(1+O30) -> 1.2777162 | Q30: =MAX($P$5:P30) -> 1.7685342 | R30: =P30/Q30-1 -> -0.27752815 | S30: =O30-Benchmark_RF!D30 -> 0.09779234
A31: 34 | B31: =Returns!A35 -> 43009 | C31: =IF(Rankings!C35<=2,1,0) -> 0 | D31: =IF(Rankings!D35<=2,1,0) -> 0 | E31: =IF(Rankings!E35<=2,1,0) -> 0 | F31: =IF(Rankings!F35<=2,1,0) -> 0 | G31: =IF(Rankings!G35<=2,1,0) -> 0 | H31: =IF(Rankings!H35<=2,1,0) -> 1 | I31: =IF(Rankings!I35<=2,1,0) -> 1 | J31: =IF(Rankings!J35<=2,1,0) -> 0 | K31: =SUM(C31:J31) -> 2 | L31: =SUMPRODUCT(C31:J31,Returns!B35:I35)/K31 -> -0.045651394 | M31: 0 | N31: 0 | O31: =L31+M31+N31 -> -0.045651394 | P31: =P30*(1+O31) -> 1.2193866 | Q31: =MAX($P$5:P31) -> 1.7685342 | R31: =P31/Q31-1 -> -0.31050999 | S31: =O31-Benchmark_RF!D31 -> -0.050511834
A32: 35 | B32: =Returns!A36 -> 43040 | C32: =IF(Rankings!C38<=2,1,0) -> 0 | D32: =IF(Rankings!D38<=2,1,0) -> 1 | E32: =IF(Rankings!E38<=2,1,0) -> 0 | F32: =IF(Rankings!F38<=2,1,0) -> 0 | G32: =IF(Rankings!G38<=2,1,0) -> 0 | H32: =IF(Rankings!H38<=2,1,0) -> 1 | I32: =IF(Rankings!I38<=2,1,0) -> 0 | J32: =IF(Rankings!J38<=2,1,0) -> 0 | K32: =SUM(C32:J32) -> 2 | L32: =SUMPRODUCT(C32:J32,Returns!B36:I36)/K32 -> 0.014399582 | M32: =-2*Assumptions!$B$13 -> -0.007 | N32: =-Assumptions!$B$16*MAX(0,(1+O29)*(1+O30)*(1+O31)-1) -> 0 | O32: =L32+M32+N32 -> 0.0073995823 | P32: =P31*(1+O32) -> 1.2284096 | Q32: =MAX($P$5:P32) -> 1.7685342 | R32: =P32/Q32-1 -> -0.30540805 | S32: =O32-Benchmark_RF!D32 -> 0.0025392209
A33: 36 | B33: =Returns!A37 -> 43070 | C33: =IF(Rankings!C38<=2,1,0) -> 0 | D33: =IF(Rankings!D38<=2,1,0) -> 1 | E33: =IF(Rankings!E38<=2,1,0) -> 0 | F33: =IF(Rankings!F38<=2,1,0) -> 0 | G33: =IF(Rankings!G38<=2,1,0) -> 0 | H33: =IF(Rankings!H38<=2,1,0) -> 1 | I33: =IF(Rankings!I38<=2,1,0) -> 0 | J33: =IF(Rankings!J38<=2,1,0) -> 0 | K33: =SUM(C33:J33) -> 2 | L33: =SUMPRODUCT(C33:J33,Returns!B37:I37)/K33 -> -0.0052983904 | M33: 0 | N33: 0 | O33: =L33+M33+N33 -> -0.0052983904 | P33: =P32*(1+O33) -> 1.221901 | Q33: =MAX($P$5:P33) -> 1.7685342 | R33: =P33/Q33-1 -> -0.30908827 | S33: =O33-Benchmark_RF!D33 -> -0.010158831
A34: 37 | B34: =Returns!A38 -> 43101 | C34: =IF(Rankings!C38<=2,1,0) -> 0 | D34: =IF(Rankings!D38<=2,1,0) -> 1 | E34: =IF(Rankings!E38<=2,1,0) -> 0 | F34: =IF(Rankings!F38<=2,1,0) -> 0 | G34: =IF(Rankings!G38<=2,1,0) -> 0 | H34: =IF(Rankings!H38<=2,1,0) -> 1 | I34: =IF(Rankings!I38<=2,1,0) -> 0 | J34: =IF(Rankings!J38<=2,1,0) -> 0 | K34: =SUM(C34:J34) -> 2 | L34: =SUMPRODUCT(C34:J34,Returns!B38:I38)/K34 -> 0.14186072 | M34: 0 | N34: 0 | O34: =L34+M34+N34 -> 0.14186072 | P34: =P33*(1+O34) -> 1.3952408 | Q34: =MAX($P$5:P34) -> 1.7685342 | R34: =P34/Q34-1 -> -0.21107504 | S34: =O34-Benchmark_RF!D34 -> 0.13683531
A35: 38 | B35: =Returns!A39 -> 43132 | C35: =IF(Rankings!C41<=2,1,0) -> 0 | D35: =IF(Rankings!D41<=2,1,0) -> 1 | E35: =IF(Rankings!E41<=2,1,0) -> 0 | F35: =IF(Rankings!F41<=2,1,0) -> 0 | G35: =IF(Rankings!G41<=2,1,0) -> 1 | H35: =IF(Rankings!H41<=2,1,0) -> 0 | I35: =IF(Rankings!I41<=2,1,0) -> 0 | J35: =IF(Rankings!J41<=2,1,0) -> 0 | K35: =SUM(C35:J35) -> 2 | L35: =SUMPRODUCT(C35:J35,Returns!B39:I39)/K35 -> -0.024763237 | M35: =-2*Assumptions!$B$13 -> -0.007 | N35: =-Assumptions!$B$16*MAX(0,(1+O32)*(1+O33)*(1+O34)-1) -> -0.021632283 | O35: =L35+M35+N35 -> -0.05339552 | P35: =P34*(1+O35) -> 1.3207412 | Q35: =MAX($P$5:P35) -> 1.7685342 | R35: =P35/Q35-1 -> -0.2532001 | S35: =O35-Benchmark_RF!D35 -> -0.058446322
A36: 39 | B36: =Returns!A40 -> 43160 | C36: =IF(Rankings!C41<=2,1,0) -> 0 | D36: =IF(Rankings!D41<=2,1,0) -> 1 | E36: =IF(Rankings!E41<=2,1,0) -> 0 | F36: =IF(Rankings!F41<=2,1,0) -> 0 | G36: =IF(Rankings!G41<=2,1,0) -> 1 | H36: =IF(Rankings!H41<=2,1,0) -> 0 | I36: =IF(Rankings!I41<=2,1,0) -> 0 | J36: =IF(Rankings!J41<=2,1,0) -> 0 | K36: =SUM(C36:J36) -> 2 | L36: =SUMPRODUCT(C36:J36,Returns!B40:I40)/K36 -> 0.10337764 | M36: 0 | N36: 0 | O36: =L36+M36+N36 -> 0.10337764 | P36: =P35*(1+O36) -> 1.4572763 | Q36: =MAX($P$5:P36) -> 1.7685342 | R36: =P36/Q36-1 -> -0.17599769 | S36: =O36-Benchmark_RF!D36 -> 0.098305633
A37: 40 | B37: =Returns!A41 -> 43191 | C37: =IF(Rankings!C41<=2,1,0) -> 0 | D37: =IF(Rankings!D41<=2,1,0) -> 1 | E37: =IF(Rankings!E41<=2,1,0) -> 0 | F37: =IF(Rankings!F41<=2,1,0) -> 0 | G37: =IF(Rankings!G41<=2,1,0) -> 1 | H37: =IF(Rankings!H41<=2,1,0) -> 0 | I37: =IF(Rankings!I41<=2,1,0) -> 0 | J37: =IF(Rankings!J41<=2,1,0) -> 0 | K37: =SUM(C37:J37) -> 2 | L37: =SUMPRODUCT(C37:J37,Returns!B41:I41)/K37 -> -0.026920272 | M37: 0 | N37: 0 | O37: =L37+M37+N37 -> -0.026920272 | P37: =P36*(1+O37) -> 1.418046 | Q37: =MAX($P$5:P37) -> 1.7685342 | R37: =P37/Q37-1 -> -0.19818005 | S37: =O37-Benchmark_RF!D37 -> -0.03197478
A38: 41 | B38: =Returns!A42 -> 43221 | C38: =IF(Rankings!C44<=2,1,0) -> 0 | D38: =IF(Rankings!D44<=2,1,0) -> 0 | E38: =IF(Rankings!E44<=2,1,0) -> 0 | F38: =IF(Rankings!F44<=2,1,0) -> 1 | G38: =IF(Rankings!G44<=2,1,0) -> 0 | H38: =IF(Rankings!H44<=2,1,0) -> 1 | I38: =IF(Rankings!I44<=2,1,0) -> 0 | J38: =IF(Rankings!J44<=2,1,0) -> 0 | K38: =SUM(C38:J38) -> 2 | L38: =SUMPRODUCT(C38:J38,Returns!B42:I42)/K38 -> -0.019534883 | M38: =-2*Assumptions!$B$13 -> -0.007 | N38: =-Assumptions!$B$16*MAX(0,(1+O35)*(1+O36)*(1+O37)-1) -> -0.0024517516 | O38: =L38+M38+N38 -> -0.028986635 | P38: =P37*(1+O38) -> 1.3769416 | Q38: =MAX($P$5:P38) -> 1.7685342 | R38: =P38/Q38-1 -> -0.22142212 | S38: =O38-Benchmark_RF!D38 -> -0.03405817
A39: 42 | B39: =Returns!A43 -> 43252 | C39: =IF(Rankings!C44<=2,1,0) -> 0 | D39: =IF(Rankings!D44<=2,1,0) -> 0 | E39: =IF(Rankings!E44<=2,1,0) -> 0 | F39: =IF(Rankings!F44<=2,1,0) -> 1 | G39: =IF(Rankings!G44<=2,1,0) -> 0 | H39: =IF(Rankings!H44<=2,1,0) -> 1 | I39: =IF(Rankings!I44<=2,1,0) -> 0 | J39: =IF(Rankings!J44<=2,1,0) -> 0 | K39: =SUM(C39:J39) -> 2 | L39: =SUMPRODUCT(C39:J39,Returns!B43:I43)/K39 -> -0.010981589 | M39: 0 | N39: 0 | O39: =L39+M39+N39 -> -0.010981589 | P39: =P38*(1+O39) -> 1.3618206 | Q39: =MAX($P$5:P39) -> 1.7685342 | R39: =P39/Q39-1 -> -0.22997214 | S39: =O39-Benchmark_RF!D39 -> -0.016447176
A40: 43 | B40: =Returns!A44 -> 43282 | C40: =IF(Rankings!C44<=2,1,0) -> 0 | D40: =IF(Rankings!D44<=2,1,0) -> 0 | E40: =IF(Rankings!E44<=2,1,0) -> 0 | F40: =IF(Rankings!F44<=2,1,0) -> 1 | G40: =IF(Rankings!G44<=2,1,0) -> 0 | H40: =IF(Rankings!H44<=2,1,0) -> 1 | I40: =IF(Rankings!I44<=2,1,0) -> 0 | J40: =IF(Rankings!J44<=2,1,0) -> 0 | K40: =SUM(C40:J40) -> 2 | L40: =SUMPRODUCT(C40:J40,Returns!B44:I44)/K40 -> 0.02672279 | M40: 0 | N40: 0 | O40: =L40+M40+N40 -> 0.02672279 | P40: =P39*(1+O40) -> 1.3982122 | Q40: =MAX($P$5:P40) -> 1.7685342 | R40: =P40/Q40-1 -> -0.20939484 | S40: =O40-Benchmark_RF!D40 -> 0.020505446
A41: 44 | B41: =Returns!A45 -> 43313 | C41: =IF(Rankings!C47<=2,1,0) -> 1 | D41: =IF(Rankings!D47<=2,1,0) -> 0 | E41: =IF(Rankings!E47<=2,1,0) -> 0 | F41: =IF(Rankings!F47<=2,1,0) -> 0 | G41: =IF(Rankings!G47<=2,1,0) -> 0 | H41: =IF(Rankings!H47<=2,1,0) -> 1 | I41: =IF(Rankings!I47<=2,1,0) -> 0 | J41: =IF(Rankings!J47<=2,1,0) -> 0 | K41: =SUM(C41:J41) -> 2 | L41: =SUMPRODUCT(C41:J41,Returns!B45:I45)/K41 -> -0.0044257353 | M41: =-2*Assumptions!$B$13 -> -0.007 | N41: =-Assumptions!$B$16*MAX(0,(1+O38)*(1+O39)*(1+O40)-1) -> 0 | O41: =L41+M41+N41 -> -0.011425735 | P41: =P40*(1+O41) -> 1.3822366 | Q41: =MAX($P$5:P41) -> 1.7685342 | R41: =P41/Q41-1 -> -0.21842809 | S41: =O41-Benchmark_RF!D41 -> -0.017665417
A42: 45 | B42: =Returns!A46 -> 43344 | C42: =IF(Rankings!C47<=2,1,0) -> 1 | D42: =IF(Rankings!D47<=2,1,0) -> 0 | E42: =IF(Rankings!E47<=2,1,0) -> 0 | F42: =IF(Rankings!F47<=2,1,0) -> 0 | G42: =IF(Rankings!G47<=2,1,0) -> 0 | H42: =IF(Rankings!H47<=2,1,0) -> 1 | I42: =IF(Rankings!I47<=2,1,0) -> 0 | J42: =IF(Rankings!J47<=2,1,0) -> 0 | K42: =SUM(C42:J42) -> 2 | L42: =SUMPRODUCT(C42:J42,Returns!B46:I46)/K42 -> 0.0027633255 | M42: 0 | N42: 0 | O42: =L42+M42+N42 -> 0.0027633255 | P42: =P41*(1+O42) -> 1.3860562 | Q42: =MAX($P$5:P42) -> 1.7685342 | R42: =P42/Q42-1 -> -0.21626835 | S42: =O42-Benchmark_RF!D42 -> -0.003476356
A43: 46 | B43: =Returns!A47 -> 43374 | C43: =IF(Rankings!C47<=2,1,0) -> 1 | D43: =IF(Rankings!D47<=2,1,0) -> 0 | E43: =IF(Rankings!E47<=2,1,0) -> 0 | F43: =IF(Rankings!F47<=2,1,0) -> 0 | G43: =IF(Rankings!G47<=2,1,0) -> 0 | H43: =IF(Rankings!H47<=2,1,0) -> 1 | I43: =IF(Rankings!I47<=2,1,0) -> 0 | J43: =IF(Rankings!J47<=2,1,0) -> 0 | K43: =SUM(C43:J43) -> 2 | L43: =SUMPRODUCT(C43:J43,Returns!B47:I47)/K43 -> 0.020208866 | M43: 0 | N43: 0 | O43: =L43+M43+N43 -> 0.020208866 | P43: =P42*(1+O43) -> 1.4140668 | Q43: =MAX($P$5:P43) -> 1.7685342 | R43: =P43/Q43-1 -> -0.20043002 | S43: =O43-Benchmark_RF!D43 -> 0.013161928
A44: 47 | B44: =Returns!A48 -> 43405 | C44: =IF(Rankings!C50<=2,1,0) -> 1 | D44: =IF(Rankings!D50<=2,1,0) -> 1 | E44: =IF(Rankings!E50<=2,1,0) -> 0 | F44: =IF(Rankings!F50<=2,1,0) -> 0 | G44: =IF(Rankings!G50<=2,1,0) -> 0 | H44: =IF(Rankings!H50<=2,1,0) -> 0 | I44: =IF(Rankings!I50<=2,1,0) -> 0 | J44: =IF(Rankings!J50<=2,1,0) -> 0 | K44: =SUM(C44:J44) -> 2 | L44: =SUMPRODUCT(C44:J44,Returns!B48:I48)/K44 -> -0.040714697 | M44: =-2*Assumptions!$B$13 -> -0.007 | N44: =-Assumptions!$B$16*MAX(0,(1+O41)*(1+O42)*(1+O43)-1) -> -0.0017008782 | O44: =L44+M44+N44 -> -0.049415575 | P44: =P43*(1+O44) -> 1.3441899 | Q44: =MAX($P$5:P44) -> 1.7685342 | R44: =P44/Q44-1 -> -0.23994123 | S44: =O44-Benchmark_RF!D44 -> -0.056467296
A45: 48 | B45: =Returns!A49 -> 43435 | C45: =IF(Rankings!C50<=2,1,0) -> 1 | D45: =IF(Rankings!D50<=2,1,0) -> 1 | E45: =IF(Rankings!E50<=2,1,0) -> 0 | F45: =IF(Rankings!F50<=2,1,0) -> 0 | G45: =IF(Rankings!G50<=2,1,0) -> 0 | H45: =IF(Rankings!H50<=2,1,0) -> 0 | I45: =IF(Rankings!I50<=2,1,0) -> 0 | J45: =IF(Rankings!J50<=2,1,0) -> 0 | K45: =SUM(C45:J45) -> 2 | L45: =SUMPRODUCT(C45:J45,Returns!B49:I49)/K45 -> -0.10587565 | M45: 0 | N45: 0 | O45: =L45+M45+N45 -> -0.10587565 | P45: =P44*(1+O45) -> 1.2018729 | Q45: =MAX($P$5:P45) -> 1.7685342 | R45: =P45/Q45-1 -> -0.32041295 | S45: =O45-Benchmark_RF!D45 -> -0.114076
A46: 49 | B46: =Returns!A50 -> 43466 | C46: =IF(Rankings!C50<=2,1,0) -> 1 | D46: =IF(Rankings!D50<=2,1,0) -> 1 | E46: =IF(Rankings!E50<=2,1,0) -> 0 | F46: =IF(Rankings!F50<=2,1,0) -> 0 | G46: =IF(Rankings!G50<=2,1,0) -> 0 | H46: =IF(Rankings!H50<=2,1,0) -> 0 | I46: =IF(Rankings!I50<=2,1,0) -> 0 | J46: =IF(Rankings!J50<=2,1,0) -> 0 | K46: =SUM(C46:J46) -> 2 | L46: =SUMPRODUCT(C46:J46,Returns!B50:I50)/K46 -> 0.089370667 | M46: 0 | N46: 0 | O46: =L46+M46+N46 -> 0.089370667 | P46: =P45*(1+O46) -> 1.3092851 | Q46: =MAX($P$5:P46) -> 1.7685342 | R46: =P46/Q46-1 -> -0.2596778 | S46: =O46-Benchmark_RF!D46 -> 0.081166966
A47: 50 | B47: =Returns!A51 -> 43497 | C47: =IF(Rankings!C53<=2,1,0) -> 1 | D47: =IF(Rankings!D53<=2,1,0) -> 0 | E47: =IF(Rankings!E53<=2,1,0) -> 0 | F47: =IF(Rankings!F53<=2,1,0) -> 0 | G47: =IF(Rankings!G53<=2,1,0) -> 1 | H47: =IF(Rankings!H53<=2,1,0) -> 0 | I47: =IF(Rankings!I53<=2,1,0) -> 0 | J47: =IF(Rankings!J53<=2,1,0) -> 0 | K47: =SUM(C47:J47) -> 2 | L47: =SUMPRODUCT(C47:J47,Returns!B51:I51)/K47 -> -0.0058530812 | M47: =-2*Assumptions!$B$13 -> -0.007 | N47: =-Assumptions!$B$16*MAX(0,(1+O44)*(1+O45)*(1+O46)-1) -> 0 | O47: =L47+M47+N47 -> -0.012853081 | P47: =P46*(1+O47) -> 1.2924568 | Q47: =MAX($P$5:P47) -> 1.7685342 | R47: =P47/Q47-1 -> -0.26919322 | S47: =O47-Benchmark_RF!D47 -> -0.021246099
A48: 51 | B48: =Returns!A52 -> 43525 | C48: =IF(Rankings!C53<=2,1,0) -> 1 | D48: =IF(Rankings!D53<=2,1,0) -> 0 | E48: =IF(Rankings!E53<=2,1,0) -> 0 | F48: =IF(Rankings!F53<=2,1,0) -> 0 | G48: =IF(Rankings!G53<=2,1,0) -> 1 | H48: =IF(Rankings!H53<=2,1,0) -> 0 | I48: =IF(Rankings!I53<=2,1,0) -> 0 | J48: =IF(Rankings!J53<=2,1,0) -> 0 | K48: =SUM(C48:J48) -> 2 | L48: =SUMPRODUCT(C48:J48,Returns!B52:I52)/K48 -> -0.047397777 | M48: 0 | N48: 0 | O48: =L48+M48+N48 -> -0.047397777 | P48: =P47*(1+O48) -> 1.2311972 | Q48: =MAX($P$5:P48) -> 1.7685342 | R48: =P48/Q48-1 -> -0.30383184 | S48: =O48-Benchmark_RF!D48 -> -0.055785474
A49: 52 | B49: =Returns!A53 -> 43556 | C49: =IF(Rankings!C53<=2,1,0) -> 1 | D49: =IF(Rankings!D53<=2,1,0) -> 0 | E49: =IF(Rankings!E53<=2,1,0) -> 0 | F49: =IF(Rankings!F53<=2,1,0) -> 0 | G49: =IF(Rankings!G53<=2,1,0) -> 1 | H49: =IF(Rankings!H53<=2,1,0) -> 0 | I49: =IF(Rankings!I53<=2,1,0) -> 0 | J49: =IF(Rankings!J53<=2,1,0) -> 0 | K49: =SUM(C49:J49) -> 2 | L49: =SUMPRODUCT(C49:J49,Returns!B53:I53)/K49 -> -0.074289725 | M49: 0 | N49: 0 | O49: =L49+M49+N49 -> -0.074289725 | P49: =P48*(1+O49) -> 1.1397319 | Q49: =MAX($P$5:P49) -> 1.7685342 | R49: =P49/Q49-1 -> -0.35554998 | S49: =O49-Benchmark_RF!D49 -> -0.082986673
A50: 53 | B50: =Returns!A54 -> 43586 | C50: =IF(Rankings!C56<=2,1,0) -> 0 | D50: =IF(Rankings!D56<=2,1,0) -> 0 | E50: =IF(Rankings!E56<=2,1,0) -> 1 | F50: =IF(Rankings!F56<=2,1,0) -> 0 | G50: =IF(Rankings!G56<=2,1,0) -> 1 | H50: =IF(Rankings!H56<=2,1,0) -> 0 | I50: =IF(Rankings!I56<=2,1,0) -> 0 | J50: =IF(Rankings!J56<=2,1,0) -> 0 | K50: =SUM(C50:J50) -> 2 | L50: =SUMPRODUCT(C50:J50,Returns!B54:I54)/K50 -> 0.046305564 | M50: =-2*Assumptions!$B$13 -> -0.007 | N50: =-Assumptions!$B$16*MAX(0,(1+O47)*(1+O48)*(1+O49)-1) -> 0 | O50: =L50+M50+N50 -> 0.039305564 | P50: =P49*(1+O50) -> 1.1845297 | Q50: =MAX($P$5:P50) -> 1.7685342 | R50: =P50/Q50-1 -> -0.33021951 | S50: =O50-Benchmark_RF!D50 -> 0.029386121
A51: 54 | B51: =Returns!A55 -> 43617 | C51: =IF(Rankings!C56<=2,1,0) -> 0 | D51: =IF(Rankings!D56<=2,1,0) -> 0 | E51: =IF(Rankings!E56<=2,1,0) -> 1 | F51: =IF(Rankings!F56<=2,1,0) -> 0 | G51: =IF(Rankings!G56<=2,1,0) -> 1 | H51: =IF(Rankings!H56<=2,1,0) -> 0 | I51: =IF(Rankings!I56<=2,1,0) -> 0 | J51: =IF(Rankings!J56<=2,1,0) -> 0 | K51: =SUM(C51:J51) -> 2 | L51: =SUMPRODUCT(C51:J51,Returns!B55:I55)/K51 -> -0.09325852 | M51: 0 | N51: 0 | O51: =L51+M51+N51 -> -0.09325852 | P51: =P50*(1+O51) -> 1.0740622 | Q51: =MAX($P$5:P51) -> 1.7685342 | R51: =P51/Q51-1 -> -0.39268225 | S51: =O51-Benchmark_RF!D51 -> -0.10330004
A52: 55 | B52: =Returns!A56 -> 43647 | C52: =IF(Rankings!C56<=2,1,0) -> 0 | D52: =IF(Rankings!D56<=2,1,0) -> 0 | E52: =IF(Rankings!E56<=2,1,0) -> 1 | F52: =IF(Rankings!F56<=2,1,0) -> 0 | G52: =IF(Rankings!G56<=2,1,0) -> 1 | H52: =IF(Rankings!H56<=2,1,0) -> 0 | I52: =IF(Rankings!I56<=2,1,0) -> 0 | J52: =IF(Rankings!J56<=2,1,0) -> 0 | K52: =SUM(C52:J52) -> 2 | L52: =SUMPRODUCT(C52:J52,Returns!B56:I56)/K52 -> 0.0053635415 | M52: 0 | N52: 0 | O52: =L52+M52+N52 -> 0.0053635415 | P52: =P51*(1+O52) -> 1.079823 | Q52: =MAX($P$5:P52) -> 1.7685342 | R52: =P52/Q52-1 -> -0.38942487 | S52: =O52-Benchmark_RF!D52 -> -0.0054271853
A53: 56 | B53: =Returns!A57 -> 43678 | C53: =IF(Rankings!C59<=2,1,0) -> 1 | D53: =IF(Rankings!D59<=2,1,0) -> 0 | E53: =IF(Rankings!E59<=2,1,0) -> 0 | F53: =IF(Rankings!F59<=2,1,0) -> 0 | G53: =IF(Rankings!G59<=2,1,0) -> 1 | H53: =IF(Rankings!H59<=2,1,0) -> 0 | I53: =IF(Rankings!I59<=2,1,0) -> 0 | J53: =IF(Rankings!J59<=2,1,0) -> 0 | K53: =SUM(C53:J53) -> 2 | L53: =SUMPRODUCT(C53:J53,Returns!B57:I57)/K53 -> -0.12575351 | M53: =-2*Assumptions!$B$13 -> -0.007 | N53: =-Assumptions!$B$16*MAX(0,(1+O50)*(1+O51)*(1+O52)-1) -> 0 | O53: =L53+M53+N53 -> -0.13275351 | P53: =P52*(1+O53) -> 0.93647269 | Q53: =MAX($P$5:P53) -> 1.7685342 | R53: =P53/Q53-1 -> -0.47048087 | S53: =O53-Benchmark_RF!D53 -> -0.14354668
A54: 57 | B54: =Returns!A58 -> 43709 | C54: =IF(Rankings!C59<=2,1,0) -> 1 | D54: =IF(Rankings!D59<=2,1,0) -> 0 | E54: =IF(Rankings!E59<=2,1,0) -> 0 | F54: =IF(Rankings!F59<=2,1,0) -> 0 | G54: =IF(Rankings!G59<=2,1,0) -> 1 | H54: =IF(Rankings!H59<=2,1,0) -> 0 | I54: =IF(Rankings!I59<=2,1,0) -> 0 | J54: =IF(Rankings!J59<=2,1,0) -> 0 | K54: =SUM(C54:J54) -> 2 | L54: =SUMPRODUCT(C54:J54,Returns!B58:I58)/K54 -> 0.081285585 | M54: 0 | N54: 0 | O54: =L54+M54+N54 -> 0.081285585 | P54: =P53*(1+O54) -> 1.0125944 | Q54: =MAX($P$5:P54) -> 1.7685342 | R54: =P54/Q54-1 -> -0.42743859 | S54: =O54-Benchmark_RF!D54 -> 0.070515447
A55: 58 | B55: =Returns!A59 -> 43739 | C55: =IF(Rankings!C59<=2,1,0) -> 1 | D55: =IF(Rankings!D59<=2,1,0) -> 0 | E55: =IF(Rankings!E59<=2,1,0) -> 0 | F55: =IF(Rankings!F59<=2,1,0) -> 0 | G55: =IF(Rankings!G59<=2,1,0) -> 1 | H55: =IF(Rankings!H59<=2,1,0) -> 0 | I55: =IF(Rankings!I59<=2,1,0) -> 0 | J55: =IF(Rankings!J59<=2,1,0) -> 0 | K55: =SUM(C55:J55) -> 2 | L55: =SUMPRODUCT(C55:J55,Returns!B59:I59)/K55 -> 0.03024912 | M55: 0 | N55: 0 | O55: =L55+M55+N55 -> 0.03024912 | P55: =P54*(1+O55) -> 1.0432245 | Q55: =MAX($P$5:P55) -> 1.7685342 | R55: =P55/Q55-1 -> -0.41011911 | S55: =O55-Benchmark_RF!D55 -> 0.019825913
A56: 59 | B56: =Returns!A60 -> 43770 | C56: =IF(Rankings!C62<=2,1,0) -> 0 | D56: =IF(Rankings!D62<=2,1,0) -> 1 | E56: =IF(Rankings!E62<=2,1,0) -> 0 | F56: =IF(Rankings!F62<=2,1,0) -> 0 | G56: =IF(Rankings!G62<=2,1,0) -> 0 | H56: =IF(Rankings!H62<=2,1,0) -> 0 | I56: =IF(Rankings!I62<=2,1,0) -> 1 | J56: =IF(Rankings!J62<=2,1,0) -> 0 | K56: =SUM(C56:J56) -> 2 | L56: =SUMPRODUCT(C56:J56,Returns!B60:I60)/K56 -> 0.057795219 | M56: =-2*Assumptions!$B$13 -> -0.007 | N56: =-Assumptions!$B$16*MAX(0,(1+O53)*(1+O54)*(1+O55)-1) -> 0 | O56: =L56+M56+N56 -> 0.050795219 | P56: =P55*(1+O56) -> 1.0962153 | Q56: =MAX($P$5:P56) -> 1.7685342 | R56: =P56/Q56-1 -> -0.38015598 | S56: =O56-Benchmark_RF!D56 -> 0.040215713
A57: 60 | B57: =Returns!A61 -> 43800 | C57: =IF(Rankings!C62<=2,1,0) -> 0 | D57: =IF(Rankings!D62<=2,1,0) -> 1 | E57: =IF(Rankings!E62<=2,1,0) -> 0 | F57: =IF(Rankings!F62<=2,1,0) -> 0 | G57: =IF(Rankings!G62<=2,1,0) -> 0 | H57: =IF(Rankings!H62<=2,1,0) -> 0 | I57: =IF(Rankings!I62<=2,1,0) -> 1 | J57: =IF(Rankings!J62<=2,1,0) -> 0 | K57: =SUM(C57:J57) -> 2 | L57: =SUMPRODUCT(C57:J57,Returns!B61:I61)/K57 -> 0.14342593 | M57: 0 | N57: 0 | O57: =L57+M57+N57 -> 0.14342593 | P57: =P56*(1+O57) -> 1.253441 | Q57: =MAX($P$5:P57) -> 1.7685342 | R57: =P57/Q57-1 -> -0.29125428 | S57: =O57-Benchmark_RF!D57 -> 0.13285726
A58: 61 | B58: =Returns!A62 -> 43831 | C58: =IF(Rankings!C62<=2,1,0) -> 0 | D58: =IF(Rankings!D62<=2,1,0) -> 1 | E58: =IF(Rankings!E62<=2,1,0) -> 0 | F58: =IF(Rankings!F62<=2,1,0) -> 0 | G58: =IF(Rankings!G62<=2,1,0) -> 0 | H58: =IF(Rankings!H62<=2,1,0) -> 0 | I58: =IF(Rankings!I62<=2,1,0) -> 1 | J58: =IF(Rankings!J62<=2,1,0) -> 0 | K58: =SUM(C58:J58) -> 2 | L58: =SUMPRODUCT(C58:J58,Returns!B62:I62)/K58 -> 0.035710907 | M58: 0 | N58: 0 | O58: =L58+M58+N58 -> 0.035710907 | P58: =P57*(1+O58) -> 1.2982025 | Q58: =MAX($P$5:P58) -> 1.7685342 | R58: =P58/Q58-1 -> -0.26594433 | S58: =O58-Benchmark_RF!D58 -> 0.025185081
A59: 62 | B59: =Returns!A63 -> 43862 | C59: =IF(Rankings!C65<=2,1,0) -> 0 | D59: =IF(Rankings!D65<=2,1,0) -> 0 | E59: =IF(Rankings!E65<=2,1,0) -> 0 | F59: =IF(Rankings!F65<=2,1,0) -> 0 | G59: =IF(Rankings!G65<=2,1,0) -> 0 | H59: =IF(Rankings!H65<=2,1,0) -> 0 | I59: =IF(Rankings!I65<=2,1,0) -> 1 | J59: =IF(Rankings!J65<=2,1,0) -> 1 | K59: =SUM(C59:J59) -> 2 | L59: =SUMPRODUCT(C59:J59,Returns!B63:I63)/K59 -> -0.010381829 | M59: =-2*Assumptions!$B$13 -> -0.007 | N59: =-Assumptions!$B$16*MAX(0,(1+O56)*(1+O57)*(1+O58)-1) -> -0.036662008 | O59: =L59+M59+N59 -> -0.054043837 | P59: =P58*(1+O59) -> 1.2280427 | Q59: =MAX($P$5:P59) -> 1.7685342 | R59: =P59/Q59-1 -> -0.30561551 | S59: =O59-Benchmark_RF!D59 -> -0.064564167
A60: 63 | B60: =Returns!A64 -> 43891 | C60: =IF(Rankings!C65<=2,1,0) -> 0 | D60: =IF(Rankings!D65<=2,1,0) -> 0 | E60: =IF(Rankings!E65<=2,1,0) -> 0 | F60: =IF(Rankings!F65<=2,1,0) -> 0 | G60: =IF(Rankings!G65<=2,1,0) -> 0 | H60: =IF(Rankings!H65<=2,1,0) -> 0 | I60: =IF(Rankings!I65<=2,1,0) -> 1 | J60: =IF(Rankings!J65<=2,1,0) -> 1 | K60: =SUM(C60:J60) -> 2 | L60: =SUMPRODUCT(C60:J60,Returns!B64:I64)/K60 -> -0.34875891 | M60: 0 | N60: 0 | O60: =L60+M60+N60 -> -0.34875891 | P60: =P59*(1+O60) -> 0.79975187 | Q60: =MAX($P$5:P60) -> 1.7685342 | R60: =P60/Q60-1 -> -0.54778829 | S60: =O60-Benchmark_RF!D60 -> -0.35765799
A61: 64 | B61: =Returns!A65 -> 43922 | C61: =IF(Rankings!C65<=2,1,0) -> 0 | D61: =IF(Rankings!D65<=2,1,0) -> 0 | E61: =IF(Rankings!E65<=2,1,0) -> 0 | F61: =IF(Rankings!F65<=2,1,0) -> 0 | G61: =IF(Rankings!G65<=2,1,0) -> 0 | H61: =IF(Rankings!H65<=2,1,0) -> 0 | I61: =IF(Rankings!I65<=2,1,0) -> 1 | J61: =IF(Rankings!J65<=2,1,0) -> 1 | K61: =SUM(C61:J61) -> 2 | L61: =SUMPRODUCT(C61:J61,Returns!B65:I65)/K61 -> 0.074438786 | M61: 0 | N61: 0 | O61: =L61+M61+N61 -> 0.074438786 | P61: =P60*(1+O61) -> 0.85928443 | Q61: =MAX($P$5:P61) -> 1.7685342 | R61: =P61/Q61-1 -> -0.5141262 | S61: =O61-Benchmark_RF!D61 -> 0.06783872
A62: 65 | B62: =Returns!A66 -> 43952 | C62: =IF(Rankings!C68<=2,1,0) -> 0 | D62: =IF(Rankings!D68<=2,1,0) -> 0 | E62: =IF(Rankings!E68<=2,1,0) -> 0 | F62: =IF(Rankings!F68<=2,1,0) -> 1 | G62: =IF(Rankings!G68<=2,1,0) -> 1 | H62: =IF(Rankings!H68<=2,1,0) -> 0 | I62: =IF(Rankings!I68<=2,1,0) -> 0 | J62: =IF(Rankings!J68<=2,1,0) -> 0 | K62: =SUM(C62:J62) -> 2 | L62: =SUMPRODUCT(C62:J62,Returns!B66:I66)/K62 -> -0.049506773 | M62: =-2*Assumptions!$B$13 -> -0.007 | N62: =-Assumptions!$B$16*MAX(0,(1+O59)*(1+O60)*(1+O61)-1) -> 0 | O62: =L62+M62+N62 -> -0.056506773 | P62: =P61*(1+O62) -> 0.81072903 | Q62: =MAX($P$5:P62) -> 1.7685342 | R62: =P62/Q62-1 -> -0.54158136 | S62: =O62-Benchmark_RF!D62 -> -0.063034487
A63: 66 | B63: =Returns!A67 -> 43983 | C63: =IF(Rankings!C68<=2,1,0) -> 0 | D63: =IF(Rankings!D68<=2,1,0) -> 0 | E63: =IF(Rankings!E68<=2,1,0) -> 0 | F63: =IF(Rankings!F68<=2,1,0) -> 1 | G63: =IF(Rankings!G68<=2,1,0) -> 1 | H63: =IF(Rankings!H68<=2,1,0) -> 0 | I63: =IF(Rankings!I68<=2,1,0) -> 0 | J63: =IF(Rankings!J68<=2,1,0) -> 0 | K63: =SUM(C63:J63) -> 2 | L63: =SUMPRODUCT(C63:J63,Returns!B67:I67)/K63 -> 0.040139028 | M63: 0 | N63: 0 | O63: =L63+M63+N63 -> 0.040139028 | P63: =P62*(1+O63) -> 0.84327091 | Q63: =MAX($P$5:P63) -> 1.7685342 | R63: =P63/Q63-1 -> -0.52318088 | S63: =O63-Benchmark_RF!D63 -> 0.034603382
A64: 67 | B64: =Returns!A68 -> 44013 | C64: =IF(Rankings!C68<=2,1,0) -> 0 | D64: =IF(Rankings!D68<=2,1,0) -> 0 | E64: =IF(Rankings!E68<=2,1,0) -> 0 | F64: =IF(Rankings!F68<=2,1,0) -> 1 | G64: =IF(Rankings!G68<=2,1,0) -> 1 | H64: =IF(Rankings!H68<=2,1,0) -> 0 | I64: =IF(Rankings!I68<=2,1,0) -> 0 | J64: =IF(Rankings!J68<=2,1,0) -> 0 | K64: =SUM(C64:J64) -> 2 | L64: =SUMPRODUCT(C64:J64,Returns!B68:I68)/K64 -> 0.17940292 | M64: 0 | N64: 0 | O64: =L64+M64+N64 -> 0.17940292 | P64: =P63*(1+O64) -> 0.99455618 | Q64: =MAX($P$5:P64) -> 1.7685342 | R64: =P64/Q64-1 -> -0.43763814 | S64: =O64-Benchmark_RF!D64 -> 0.17384799
A65: 68 | B65: =Returns!A69 -> 44044 | C65: =IF(Rankings!C71<=2,1,0) -> 0 | D65: =IF(Rankings!D71<=2,1,0) -> 0 | E65: =IF(Rankings!E71<=2,1,0) -> 0 | F65: =IF(Rankings!F71<=2,1,0) -> 1 | G65: =IF(Rankings!G71<=2,1,0) -> 1 | H65: =IF(Rankings!H71<=2,1,0) -> 0 | I65: =IF(Rankings!I71<=2,1,0) -> 0 | J65: =IF(Rankings!J71<=2,1,0) -> 0 | K65: =SUM(C65:J65) -> 2 | L65: =SUMPRODUCT(C65:J65,Returns!B69:I69)/K65 -> 0.0091443175 | M65: =-2*Assumptions!$B$13 -> -0.007 | N65: =-Assumptions!$B$16*MAX(0,(1+O62)*(1+O63)*(1+O64)-1) -> -0.023613558 | O65: =L65+M65+N65 -> -0.021469241 | P65: =P64*(1+O65) -> 0.97320381 | Q65: =MAX($P$5:P65) -> 1.7685342 | R65: =P65/Q65-1 -> -0.44971162 | S65: =O65-Benchmark_RF!D65 -> -0.027195101
A66: 69 | B66: =Returns!A70 -> 44075 | C66: =IF(Rankings!C71<=2,1,0) -> 0 | D66: =IF(Rankings!D71<=2,1,0) -> 0 | E66: =IF(Rankings!E71<=2,1,0) -> 0 | F66: =IF(Rankings!F71<=2,1,0) -> 1 | G66: =IF(Rankings!G71<=2,1,0) -> 1 | H66: =IF(Rankings!H71<=2,1,0) -> 0 | I66: =IF(Rankings!I71<=2,1,0) -> 0 | J66: =IF(Rankings!J71<=2,1,0) -> 0 | K66: =SUM(C66:J66) -> 2 | L66: =SUMPRODUCT(C66:J66,Returns!B70:I70)/K66 -> 0.036518222 | M66: 0 | N66: 0 | O66: =L66+M66+N66 -> 0.036518222 | P66: =P65*(1+O66) -> 1.0087435 | Q66: =MAX($P$5:P66) -> 1.7685342 | R66: =P66/Q66-1 -> -0.42961607 | S66: =O66-Benchmark_RF!D66 -> 0.030787119
A67: 70 | B67: =Returns!A71 -> 44105 | C67: =IF(Rankings!C71<=2,1,0) -> 0 | D67: =IF(Rankings!D71<=2,1,0) -> 0 | E67: =IF(Rankings!E71<=2,1,0) -> 0 | F67: =IF(Rankings!F71<=2,1,0) -> 1 | G67: =IF(Rankings!G71<=2,1,0) -> 1 | H67: =IF(Rankings!H71<=2,1,0) -> 0 | I67: =IF(Rankings!I71<=2,1,0) -> 0 | J67: =IF(Rankings!J71<=2,1,0) -> 0 | K67: =SUM(C67:J67) -> 2 | L67: =SUMPRODUCT(C67:J67,Returns!B71:I71)/K67 -> -0.0051337602 | M67: 0 | N67: 0 | O67: =L67+M67+N67 -> -0.0051337602 | P67: =P66*(1+O67) -> 1.0035648 | Q67: =MAX($P$5:P67) -> 1.7685342 | R67: =P67/Q67-1 -> -0.43254428 | S67: =O67-Benchmark_RF!D67 -> -0.010911571
